Workbook
Name 安规: 数据源!$L$2:$L$24
Name 包装: 数据源!$H$2:$H$24
Name 不涉及: 数据源!$AL$2
Name 否: 数据源!$AK$2:$AK$12
Name 功能: 数据源!$K$2:$K$24
Name 计划采购部: 数据源!$AC$2:$AC$6
Name 技术质量部: 数据源!$AD$2:$AD$6
Name 内部: 数据源!$J$2:$J$24
Name 其它: 数据源!$N$2:$N$24
Name 试产: 数据源!$E$2:$E$6
Name 是: 数据源!$AJ$2:$AJ$7
Name 外观: 数据源!$I$2:$I$24
Name 宜胜照明1: 数据源!$Z$2:$Z$6
Name 宜胜照明2: 数据源!$AA$2:$AA$6
Name 宜胜照明3: 数据源!$AB$2:$AB$6

Sheet 宜胜客诉台账
A1: 发生时间 | B1: 年 | C1: 月 | D1: 周 | E1: 订单号 | F1: 产品型号 | G1: 客户 | H1: 事业部 | I1: 业务 | J1: 产品 | K1: CQE | L1: 问题描述 | M1: 订单数量 | N1: 客诉数量 | O1: 不良占比 | P1: 问题来源 | Q1: 问题类别 | R1: 原因分析 | S1: 原因类别 | T1: 临时措施 | U1: 长期措施 | V1: 是否根本解 | W1: 措施类型 | X1: 责任部门 | Y1: 二级部门3 | Z1: 计划完成时间 | AA1: 实际完成时间 | AB1: 状态 | AC1: 跟进人 | AD1: 计划完成年 | AE1: 计划完成月 | AF1: 计划完成周
A2: 45469 | B2: =IF(A2="","",YEAR(A2)) -> 2024 | C2: =IF(A2="","",TEXT(A2,"m")) -> 6 | D2: =IF(A2="","","W"&WEEKNUM(A2,2)) -> W26 | E2: Y23P1108 | F2: AL5005-9W | G2: 澳大利亚1541 | H2: 宜胜照明2 | I2: 徐碧琳 | J2: 彭弼坤 | K2: 吴军 | L2: 测试点亮过程中，灯不亮，通电1分钟左右冒烟 | O2: =IFERROR(N2/M2,"") | P2: 售后客诉 | Q2: 功能 | R2: 1.通过客户提供信息，进行失效模式复现，当灯板端子脱焊松动通电后，1分20秒左右产品冒浓烟，功率升高至10-25W，2分40秒后烟雾逐渐消失，3分钟后所有现象消失；检查灯板，电容尾部有鼓包、发黑现象，电容下方有漏液，其他无异常；与客户提供视频及图片完全一致； 2.抽取5PCS灯板进行焊点拉力测试，测试结果均≥40N,远远高一般标准≥10N,排除产品批量焊接不良可能性； 3.经过以上排查分析，此次问题是由于灯板端子虚焊松动，导致上电空载，电容电解液分解产生浓烟，完全分解后浓烟消失，电路断开，排除后续可能造成失火现象等不良影响，且筒灯壳体为阻燃材质； 4.端子虚焊流出原因： ①维修品未经老化测试流入包装； ②PCB及元器件受潮； ③印刷锡膏开盖后未及时使用完毕； ④印刷钢网未及时清洗； | S2: 电子设计 | T2: 1.排查现有库存以及订单情况，现有客户订单Y24P0507-1，订单量20000PCS； 2.暂停生产，待排查处理结果； 3.根据客户提供信息，进行失效模式复现； | U2: 1.不良品红色标贴标识，维修品分批统一老化测试; 2.SMT车间温湿度接近管控范围增加预警机制; 3.锡膏使用采取先进先出，保证开盖锡膏24小时内使用完; 4.换线停线超过1小时按工艺要求清洁钢网 | V2: 否 | W2: 工艺优化 | X2: 宜胜照明2 | Y2: 生产二 | Z2: 45469 | AA2: 45469 | AB2: =IF(A2="","",_xlfn.IFS(AND(Z2=0,AA2=0),"未回复",AND(AA2<>0,Z2=0),"报错",AND(Z2>=NOW(),Z2<>0,AA2=0),"正常进行中",AND(AA2<>0,Z2>=AA2),"按时关闭",AND(Z2<>0,Z2<=AA2),"延期关闭",AND(AA2=0,Z2<NOW()),"延期未关闭")) -> 按时关闭 | AC2: 赵纯杰 | AD2: =IF(Z2="","",YEAR(Z2)) -> 2024 | AE2: =IF(Z2="","",TEXT(Z2,"m")) -> 6 | AF2: =IF(Z2="","","W"&WEEKNUM(Z2,2)) -> W26
A3: 45446 | B3: =IF(A3="","",YEAR(A3)) -> 2024 | C3: =IF(A3="","",TEXT(A3,"m")) -> 6 | D3: =IF(A3="","","W"&WEEKNUM(A3,2)) -> W23 | E3: D24A003 | F3: LC1201C-7W2-G7-低漏光 | G3: 捷克081 | H3: 宜胜照明1 | I3: 金凤燕 | J3: 谢彭沛 | K3: 李宁 | L3: 4000K的漏光严重（见附件），客户索赔金额276美金。 | O3: =IFERROR(N3/M3,"") | P3: 售后客诉 | Q3: 外观 | R3: 事情缘由：客户下单产品为低漏光版本，壳体为老模具库存消耗完后，壳体涉及停产，剩下2000数量，需验证壳体才能做大货，壳体验证时有进行照片拍摄，漏光效果不明显，就通知进行安排做货，验证方案时效果如下 问题暴漏：验证时验证效果不充分，壳体涉及停产未及时进行产品替代。 后续处理：1.充分验证壳体漏光效果，寻找替代壳体。2：涉及停产及时进行替代。3：需找到壳体给客户重新寄样进行确认。 补充：此订单下单日期为20240112，刚实行报价制度阶段，业务已进行利润给到工业端，按照当时下单流程节点，此订单业务所加的利润在宜胜端口 后面收到客诉通知再次进行验证，发现确实存在漏光，再次测试效果如下 | S3: 来料不良 | T3: 这个订单要求低漏光的壳体材料，原材料工厂有4000个，宇兴先用这批做了3000只3000K和1000只4000K。 因为原材料工厂后面不做这个低漏光的壳体了，后面的2000个壳体找了另一家新工厂做的。 产品端针对新供方物料有打样确认验证过，但未发现有漏光问题。 核对当时的留样，发现该产品只有在暗光处、位置较低处，漏光才会较为明显，对比客户反馈的图片，问题一致。 结论： 产品经理在更换新供方之后，有打样验证的动作，但未跟客户进行确认。导致双方判定标准有差异 | U3: 后续类似情况，需与客户端做确认，保证标准理解一致 | V3: 否 | W3: 纠错 | X3: 宜胜照明1 | Y3: 研发六 | Z3: 45455 | AA3: 45455 | AB3: =IF(A3="","",_xlfn.IFS(AND(Z3=0,AA3=0),"未回复",AND(AA3<>0,Z3=0),"报错",AND(Z3>=NOW(),Z3<>0,AA3=0),"正常进行中",AND(AA3<>0,Z3>=AA3),"按时关闭",AND(Z3<>0,Z3<=AA3),"延期关闭",AND(AA3=0,Z3<NOW()),"延期未关闭")) -> 按时关闭 | AC3: 杨高照 | AD3: =IF(Z3="","",YEAR(Z3)) -> 2024 | AE3: =IF(Z3="","",TEXT(Z3,"m")) -> 6 | AF3: =IF(Z3="","","W"&WEEKNUM(Z3,2)) -> W24
A4: 45447 | B4: =IF(A4="","",YEAR(A4)) -> 2024 | C4: =IF(A4="","",TEXT(A4,"m")) -> 6 | D4: =IF(A4="","","W"&WEEKNUM(A4,2)) -> W23 | L4: 投光灯进水 | O4: =IFERROR(N4/M4,"") | P4: 售后客诉 | Q4: 功能 | S4: 其它 | V4: 是 | W4: 其它 | X4: 宜胜照明3 | Z4: 45447 | AA4: 45447 | AB4: =IF(A4="","",_xlfn.IFS(AND(Z4=0,AA4=0),"未回复",AND(AA4<>0,Z4=0),"报错",AND(Z4>=NOW(),Z4<>0,AA4=0),"正常进行中",AND(AA4<>0,Z4>=AA4),"按时关闭",AND(Z4<>0,Z4<=AA4),"延期关闭",AND(AA4=0,Z4<NOW()),"延期未关闭")) -> 按时关闭 | AC4: 杨高照 | AD4: =IF(Z4="","",YEAR(Z4)) -> 2024 | AE4: =IF(Z4="","",TEXT(Z4,"m")) -> 6 | AF4: =IF(Z4="","","W"&WEEKNUM(Z4,2)) -> W23
A5: 45488 | B5: =IF(A5="","",YEAR(A5)) -> 2024 | C5: =IF(A5="","",TEXT(A5,"m")) -> 7 | D5: =IF(A5="","","W"&WEEKNUM(A5,2)) -> W29 | L5: 收到客户反馈，订单：A123S233 65WT灯灯杯摇晃内部有一些异响，有一些摇晃没有异响（正常品为没有异响），经分析PCB板和灯杯卡槽之间有的没有点胶。有的胶量点少了，导致PCB板脱落，故T灯出现摇晃异响现象； | O5: =IFERROR(N5/M5,"") | P5: 售后客诉 | Q5: 内部 | R5: 1、产生原因： 生产过程中，先点胶再卡PCB板，有个别灯杯卡槽在没有点胶的情况下，插上了控制板，还有个别灯杯卡槽位置胶量点少了，也插上控制板了。 2、流出原因： 由于该型号产品是半自动产线生产的，外观检查时会通过“来回晃动听声音”的方式来判断灯体内部是否固定好控制板，因为板子插在卡槽内，部分没有听出响动，判断合格，初步分析为工人在中午下班时间，有个别产品在半自动线上，未完成作业，上班时，打胶后产品胶干了导致不良品流出。 | S5: 过程工艺 | T5: 1.库存排查：瑞亚仓库数量3000PCS，将仓库货物进行返工。开箱进行摇晃后在点亮测试，3000台未发现不良品。 | U5: 1.更改作业流程，先卡PCB板，在点胶，确保每个灯杯的卡槽内有足够的胶量。 生产工单，备注点胶作业。 2.SOP增加工位检查点胶作业流程。 1.车间生产前给员工培训，按SOP流程作业，下班前5分钟清空生产线未完成半成品。 2.品质巡检过程中检查该工序，生产是否落实下去。下班前清空生产线半成品。 | V5: 否 | W5: 工艺优化 | X5: 宜胜照明1 | Y5: 研发六 | Z5: 45496 | AA5: 45496 | AB5: =IF(A5="","",_xlfn.IFS(AND(Z5=0,AA5=0),"未回复",AND(AA5<>0,Z5=0),"报错",AND(Z5>=NOW(),Z5<>0,AA5=0),"正常进行中",AND(AA5<>0,Z5>=AA5),"按时关闭",AND(Z5<>0,Z5<=AA5),"延期关闭",AND(AA5=0,Z5<NOW()),"延期未关闭")) -> 按时关闭 | AC5: 李俊林 | AD5: =IF(Z5="","",YEAR(Z5)) -> 2024 | AE5: =IF(Z5="","",TEXT(Z5,"m")) -> 7 | AF5: =IF(Z5="","","W"&WEEKNUM(Z5,2)) -> W30
A6: 45477 | B6: =IF(A6="","",YEAR(A6)) -> 2024 | C6: =IF(A6="","",TEXT(A6,"m")) -> 7 | D6: =IF(A6="","","W"&WEEKNUM(A6,2)) -> W27 | L6: 瑞士070面板灯夹膜 | O6: =IFERROR(N6/M6,"") | P6: 售后客诉 | Q6: 内部 | S6: 人员作业 | V6: 是 | W6: 防呆防错 | X6: 宜胜照明2 | Z6: 45478 | AB6: =IF(A6="","",_xlfn.IFS(AND(Z6=0,AA6=0),"未回复",AND(AA6<>0,Z6=0),"报错",AND(Z6>=NOW(),Z6<>0,AA6=0),"正常进行中",AND(AA6<>0,Z6>=AA6),"按时关闭",AND(Z6<>0,Z6<=AA6),"延期关闭",AND(AA6=0,Z6<NOW()),"延期未关闭")) -> 延期未关闭 | AC6: 杨高照 | AD6: =IF(Z6="","",YEAR(Z6)) -> 2024 | AE6: =IF(Z6="","",TEXT(Z6,"m")) -> 7 | AF6: =IF(Z6="","","W"&WEEKNUM(Z6,2)) -> W27
A7: 45467 | B7: =IF(A7="","",YEAR(A7)) -> 2024 | C7: =IF(A7="","",TEXT(A7,"m")) -> 6 | D7: =IF(A7="","","W"&WEEKNUM(A7,2)) -> W26 | E7: Y24D0307 | F7: AL2017 | G7: 菲律宾1579-1 | H7: 宜胜照明2 | J7: 彭弼坤 | K7: 周利军 | L7: 扭簧护套掉色 | O7: =IFERROR(N7/M7,"") | P7: 售后客诉 | Q7: 外观 | R7: PVC材质，蓝色护套与绿色护套高温高湿验证，绿色护套脱色现象 | S7: 结构设计 | V7: 否 | AB7: =IF(A7="","",_xlfn.IFS(AND(Z7=0,AA7=0),"未回复",AND(AA7<>0,Z7=0),"报错",AND(Z7>=NOW(),Z7<>0,AA7=0),"正常进行中",AND(AA7<>0,Z7>=AA7),"按时关闭",AND(Z7<>0,Z7<=AA7),"延期关闭",AND(AA7=0,Z7<NOW()),"延期未关闭")) -> 未回复 | AC7: 赵纯杰 | AD7: =IF(Z7="","",YEAR(Z7)) | AE7: =IF(Z7="","",TEXT(Z7,"m")) | AF7: =IF(Z7="","","W"&WEEKNUM(Z7,2))
A8: 45471 | B8: =IF(A8="","",YEAR(A8)) -> 2024 | C8: =IF(A8="","",TEXT(A8,"m")) -> 6 | D8: =IF(A8="","","W"&WEEKNUM(A8,2)) -> W26 | E8: R24D0207 | F8: LB1163E1-9W2/LB211-8W | L8: LB1163E1-9W2漏装1箱 LB211-8W漏装30箱 | O8: =IFERROR(N8/M8,"") | P8: 售后客诉 | Q8: 其它 | S8: 人员作业 | V8: 否 | W8: 纠错 | AB8: =IF(A8="","",_xlfn.IFS(AND(Z8=0,AA8=0),"未回复",AND(AA8<>0,Z8=0),"报错",AND(Z8>=NOW(),Z8<>0,AA8=0),"正常进行中",AND(AA8<>0,Z8>=AA8),"按时关闭",AND(Z8<>0,Z8<=AA8),"延期关闭",AND(AA8=0,Z8<NOW()),"延期未关闭")) -> 未回复 | AC8: 杨高照 | AD8: =IF(Z8="","",YEAR(Z8)) | AE8: =IF(Z8="","",TEXT(Z8,"m")) | AF8: =IF(Z8="","","W"&WEEKNUM(Z8,2))
A9: 45496 | B9: =IF(A9="","",YEAR(A9)) -> 2024 | C9: =IF(A9="","",TEXT(A9,"m")) -> 7 | D9: =IF(A9="","","W"&WEEKNUM(A9,2)) -> W30 | E9: M24L009-1 | F9: HL132 | G9: 巴西724 | H9: 宜胜照明3 | J9: 邱奇 | K9: 丁亚双 | L9: 混装1箱其他客户产品 | O9: =IFERROR(N9/M9,"") | P9: 售后客诉 | Q9: 其它 | R9: 混料 | S9: 人员作业 | T9: 库存全检返工 | U9: 1.备品配件损耗全部降低（已经执行）. 2.备品改为易损耗物料有备品不会是整套物料有备品（不会多做齐套产品）. 3.车间安排专人入库入库前数量核对入库后与仓管核对数量. 4.车间对班组长以及员工宣导培训. 5.针对同产品不同客户计划排产分开排产. 6.多生产产品车间统一放置与大货分开. | V9: 否 | W9: 纠错 | X9: 宜胜照明3 | Z9: 45498 | AA9: 45498 | AB9: =IF(A9="","",_xlfn.IFS(AND(Z9=0,AA9=0),"未回复",AND(AA9<>0,Z9=0),"报错",AND(Z9>=NOW(),Z9<>0,AA9=0),"正常进行中",AND(AA9<>0,Z9>=AA9),"按时关闭",AND(Z9<>0,Z9<=AA9),"延期关闭",AND(AA9=0,Z9<NOW()),"延期未关闭")) -> 按时关闭 | AC9: 赵纯杰 | AD9: =IF(Z9="","",YEAR(Z9)) -> 2024 | AE9: =IF(Z9="","",TEXT(Z9,"m")) -> 7 | AF9: =IF(Z9="","","W"&WEEKNUM(Z9,2)) -> W30
A10: 45499 | B10: =IF(A10="","",YEAR(A10)) -> 2024 | C10: =IF(A10="","",TEXT(A10,"m")) -> 7 | D10: =IF(A10="","","W"&WEEKNUM(A10,2)) -> W30 | E10: Z23T013 | F10: LG158-50W-W-G3 | G10: 埃及442 | H10: 宜胜照明3 | J10: 陈中平协助 | K10: 李冬雪 | L10: 客户反馈产品组装后测试点亮1个小时内出现闪灯与不亮 | O10: =IFERROR(N10/M10,"") | P10: 售后客诉 | Q10: 功能 | R10: 1. 发生原因： - 电源板 C4 电容贴错。BOM 要求为 22PF 的电容，实际为 220PF，造成空载电压 130，超过电解电容 100V 耐压，导致电容击穿。 2. 流出原因： - 整个生产批次均未执行有效的首件检验，料号、BOM信息未核对正确，导致错误未被及时发现（电容规格0805 220 50V误认为220PF电容，实际0805 220 50V是22PF电容。 - 本订单散件发货，客户组装，但大货生产时未进行成品组装老化及功能测试，未对成品的性能做管控 | S10: 人员作业 | T10: 重新生产一批电源板补发客户 | U10: 永久纠正措施：1. 对负责该生产批次的作业人员进行重新培训和考核，确保其熟练掌握正确的贴片操作和 BOM 核对流程，明确操作规范和质量要求，并定期考核。 2. 优化生产流程，在贴片环节前增加物料二次核对步骤，由专人负责； 3. 优化质量管控流程，完善首件检验制度，明确检验标准和责任人员，首件检验结果需记录并签字确认，合理增加关键部件的抽检比例和频率； 预防措施：1. 完善物料管理制度 - 建立严格的物料入库检验流程，对每一批次的物料进行规格、型号、参数等方面的抽检，确保物料符合要求。 - 优化物料存储环境，按照不同规格和型号分类存放，并做好明确标识。 2. 强化生产过程中的检验环节 - 制定详细的生产流程检验标准和操作指南，明确每个工序的检验项目和责任人。 3. 持续培训与教育 - 定期组织作业人员参加技能培训和质量意识教育活动，分享常见的质量问题案例及解决方法，提高员工的质量意识和操作技能。 4. 优化订单管理 - 对于散件发货的订单，在生产过程中增加模拟组装、老化及功能测试环节，确保产品性能符合要求后再发货。 5. 加强监督与审核 - 成立专门的质量监督小组，定期对生产过程和产品质量进行检查和审核，对不符合质量要求的行为进行及时纠正和处罚。 | V10: 是 | W10: 防呆防错 | X10: 宜胜照明3 | Z10: 45503 | AA10: 45503 | AB10: =IF(A10="","",_xlfn.IFS(AND(Z10=0,AA10=0),"未回复",AND(AA10<>0,Z10=0),"报错",AND(Z10>=NOW(),Z10<>0,AA10=0),"正常进行中",AND(AA10<>0,Z10>=AA10),"按时关闭",AND(Z10<>0,Z10<=AA10),"延期关闭",AND(AA10=0,Z10<NOW()),"延期未关闭")) -> 按时关闭 | AC10: 赵纯杰 | AD10: =IF(Z10="","",YEAR(Z10)) -> 2024 | AE10: =IF(Z10="","",TEXT(Z10,"m")) -> 7 | AF10: =IF(Z10="","","W"&WEEKNUM(Z10,2)) -> W31
A11: 45512 | B11: =IF(A11="","",YEAR(A11)) -> 2024 | C11: =IF(A11="","",TEXT(A11,"m")) -> 8 | D11: =IF(A11="","","W"&WEEKNUM(A11,2)) -> W32 | E11: P24V001-1 | F11: LG172L-30W2-俄罗斯482 | G11: 俄罗斯482 | H11: 宜胜照明3 | I11: 黄亚琳 | J11: 王燕赟 | K11: 周利军 | L11: 1.50W, 70W, 100W 掉功率 2. 所有产品电线不阻燃 客户索赔29034.72元（4021.43美元） | M11: 40988 | N11: 40988 | O11: =IFERROR(N11/M11,"") -> 1 | P11: 售后客诉 | Q11: 功能 | R11: 1.经分析本批次产品掉功率，锁定原因为导热硅脂导热系数不合格，要求1.5W/mk，实测1.2076W/mk 2.电源线不阻燃为设计原因，未使用阻燃材料 | S11: 来料不良 | T11: 1.本批次产品客户让步接收，后续继续跟进，如有异常及时提供技术支持和解决方案 2.立即启动对后续产品的预防措施，防止类似问题再次发生 | U11: 1.更换导热系数符合标准(1.5W/hk)的导热硅脂，加强原材料检验环节，确保导热硅脂质量 ； 2.电源线全部更换为阻燃材料，并建立严格的采购标准和检验流程； 3.完善检验规范，原检验标准“在额定电压条件下测试功率”更改为“在额定电压下持续运行20min，过程中LED光源功率应在标准值以内”； | V11: 是 | W11: 设计变更-预防 | X11: 宜胜照明3 | Y11: 研发一 | Z11: 45513 | AA11: 45513 | AB11: =IF(A11="","",_xlfn.IFS(AND(Z11=0,AA11=0),"未回复",AND(AA11<>0,Z11=0),"报错",AND(Z11>=NOW(),Z11<>0,AA11=0),"正常进行中",AND(AA11<>0,Z11>=AA11),"按时关闭",AND(Z11<>0,Z11<=AA11),"延期关闭",AND(AA11=0,Z11<NOW()),"延期未关闭")) -> 按时关闭 | AC11: 赵纯杰 | AD11: =IF(Z11="","",YEAR(Z11)) -> 2024 | AE11: =IF(Z11="","",TEXT(Z11,"m")) -> 8 | AF11: =IF(Z11="","","W"&WEEKNUM(Z11,2)) -> W32
A12: 45519 | B12: =IF(A12="","",YEAR(A12)) -> 2024 | C12: =IF(A12="","",TEXT(A12,"m")) -> 8 | D12: =IF(A12="","","W"&WEEKNUM(A12,2)) -> W33 | E12: T23S0620 （太阳能灯） | F12: F-WL106-10W | G12: 匈牙利087 | H12: 宜胜照明2 | I12: 陈晨怡 | J12: 周伟慧 | K12: 周利军 | L12: 8月初开始，客户陆续收到终端店铺的退货，主要问题在于灯头断裂，无法使用，目前没有可以维修的办法，只能报废处理。 8月7号开始，客户开始现有库存的全检工作。8月13号出全检结果，目前全检出来的不良数量200个。比例40% | M12: 504 | N12: 200 | O12: =IFERROR(N12/M12,"") -> 0.3968254 | P12: 售后客诉 | Q12: 功能 | R12: 1）螺丝打的比较紧，扭力大 2）运输过程中，横向收到冲击 | S12: 结构设计 | T12: 最终与客户沟通协商补货给他，本月畅想重新下单T24P037-1补货给客户，成本预计11536RMB | U12: 优化内部结构，中间连接处由直角改为圆角，使得进料更加连贯，同步增加塑料件的壁厚，使得连接处的受力面积增加，分散不同方向上的冲击力，让内部结构更加稳定；同时加厚了下方台阶（打螺丝的位置），对螺丝固定时起到更好的支撑 | V12: 是 | W12: 设计变更-预防 | X12: 其它事业部 | AB12: =IF(A12="","",_xlfn.IFS(AND(Z12=0,AA12=0),"未回复",AND(AA12<>0,Z12=0),"报错",AND(Z12>=NOW(),Z12<>0,AA12=0),"正常进行中",AND(AA12<>0,Z12>=AA12),"按时关闭",AND(Z12<>0,Z12<=AA12),"延期关闭",AND(AA12=0,Z12<NOW()),"延期未关闭")) -> 未回复 | AD12: =IF(Z12="","",YEAR(Z12)) | AE12: =IF(Z12="","",TEXT(Z12,"m")) | AF12: =IF(Z12="","","W"&WEEKNUM(Z12,2))
A13: 45519 | B13: =IF(A13="","",YEAR(A13)) -> 2024 | C13: =IF(A13="","",TEXT(A13,"m")) -> 8 | D13: =IF(A13="","","W"&WEEKNUM(A13,2)) -> W33 | E13: S21K008 | F13: Z2-LG502-10W | G13: 德国588 | H13: 宜胜照明2 | I13: 施月紫 | J13: 王燕赟 | K13: 周利军 | L13: 21K008订单2022年出货3000pcs工作灯，2024年1月发生客诉，产品塑料件开裂，比例很高。 客户要求全额赔偿；经协商后同意按50%货值给赔偿款，同时由我司免费赔货同等数量产品给客户替换。 而赔货产品不再另做大货，直接用T23U019此票订单遗留库存产品来出 | M13: 3000 | N13: 330 | O13: =IFERROR(N13/M13,"") -> 0.11 | P13: 售后客诉 | Q13: 外观 | R13: 1.塑料件供应商在生产过程中工艺控制不稳定，导致PC材料的强度、韧性等性能下降 2.注塑过程中工艺参数设置不合理，如温度、压力、冷却时间等，导致内应力残留 3.产品设计存在壁厚不均，在使用过程中容易产生应力集中，增加开裂风险 4.缺乏有效的加强结构设计，无法有效分散外力作用 | S13: 结构设计 | T13: 经协商后同意按50%货值给赔偿款，同时由我司免费赔货同等数量产品给客户替换。 而赔货产品不再另做大货，直接用T23U019此票订单遗留库存产 | U13: 1.与原材料供应商深入沟通，要求其加强生产过程质量控制，确保材料稳定性； 2.控制储存环境如温度。湿度，阳光直射等，避免因环境因素而导致性能下降； 3.设计应考虑壁厚分布，减少应力集中； 4.增加合理的加强结构，提高产品的整体强度和抗外力能力 | V13: 是 | W13: 纠错 | X13: 宜胜照明2 | Y13: 研发九 | Z13: 45521 | AA13: 45521 | AB13: =IF(A13="","",_xlfn.IFS(AND(Z13=0,AA13=0),"未回复",AND(AA13<>0,Z13=0),"报错",AND(Z13>=NOW(),Z13<>0,AA13=0),"正常进行中",AND(AA13<>0,Z13>=AA13),"按时关闭",AND(Z13<>0,Z13<=AA13),"延期关闭",AND(AA13=0,Z13<NOW()),"延期未关闭")) -> 按时关闭 | AC13: 赵纯杰 | AD13: =IF(Z13="","",YEAR(Z13)) -> 2024 | AE13: =IF(Z13="","",TEXT(Z13,"m")) -> 8 | AF13: =IF(Z13="","","W"&WEEKNUM(Z13,2)) -> W33
A14: 45512 | B14: =IF(A14="","",YEAR(A14)) -> 2024 | C14: =IF(A14="","",TEXT(A14,"m")) -> 8 | D14: =IF(A14="","","W"&WEEKNUM(A14,2)) -> W32 | E14: T24X003 | F14: ST-LR432-4WX5IC3-0612-G2-3M | G14: 德国793 | H14: 宜胜照明2 | I14: 姚优静 | J14: 屠磊 | K14: 周利军 | L14: 订单号：T24X003 产品：智能霓虹灯带 数量：16700pcs 订单金额：828821人民币 此订单为德国Aldi商超订单，下单前已明确产品需要符合客户的化学测试要求。 工厂提供的产前样化学测试没有问题，且保证大货品质跟产前样保持一致。 但是在验货阶段，大货抽样寄到德国测试之后发现化学不过，面临整单取消的风险。 经业务与供方核实后，发现大货确实存在污染，导致测试不过。 后经业务与客户沟通，最终成功说服终端让步接受，但是需要缴纳5000美元的罚金； 除此之外，整个订单过程中还产生679.09美元的重测费用，客户向我们索赔共计5679.09美元。 该笔索赔费用全部由供方承担 | M14: 16700 | N14: 16700 | O14: =IFERROR(N14/M14,"") -> 1 | P14: 售后客诉 | Q14: 安规 | R14: 对原材料以及贴片半成品进行检测排查，测试结果OK，灯条包皮后拿去测试，结果NG，锁定问题原因是包外皮机器之前生产过非ROSH要求的产品，使用了非环保材料，而水槽没有定期清洗导致。 | S14: 过程工艺 | T14: 1、设立环保产品专用包外皮机器，单独分开 2、料筒和材料区域单独分开 3、水槽做货前清洗。 2.立即启动对后续产品的预防措施，防止类似问题再次发生 | U14: 1.胶料材料商环保胶料独立车间生产 2.来料环保材料独立位置堆放 3.环保机器独立使用 | V14: 否 | W14: 供应商改善 | X14: 宜胜照明2 | Y14: 研发五 | Z14: 45519 | AA14: 45519 | AB14: =IF(A14="","",_xlfn.IFS(AND(Z14=0,AA14=0),"未回复",AND(AA14<>0,Z14=0),"报错",AND(Z14>=NOW(),Z14<>0,AA14=0),"正常进行中",AND(AA14<>0,Z14>=AA14),"按时关闭",AND(Z14<>0,Z14<=AA14),"延期关闭",AND(AA14=0,Z14<NOW()),"延期未关闭")) -> 按时关闭 | AC14: 赵纯杰 | AD14: =IF(Z14="","",YEAR(Z14)) -> 2024 | AE14: =IF(Z14="","",TEXT(Z14,"m")) -> 8 | AF14: =IF(Z14="","","W"&WEEKNUM(Z14,2)) -> W33
A15: 45535 | B15: =IF(A15="","",YEAR(A15)) -> 2024 | C15: =IF(A15="","",TEXT(A15,"m")) -> 8 | D15: =IF(A15="","","W"&WEEKNUM(A15,2)) -> W35 | E15: M24H005 | F15: ST-WS1002 9-2300W3- WFT-03-G1 | G15: 巴西527 | H15: 宜胜照明1 | I15: 徐赢意 | J15: 赖长金 | K15: 丁亚双 | L15: 单插黑色玻璃破损 | M15: 520 | N15: 520 | O15: =IFERROR(N15/M15,"") -> 1 | P15: 售后客诉 | Q15: 外观 | R15: 针对产品玻璃面板不良，排查因项目首次生产新工人未培训作业，导致工人未区分玻璃方向。将玻璃方向装反。 返工过程中玻璃面板已经打胶固定，工人使用工具对四个角撬开，造成玻璃面板损伤。 | S15: 过程工艺 | T15: 将已经完成打胶玻璃300台进行挑选返工，挑选出187台，拆开玻璃进行返工作业。 | U15: 1、此问题为首次生产导致。后续订单已经更改作业流程。2、将后续订单:M24H033进行排查，已排除此问题再次发生。首件确认合格 (生产、工业、品质）签字确认，大货上线生产。 3、玻璃破损问题已经要求作业人员规范作业。以及外观检验对比图。 | V15: 否 | W15: 流程优化 | X15: 宜胜照明1 | Y15: 生产一 | Z15: 45538 | AA15: 45538 | AB15: =IF(A15="","",_xlfn.IFS(AND(Z15=0,AA15=0),"未回复",AND(AA15<>0,Z15=0),"报错",AND(Z15>=NOW(),Z15<>0,AA15=0),"正常进行中",AND(AA15<>0,Z15>=AA15),"按时关闭",AND(Z15<>0,Z15<=AA15),"延期关闭",AND(AA15=0,Z15<NOW()),"延期未关闭")) -> 按时关闭 | AC15: 李俊林 | AD15: =IF(Z15="","",YEAR(Z15)) -> 2024 | AE15: =IF(Z15="","",TEXT(Z15,"m")) -> 9 | AF15: =IF(Z15="","","W"&WEEKNUM(Z15,2)) -> W36
A16: 45537 | B16: =IF(A16="","",YEAR(A16)) -> 2024 | C16: =IF(A16="","",TEXT(A16,"m")) -> 9 | D16: =IF(A16="","","W"&WEEKNUM(A16,2)) -> W36 | E16: A124S057+080 | F16: LC1101E-5 .5W2-G2-1 796 | G16: 郎德万斯-俄罗斯 | H16: 宜胜照明1 | I16: 张美娟 | K16: 王超 | L16: 订单A124S057+080大货客户已收到，但客户收到货后发现大货有异常现象： 1. 空彩盒（无产品） | M16: / | N16: / | O16: / | P16: 售后客诉 | Q16: 包装 | R16: 因为无法查询问题，已转内部报告回复 | S16: 人员作业 | X16: 其它事业部 | Y16: 供方管理组 | Z16: 45550 | AA16: 45550 | AB16: =IF(A16="","",_xlfn.IFS(AND(Z16=0,AA16=0),"未回复",AND(AA16<>0,Z16=0),"报错",AND(Z16>=NOW(),Z16<>0,AA16=0),"正常进行中",AND(AA16<>0,Z16>=AA16),"按时关闭",AND(Z16<>0,Z16<=AA16),"延期关闭",AND(AA16=0,Z16<NOW()),"延期未关闭")) -> 按时关闭 | AC16: 李俊林 | AD16: =IF(Z16="","",YEAR(Z16)) -> 2024 | AE16: =IF(Z16="","",TEXT(Z16,"m")) -> 9 | AF16: =IF(Z16="","","W"&WEEKNUM(Z16,2)) -> W37
A17: 45544 | B17: =IF(A17="","",YEAR(A17)) -> 2024 | C17: =IF(A17="","",TEXT(A17,"m")) -> 9 | D17: =IF(A17="","","W"&WEEKNUM(A17,2)) -> W37 | E17: Y24P0516 | F17: LB2101C-9 1 W2-BM-G1 | G17: 澳大利亚020-1 | H17: 宜胜照明1 | I17: 徐碧琳 | K17: 张煊 | L17: 客户反馈工单;Y24P0516、测试灯不亮， 经过将不良品进行分析，发现灯板焊盘脱落，导致灯不亮。 | M17: / | N17: / | O17: / | P17: 售后客诉 | Q17: 功能 | R17: 经过初步了解到因装配过程中，工人对插灯板时未注意，造成端子损伤。模拟测试同系列20pcs产品进行（震动+跌落+40℃恒温箱点亮2H），撬开灯罩未发现有灯板焊盘损伤不良，初步判定为装配时损伤了焊盘导致。 | S17: 人员作业 | T17: 1.增加巡检对球泡抽检，将此问题在同方案机种上验证。 未发现不良品 2.在同方案订单生产放置不良品，工人已经检出不良品。 模拟测试合格 3.将对客户反馈问题，内部协商签订质量保函，业务端回传给客户。 | U17: 1.通过客人反馈问题进行分析处理：1.端子焊盘在原有的位置加大，防止因为焊盘小，导致人员装配时间造成受力不均匀。 | V17: 是 | W17: 设计变更-预防 | X17: 宜胜照明1 | Y17: 研发六 | Z17: 45549 | AA17: 45546 | AB17: =IF(A17="","",_xlfn.IFS(AND(Z17=0,AA17=0),"未回复",AND(AA17<>0,Z17=0),"报错",AND(Z17>=NOW(),Z17<>0,AA17=0),"正常进行中",AND(AA17<>0,Z17>=AA17),"按时关闭",AND(Z17<>0,Z17<=AA17),"延期关闭",AND(AA17=0,Z17<NOW()),"延期未关闭")) -> 按时关闭 | AC17: 李俊林 | AD17: =IF(Z17="","",YEAR(Z17)) -> 2024 | AE17: =IF(Z17="","",TEXT(Z17,"m")) -> 9 | AF17: =IF(Z17="","","W"&WEEKNUM(Z17,2)) -> W37
A18: 45544 | B18: =IF(A18="","",YEAR(A18)) -> 2024 | C18: =IF(A18="","",TEXT(A18,"m")) -> 9 | D18: =IF(A18="","","W"&WEEKNUM(A18,2)) -> W37 | E18: M24H015 | F18: ST-WS7007 2-1800W3- WFT-G2 | G18: 巴西527 | H18: 宜胜照明1 | I18: 徐赢意 | J18: 赖长金 | K18: 丁亚双 | L18: 客验出现外箱变形，内部彩盒破损 | M18: 520 | N18: / | O18: / | P18: 客户验货 | Q18: 包装 | R18: 经过仓库排查，发现货物运输过程中货物掉下来，导致外箱摔下来，里面彩盒变形。 | S18: 人员作业 | T18: 针对此批外箱货物进行统一返工处理，彩盒更换，产品测试功能是否正常。 返工结果：产品功能测试正常。外箱增加发泡膜。 | U18: 1、针对外箱尺寸偏大，出现外箱变形，后续订单已经修改外箱尺寸，从订单;M24H033-1开始。外箱尺寸已经修改。原外箱尺寸35*31*27改成34.5x30x26cm。 2、因为外箱掉落导致内部彩盒变形，已经和仓库对接清楚，后续针对此客户货物，如出现货物掉下来，通知生产这边进行检查，内部产品是否损坏，彩盒是否出现不良。 3、仓库转移货物时，严禁货物超高堆积。按要求作业 | V18: 否 | W18: 人员培训 | X18: 其它事业部 | Y18: 优泰物流司 | Z18: 45544 | AA18: 45544 | AB18: =IF(A18="","",_xlfn.IFS(AND(Z18=0,AA18=0),"未回复",AND(AA18<>0,Z18=0),"报错",AND(Z18>=NOW(),Z18<>0,AA18=0),"正常进行中",AND(AA18<>0,Z18>=AA18),"按时关闭",AND(Z18<>0,Z18<=AA18),"延期关闭",AND(AA18=0,Z18<NOW()),"延期未关闭")) -> 按时关闭 | AC18: 李俊林 | AD18: 2024 | AE18: 9 | AF18: =IF(Z18="","","W"&WEEKNUM(Z18,2)) -> W37
A19: 45544 | B19: =IF(A19="","",YEAR(A19)) -> 2024 | C19: =IF(A19="","",TEXT(A19,"m")) -> 9 | D19: =IF(A19="","","W"&WEEKNUM(A19,2)) -> W37 | F19: 180路灯 | I19: 张美娟 | J19: 余元浩 | K19: 王超 | L19: 180路灯2PCS死灯 | N19: 2 | O19: =IFERROR(N19/M19,"") | P19: 售后客诉 | Q19: 功能 | R19: 经检查分析：45W驱动电源保险电阻熔断，元器件MOS损坏 60W灯板及驱动电源烧坏，已无法维修 LED失效可能原因： - 雷击影响：实际使用环境中可能遭受感应雷击（如静电和电磁感应雷击）导致驱动中保险丝熔断，尽管灯具浪涌测试合格，但实际环境更为复杂。雷击电压可达数千伏至几万伏，驱动中的保险丝也正是防止各种异常导致瞬间电流增大，保险丝熔断电路防止灯具主体受损 ，但若瞬间产生电压过高，超过灯具承受极限，就会导致灯具主体完全烧毁。 - 供电电压不稳：灯具连接的公共用电线路复杂，电压波动可能超出灯具承受范围导致保险丝熔断。 - 排除原因 - 灯珠和关键元器件温升：最大环温下灯珠和 IC 温升符合要求，不是灯具不亮的因素。 - LED 死灯与电路关系：死灯是其他原因造成的结果而非导致灯具不亮的原因，且短路 LED 复现灯板烧毁的假设不成立。 | S19: 其它 | T19: 对产品关键元器件温升进行测试，灯珠温升66.7℃（参考标准在60-80℃）驱动IC温升60.2℃（参考标准70-90℃） 浪涌（2500V)进行测试,测试结果OK 确保同批次产品符合标准 | U19: 针对驱动电源 - 加强对驱动电源供应商的管理，要求供应商对每批次元件提供更详细的质量检测报告，提高元件质量的稳定性。 - 优化驱动电源的生产质量管控流程，增加生产过程中的抽检频率，确保每一个驱动电源符合质量标准。 针对雷击、供电电压不稳问题 - 随时提供技术支持与服务，包括安装位置选择、接地方法等方面的建议，帮助客户减少灯具遭受雷击的风险；公共用电环境灯具使用，客户在电压不稳时可以采取的一些简单外部措施，如使用家用稳压器等，避免对灯具造成损坏。 | V19: 是 | W19: 其它 | Z19: 45547 | AA19: 45547 | AB19: =IF(A19="","",_xlfn.IFS(AND(Z19=0,AA19=0),"未回复",AND(AA19<>0,Z19=0),"报错",AND(Z19>=NOW(),Z19<>0,AA19=0),"正常进行中",AND(AA19<>0,Z19>=AA19),"按时关闭",AND(Z19<>0,Z19<=AA19),"延期关闭",AND(AA19=0,Z19<NOW()),"延期未关闭")) -> 按时关闭 | AC19: 赵纯杰 | AD19: =IF(Z19="","",YEAR(Z19)) -> 2024 | AE19: =IF(Z19="","",TEXT(Z19,"m")) -> 9 | AF19: =IF(Z19="","","W"&WEEKNUM(Z19,2)) -> W37
A20: 45549 | B20: 2024 | C20: 9 | D20: =IF(A20="","","W"&WEEKNUM(A20,2)) -> W37 | E20: P24R023/R032/R033 | F20: 球泡 | G20: 俄罗斯482-3 | H20: 宜胜照明1 | L20: 1.P24R023 LBD B35-10W-840-E14 R 灯头变形6pcs 2.P24R023 LED B35-8W-865-E14 R 1pc电解端子起翘 加抽100pcs（1pc保险电阻端子起翘）客户形容灯头很顺滑 测试扭力没有阻力 3. P24R023 LBD MR16-11W-840-GU5.3 R 1PC不亮 保险电阻端子起翘（未加抽） 4. P24R023 LBD P45-10W-865-B27 R 功率不足 实测6.47W 客户要求≥6.5W 5.P24R023 LED P45-8W-865-E27 R IPC 扭力不过（未加抽） 6. P24R032 LED A60-15W-827-E27 R IPC 不亮 1pc混灯 瓦数偏低（实测8.4W 要求＞8.5w） 扭力不过1pc 7.P24R032 LED A60-15W-865-E27 R 4pcs 不亮（客户发现一个 未加抽） 瓦数偏低（实测8.4W 要求≥8.5W） | R20: 经过确认此问题为生产作业问题。 | V20: 否 | AB20: =IF(A20="","",_xlfn.IFS(AND(Z20=0,AA20=0),"未回复",AND(AA20<>0,Z20=0),"报错",AND(Z20>=NOW(),Z20<>0,AA20=0),"正常进行中",AND(AA20<>0,Z20>=AA20),"按时关闭",AND(Z20<>0,Z20<=AA20),"延期关闭",AND(AA20=0,Z20<NOW()),"延期未关闭")) -> 未回复 | AD20: =IF(Z20="","",YEAR(Z20)) | AE20: =IF(Z20="","",TEXT(Z20,"m")) | AF20: =IF(Z20="","","W"&WEEKNUM(Z20,2))
A21: 45561 | B21: =IF(A21="","",YEAR(A21)) -> 2024 | C21: =IF(A21="","",TEXT(A21,"m")) -> 9 | D21: =IF(A21="","","W"&WEEKNUM(A21,2)) -> W39 | E21: M24S064K M22K044 | F21: 智能插座 | G21: 阿根廷037 | H21: 宜胜照明1 | L21: 产品额定电流10A，在220V情况下最大负载2200W，客户实际使用过程中，电流达到7/8A，产品会损坏，已回收50PCS大货，产品经理实测产品出现问题 | M21: 5200 8000 | N21: 50 | O21: / | P21: 售后客诉 | Q21: 功能 | R21: 供应商也过来现场测试过了、初步分析为供应商的继电器未达到10A的标准。上限10A、导致现场出现2个问题、底电压测试功能正常、继电器内部触点无任何变化。、当电压放到9A测试、长开测试1小时、连续开关测试1小时、继电器内部触电呈现发蓝发红现象。初步分析此现象为过载状态。 经过确认供应商继电器有问题，掉落地上以后，测试不良 | S21: 结构设计 | T21: 经过和供应商产品经理确认，此批继电器为供应商问题，已经和供应商确认。 | V21: 是 | Z21: 45572 | AA21: 45572 | AB21: 按时关闭 | AC21: 李俊林 | AD21: 2024 | AE21: 9 | AF21: 39W
A22: 45573 | B22: =IF(A22="","",YEAR(A22)) -> 2024 | C22: =IF(A22="","",TEXT(A22,"m")) -> 10 | D22: =IF(A22="","","W"&WEEKNUM(A22,2)) -> W41 | E22: Y24P0516 | F22: 球泡 | G22: 洪都拉斯008 | H22: 宜胜照明1 | L22: 产品点亮测试，灯不亮。 | M22: / | N22: / | O22: / | P22: 售后客诉 | Q22: 功能 | R22: 1.产生原因：将不良品进行分析，发现产品芯片破损，经过测量发现芯片短路，造成产品灯微亮，测试无输出，将产品寄回供应商进行分析，发现回传报告显示，芯片因为芯片破损导致局部短路温度过高。造成产品灯微亮，测试无功率。 将不良更换芯片后面测试正常。 2.流出原因：经与供应商确认，此问题是IC小批次不良，在长期在低压100V老化时存在风险，而此款产品我司同客户约定测试电压为AC120V及AC220V，生产中仅在120V以上做了长期老化，没能发现问题，致使产品流出。 | S22: 过程工艺 | T22: 增加老化时间，从原来的1小时更改成2小时 | U22: 1.通过以上自查进行分析处理：1.修改老化SOP设置 从原有的120V 修正为低压100V 常压 120V 高压140V； | V22: 否 | Y22: 生产一 | Z22: 45573 | AA22: 45573 | AB22: =IF(A22="","",_xlfn.IFS(AND(Z22=0,AA22=Z22>0,Z22=0),"报错",AND(Z22>=NOW(),Z22<>0,AA22=0),"正常进行中",AND(AA22<>0,Z22>=AA22),"按时关闭",AND(Z22<>0,Z22<=AA22),"延期关闭",AND(AA22=0,Z22<NOW()),"延期未关闭")) -> 按时关闭 | AC22: 李俊林 | AD22: =IF(Z22="","",YEAR(Z22)) -> 2024 | AE22: =IF(Z22="","",TEXT(Z22,"m")) -> 10 | AF22: =IF(Z22="","","W"&WEEKNUM(Z22,2)) -> W41
A23: 45575 | B23: =IF(A23="","",YEAR(A23)) -> 2024 | C23: =IF(A23="","",TEXT(A23,"m")) -> 10 | D23: =IF(A23="","","W"&WEEKNUM(A23,2)) -> W41 | E23: M24H026 | F23: 智能插座 | G23: 巴西527 | H23: 宜胜照明1 | L23: 客户发了一个客诉邮件，关于ETS 两开单插的： 527的终端客户将设备插入插座时，发生了短路，导致产品损坏无法修复。但是用户家里所有的保护装置都被触发了，所以只有ETS 2002被损坏了。在检查产品时，发现插座中的接地连接器在出厂时是弯曲的，用户在连接设备时，引脚会推动已经弯曲的金属连接器而导致短路。 | M23: / | N23: / | O23: / | P23: 售后客诉 | Q23: 功能 | R23: 1.经过初步分析为生产时未测试地线位置接触，导致客户使用过程中，因为地线接触到火线，造成炸机 | S23: 过程工艺 | T23: 1.车间是对每一个插座用标准的巴西插头进行插入测试的，能正常插拔就是OK的。 另外，客户那边的允收标准也同步问一下。 目前大货是按给客户送样的产品生产的，客户那边应该也是做了证书的。对于客户提出的问题，现在设计上对接地的金属插片进行了调整 | U23: 规格地线端子使用规格 | V23: 是 | Y23: 研发六 | Z23: 45577 | AA23: 45577 | AB23: =IF(A23="","",_xlfn.IFS(AND(Z23=0,AA23=0),"未回复",AND(AA23<>0,Z23=0),"报错",AND(Z23>=NOW(),Z23<>0,AA23=0),"正常进行中",AND(AA23<>0,Z23>=AA23),"按时关闭",AND(Z23<>0,Z23<=AA23),"延期关闭",AND(AA23=0,Z23<NOW()),"延期未关闭")) -> 按时关闭 | AC23: 李俊林 | AD23: =IF(Z23="","",YEAR(Z23)) -> 2024 | AE23: =IF(Z23="","",TEXT(Z23,"m")) -> 10 | AF23: =IF(Z23="","","W"&WEEKNUM(Z23,2)) -> W41
A24: 45614 | B24: =IF(A24="","",YEAR(A24)) -> 2024 | C24: =IF(A24="","",TEXT(A24,"m")) -> 11 | D24: =IF(A24="","","W"&WEEKNUM(A24,2)) -> W47 | E24: M24A002 | F24: 智能插座 | G24: 巴西527 | H24: 宜胜照明1 | L24: 客户验货中发现： 1. 外观问题： 1.1.插座划伤，轻微*3。 1. 2.玻璃背部划伤*5。 1. 3.玻璃面板边缘破损*2 。 | M24: / | N24: / | O24: / | P24: 售后客诉 | Q24: 外观 | R24: 1.插座划伤，轻微：塑料件旁边有一个电子开关需要按压测试，生产人员使用的测试工具不规范（PCB板边），较为锋利，测试时会误伤塑胶件。 2.玻璃背部划伤：（供应商）覆底膜进入机器抽真空后，在尾分使用美工刀作业，造成玻璃背部划伤。 3.玻璃面板边缘破损：该订单为返工订单，返工过程中需要拆开玻璃进行内部测试，拆开后的玻璃摆放堆积，造成相互之间有磕碰。 | S24: 过程工艺 | T24: 1.针对塑料件划伤：目前已经对该测试岗位重新制定按压工具（胶棒），避免划伤问题。 模拟测试100台，塑料件外观检查未发现外观不良 2.玻璃背部划伤： 供方措施：暂未回复 我方措施：返工时针对玻璃保护膜需要撕下来看划痕。 请业务端与客户沟通，撕开膜以后外观确认。撕膜后重新覆膜的状态对比已经放置在报告后端。如确认OK，后续将此问题增加进检验要求内部。 3.玻璃面板边缘破损：本次返工时，增加玻璃放置箱，只能单排放置，不得有相互堆积、错乱放置 | U24: 1、使用重新制定按压工具（胶棒），可有效避免划伤问题。 2.对于玻璃内部划痕的问题以反馈供应商进行排查划伤原因。 3.制定SOP，并明确返工作业流程，以及摆放方式，巡检增加返工过程中生产，是否按SOP要求作业。 | V24: 是 | W24: 防呆防错 | X24: 宜胜照明1 | Y24: 生产一 | Z24: 45616 | AA24: 45616 | AB24: =IF(A24="","",_xlfn.IFS(AND(Z24=0,AA24=0),"未回复",AND(AA24<>0,Z24=0),"报错",AND(Z24>=NOW(),Z24<>0,AA24=0),"正常进行中",AND(AA24<>0,Z24>=AA24),"按时关闭",AND(Z24<>0,Z24<=AA24),"延期关闭",AND(AA24=0,Z24<NOW()),"延期未关闭")) -> 按时关闭 | AD24: =IF(Z24="","",YEAR(Z24)) -> 2024 | AE24: =IF(Z24="","",TEXT(Z24,"m")) -> 11 | AF24: =IF(Z24="","","W"&WEEKNUM(Z24,2)) -> W47
A25: 45620 | B25: =IF(A25="","",YEAR(A25)) -> 2024 | C25: =IF(A25="","",TEXT(A25,"m")) -> 11 | D25: =IF(A25="","","W"&WEEKNUM(A25,2)) -> W47 | E25: M24H022 | F25: 智能插座 | G25: 巴西527 | H25: 宜胜照明1 | L25: 客户反馈外箱打开后发现内部彩盒装混装，内部标签，产品一致，彩盒出现混装。 1.工单数量合计：5080台，挑选出88台。 | M25: 5080 | N25: 88 | O25: =IFERROR(N25/M25,"") -> 0.017322835 | P25: 售后客诉 | Q25: 包装 | R25: 1.通过目前仓库物料排查，发现内部仓库未规范摆放物料现象。将此问题进行复盘，物料摆放过近，容易造成物料领用过程中料混。 2.生产过程中，全检验人员检查力度不够，未及时发现问题存在。 3.彩盒装混装已转供方分析处理。（供应商）初步分析为人员变动，在包装过程中未及时清理上工单，造成将上款包材混装。 | S25: 人员作业 | T25: 1.提供客户反馈问题，将内部已经生产完成订单进行排查，统计数量，做整批返工处理。 2.已完成成品合计：24800台，将整批全部返工。 附件返工视频---24800台全部返工未出现彩盒混装。 3.彩盒装混装： 供方措施：暂未回复 我方措施：通知仓库接受物料过程中，检查是否将物料排放整齐，拒绝堆积物料送入公司。 | U25: 1.仓库物料摆放整改，将物料进行分类，防止运输过程，以及物料摆放，进行缠绕膜方式，防止物料混在一起。 2.规范人员检验方法，SOP增加检验标准。 | V25: 是 | W25: 其它 | X25: 宜胜照明1 | Y25: 生产一 | Z25: 45622 | AA25: 45622 | AB25: =IF(A25="","",_xlfn.IFS(AND(Z25=0,AA25=0),"未回复",AND(AA25<>0,Z25=0),"报错",AND(Z25>=NOW(),Z25<>0,AA25=0),"正常进行中",AND(AA25<>0,Z25>=AA25),"按时关闭",AND(Z25<>0,Z25<=AA25),"延期关闭",AND(AA25=0,Z25<NOW()),"延期未关闭")) -> 按时关闭 | AD25: =IF(Z25="","",YEAR(Z25)) -> 2024 | AE25: =IF(Z25="","",TEXT(Z25,"m")) -> 11 | AF25: =IF(Z25="","","W"&WEEKNUM(Z25,2)) -> W48
A26: 45644 | B26: =IF(A26="","",YEAR(A26)) -> 2024 | C26: =IF(A26="","",TEXT(A26,"m")) -> 12 | D26: =IF(A26="","","W"&WEEKNUM(A26,2)) -> W51 | E26: A522M054 | F26: BL212-15W-PIR | G26: 澳大利亚1283 | H26: 宜胜照明3 | L26: 2022年A522M054订单，出货时间在2023年1月。客户在2024年11月反馈该项目有320PCS灯具出现半亮或不亮现象 | M26: 2070 | N26: 230 | O26: =IFERROR(N26/M26,"") -> 0.11111111 | P26: 售后客诉 | Q26: 功能 | R26: 不良现象分析：分别对客户寄回4PCS产品进行检查，均为电容中间灯珠死灯导致产品不亮，电解电容中间灯珠为灯板线路第一颗灯珠，连接此灯珠两端，其余整灯可正常点亮。4PC灯具不良现象完全一致。 根本原因分析： 1. 电气应力过大：由于灯具安装在人流量密集区域，感应频繁开关，开关瞬间产生较大电流冲击。而第一颗灯珠在电路中处于起始位置，承受的电流冲击相对更大，长时间累积导致灯珠内部芯片受损，最终死灯。 2. 线性方案局限性：采用的线性方案在应对频繁开关和大电流冲击时，缺乏有效的电流稳定和保护机制。无法有效分散或缓冲瞬间大电流对灯珠的影响，使得灯珠更容易因电气过载而损坏。 | S26: 电子设计 | T26: 与客户沟通，为受影响的客户提供临时替换320pcs灯具，确保其正常使用，减少对客户业务的影响。 | U26: 措施建议： 1. 电路优化： 更改灯具电路线性方案，采用具备软启动功能和电流限制保护的驱动方案，降低开关瞬间电流冲击幅度，均匀分配电流至每颗灯珠，减少单颗灯珠承受的电气应力。 2.使用质量更好可靠性更高的灯珠，可延长一些灯具使用寿命。 | V26: 否 | W26: 纠错 | X26: 宜胜照明3 | Y26: 研发二 | Z26: 45651 | AA26: 45651 | AB26: =IF(A26="","",_xlfn.IFS(AND(Z26=0,AA26=0),"未回复",AND(AA26<>0,Z26=0),"报错",AND(Z26>=NOW(),Z26<>0,AA26=0),"正常进行中",AND(AA26<>0,Z26>=AA26),"按时关闭",AND(Z26<>0,Z26<=AA26),"延期关闭",AND(AA26=0,Z26<NOW()),"延期未关闭")) -> 按时关闭 | AD26: =IF(Z26="","",YEAR(Z26)) -> 2024 | AE26: =IF(Z26="","",TEXT(Z26,"m")) -> 12 | AF26: =IF(Z26="","","W"&WEEKNUM(Z26,2)) -> W52
A27: 45649 | B27: =IF(A27="","",YEAR(A27)) -> 2024 | C27: =IF(A27="","",TEXT(A27,"m")) -> 12 | D27: =IF(A27="","","W"&WEEKNUM(A27,2)) -> W52 | E27: Z24V002-1 | F27: 方形投光灯_LG189-150W | G27: 中国2354 | H27: 宜胜照明3 | L27: 150W投光灯玻璃内部水汽 | M27: 500 | N27: 350 | O27: =IFERROR(N27/M27,"") -> 0.7 | P27: 售后客诉 | Q27: 安规 | R27: 原因分析：热空气遇冷凝结 投光灯点亮后，灯体内的灯泡等发光元件会产生热量，使灯体内的空气温度升高。当热空气遇到冰冷的灯体外壳（在寒冷天气下）时，热空气就会迅速降温，其中的水蒸气达到饱和状态后就会凝结成小水滴，形成水汽。这就如同冬天室内温暖的空气遇到冰冷的窗户玻璃时会在玻璃上形成水珠一样 | S27: 结构设计 | T27: 与客户沟通，为受影响的客户提供临时替换该订单有问题产品，确保其正常使用，减少对客户业务的影响。 | U27: 改善措施：灯体增加呼吸孔，平衡灯具内部的气压，同时阻止外界的水汽进入。在寒冷天气下，它有助于维持灯具内部环境的相对稳定。 该款产品结构增加呼吸孔已于2024年6月进行变更。 | V27: 是 | W27: 设计变更-预防 | X27: 宜胜照明3 | Y27: 研发一 | Z27: 45651 | AA27: 45651 | AB27: =IF(A27="","",_xlfn.IFS(AND(Z27=0,AA27=0),"未回复",AND(AA27<>0,Z27=0),"报错",AND(Z27>=NOW(),Z27<>0,AA27=0),"正常进行中",AND(AA27<>0,Z27>=AA27),"按时关闭",AND(Z27<>0,Z27<=AA27),"延期关闭",AND(AA27=0,Z27<NOW()),"延期未关闭")) -> 按时关闭 | AD27: =IF(Z27="","",YEAR(Z27)) -> 2024 | AE27: =IF(Z27="","",TEXT(Z27,"m")) -> 12 | AF27: =IF(Z27="","","W"&WEEKNUM(Z27,2)) -> W52
A28: 45670 | B28: =IF(A28="","",YEAR(A28)) -> 2025 | C28: =IF(A28="","",TEXT(A28,"m")) -> 1 | D28: =IF(A28="","","W"&WEEKNUM(A28,2)) -> W3 | E28: R23X0418 | F28: HL120C-200W高顶灯 | G28: 俄罗斯745 | H28: 宜胜照明3 | L28: 订单总数量3780pcs，200W这一款1200pcs，客户检查400pcs，其中150pcs壳体吊环螺丝孔无螺纹，不良比例37.5% | M28: 1200 | N28: 150 | O28: =IFERROR(N28/M28,"") -> 0.125 | P28: 售后客诉 | Q28: 内部 | R28: 发生原因：供应商生产过程中攻丝设备出现故障，导致部分螺丝孔未攻出完整螺纹。同时，供应商的生产人员在操作过程中未及时发现和处理设备故障，也未对加工后的产品进行严格检验。 流出原因：来料及制程对结构安装配件存在漏检现象或抽检比例不足 | S28: 来料不良 | T28: 与客户沟通，有以下临时措施可供选择： 1.使用M10丝锥进行攻丝处理，人工费用由我司承担； 2.换货处理，不良品进行退换货处理； 3.折价处理，吊环螺丝孔不影响产品功能正常使用，只是安装过程可能会对客户造成一些影响，可根据不良率对该批产品折价赔偿处理。 | U28: 1.供应商整改：我司已于2024年7月底因该供应商质量不符合公司要求且无整改意向，而中断与该供应商合作；后续继续加强对供应商管理，定期对供应商进行考核。 2.合理调整抽样方案，增加样本抽样数量，加强生产过程巡检频率，螺纹孔纳入产线外观检验人员必检项目，防止不良流出，成品检验抽检需对配件包物料进行实配 3.建立质量预警机制：与供应商共享质量数据，当出现质量波动或异常趋势时，及时发出预警，共同分析原因并采取措施。 4.定期审核与评估：定期对供应商进行审核，包括生产过程、质量控制体系等方面。对公司内部的检验流程、生产工艺等进行评估，持续优化改善。 5.案例培训：整理此次问题案例在公司内部进行培训，提高全体人员质量意识。 | V28: 否 | W28: 供应商改善 | X28: 计划采购部 | Y28: 供方管理组 | Z28: 45671 | AA28: 45671 | AB28: =IF(A28="","",_xlfn.IFS(AND(Z28=0,AA28=0),"未回复",AND(AA28<>0,Z28=0),"报错",AND(Z28>=NOW(),Z28<>0,AA28=0),"正常进行中",AND(AA28<>0,Z28>=AA28),"按时关闭",AND(Z28<>0,Z28<=AA28),"延期关闭",AND(AA28=0,Z28<NOW()),"延期未关闭")) -> 按时关闭 | AD28: =IF(Z28="","",YEAR(Z28)) -> 2025 | AE28: =IF(Z28="","",TEXT(Z28,"m")) -> 1 | AF28: =IF(Z28="","","W"&WEEKNUM(Z28,2)) -> W3
A29: 45672 | B29: =IF(A29="","",YEAR(A29)) -> 2025 | C29: =IF(A29="","",TEXT(A29,"m")) -> 1 | D29: =IF(A29="","","W"&WEEKNUM(A29,2)) -> W3 | E29: A224M005 | F29: BL111C-20W | G29: 飞利浦-JP | H29: 宜胜照明3 | L29: 灯具不亮 | M29: 400 | N29: 36 | O29: =IFERROR(N29/M29,"") -> 0.09 | P29: 售后客诉 | Q29: 功能 | R29: 1.不排除灯珠本身质量问题的损坏（可能性极小，三星灯珠） 2.导热硅脂未贴于芯片及元器件位置，元器件温度过高电路不稳失衡，但更换灯珠后，一直老化无任何异常；3.PCB底部铜箔有发黄迹象，判定驱动处于高温环境中，实际测试温升OK，可推测产品实际应用环境高于产品要求！高温环境中驱动稳定性会有一定程度上的削弱（抗浪涌抗冲击能力变差） 4.现场安装环境(未知），如安装环境温度、周边电路电压、电流稳定性等 | S29: 电子设计 | T29: 客户回复使用环境为-35℃冷库环境，要求灯珠寄供应商分析 | V29: 否 | W29: 纠错 | X29: 宜胜照明3 | Y29: 研发二 | Z29: 45679 | AA29: 45679 | AB29: =IF(A29="","",_xlfn.IFS(AND(Z29=0,AA29=0),"未回复",AND(AA29<>0,Z29=0),"报错",AND(Z29>=NOW(),Z29<>0,AA29=0),"正常进行中",AND(AA29<>0,Z29>=AA29),"按时关闭",AND(Z29<>0,Z29<=AA29),"延期关闭",AND(AA29=0,Z29<NOW()),"延期未关闭")) -> 按时关闭 | AD29: =IF(Z29="","",YEAR(Z29)) -> 2025 | AE29: =IF(Z29="","",TEXT(Z29,"m")) -> 1 | AF29: =IF(Z29="","","W"&WEEKNUM(Z29,2)) -> W4
A30: 45699 | B30: =IF(A30="","",YEAR(A30)) -> 2025 | C30: =IF(A30="","",TEXT(A30,"m")) -> 2 | D30: =IF(A30="","","W"&WEEKNUM(A30,2)) -> W7 | E30: W24T023 | F30: ST-LC2201E-5.5W2-WF5 LC2221E4-7W2-TD-G1-21 | G30: 德国675 | H30: 宜胜照明1 | L30: 客户反馈 2024年W24T023订单，出货时间在2024年12月，订单两款产品，分别为货号990000102数量6000pcs（共20箱），货号990000132数量3900pcs（共13箱），客户实际收到产品990000102数量5700pcs（19箱）；990000132数量4200pcs（14箱），造成客户多支付348美金，客户需要下次订单时扣除该笔费用。 | M30: 6000/3900 | N30: 300 | O30: 0.05 | P30: 售后客诉 | Q30: 包装 | R30: 不良原因排查： 1.对生产信息进行排查，生产投料数量与入库数量、成品验货记录均与订单一致，排除两款产品一款多做一款少做的可能； 2.客户按外箱货号（990000102,990000132）多次清点数量，确认990000102少一箱，990000132多一箱，排查仓库发货记录及仓库库存信息，该订单两款产品入库后分开放置，出货时为同一货柜出货，货物订单数量全部发出； 3.排查外箱采购记录，990000102采购外箱21个，990000132采购外箱14个，两款产品各有多采购一个外箱备用，生产包装未仔细核对外箱信息，误将不同规格型号装入错误外箱 | S30: 其它 | T30: 与客户沟通，为避免客户继续清点产品数量信息，而要求外部仓库做任何移动货物或者关于货物的任何事情支付额外费用，同意客户下次订单时扣除该笔费用，同时针对此次问题向客户表达歉意。 | U30: 1.大货订单首件核对后生产并对外箱PO号进行点检存档记录，确保外箱信息正确。 2.大货生产完成摆托PO号朝外入库前确认外箱PO号内容是否正确。 3.尾数产品所有物料按照工单放置在托盘上使用缠绕膜封好并做好标识。 4.订单扫尾按照新工单进行首件确认合格后才可进行收尾并对外箱PO号进行点检确认。 | V30: 否 | W30: 流程优化 | X30: 宜胜照明1 | Y30: 生产一 | Z30: 45668 | AA30: 45668 | AB30: =IF(A30="","",_xlfn.IFS(AND(Z30=0,AA30=0),"未回复",AND(AA30<>0,Z30=0),"报错",AND(Z30>=NOW(),Z30<>0,AA30=0),"正常进行中",AND(AA30<>0,Z30>=AA30),"按时关闭",AND(Z30<>0,Z30<=AA30),"延期关闭",AND(AA30=0,Z30<NOW()),"延期未关闭")) -> 按时关闭 | AD30: =IF(Z30="","",YEAR(Z30)) -> 2025 | AE30: =IF(Z30="","",TEXT(Z30,"m")) -> 1 | AF30: =IF(Z30="","","W"&WEEKNUM(Z30,2)) -> W2
A31: 45699 | B31: =IF(A31="","",YEAR(A31)) -> 2025 | C31: =IF(A31="","",TEXT(A31,"m")) -> 2 | D31: =IF(A31="","","W"&WEEKNUM(A31,2)) -> W7 | E31: M23H036-B | F31: ST-LB208-10W3-WF5LC-G1 | G31: 巴西527 | H31: 宜胜照明1 | L31: 客户反馈订单M23H036-B球泡灯，型号ST-LB208-10W3-WF5LC-G1，订单数量25200pcs，发现5pcs手机APP控制关灯后，灯珠有余亮现象。 | M31: 25200 | N31: 5 | O31: =IFERROR(N31/M31,"") -> 0.0001984127 | P31: 售后客诉 | Q31: 功能 | R31: 1.对客户退回样品拆机检查，为KP18058ESPA芯片失效导致手机APP控制关灯后余亮，更换芯片后，产品功能恢复正常； 2.对KP18058ESPA失效进行FT复测，测试结果显示OUT4、OUT5耐压异常偏低； 3.进一步对失效芯片进行Decap拆封分析，Decap拍照无明显异常，芯片表面无明显异常； 4.失效芯片EMMI分析（PIN6加电压）：OUT4 MOS附件存在微小漏电亮点，判断击穿瞬间能量较小，推测为ESD静电击穿； 综上：不良样品手机APP控制关灯后余量现象为ESD静电击穿芯片导致功能异常。 | S31: 过程工艺 | T31: 不良产品更换货 | U31: 1.开线对设备和静电环进行接地点检 2.接触到灯板和电源的工位佩戴静电环和手套 3.灯板电源使用静电盒分开放置不能堆积 | V31: 否 | W31: 人员培训 | X31: 宜胜照明1 | Y31: 生产一 | Z31: 45670 | AA31: 45670 | AB31: =IF(A31="","",_xlfn.IFS(AND(Z31=0,AA31=0),"未回复",AND(AA31<>0,Z31=0),"报错",AND(Z31>=NOW(),Z31<>0,AA31=0),"正常进行中",AND(AA31<>0,Z31>=AA31),"按时关闭",AND(Z31<>0,Z31<=AA31),"延期关闭",AND(AA31=0,Z31<NOW()),"延期未关闭")) -> 按时关闭 | AD31: =IF(Z31="","",YEAR(Z31)) -> 2025 | AE31: =IF(Z31="","",TEXT(Z31,"m")) -> 1 | AF31: =IF(Z31="","","W"&WEEKNUM(Z31,2)) -> W3
A32: 45706 | B32: =IF(A32="","",YEAR(A32)) -> 2025 | C32: =IF(A32="","",TEXT(A32,"m")) -> 2 | D32: =IF(A32="","","W"&WEEKNUM(A32,2)) -> W8 | E32: D24A035 | F32: T100/T120/T140/T160光源板 | G32: 突尼斯100 | H32: 宜胜照明1 | L32: 客户反馈订单D24A035散件发货4款T泡光源板端子起翘，不良比例50% | M32: 50500 | O32: 0.5 | P32: 售后客诉 | Q32: 功能 | R32: 1.焊点牢固可靠性确认：库存查询该订单同批次4款灯板各有5PC在仓库，对端子焊点做30N-1min推拉力测试，测试结果合格。 2.包装方式：灯板采用背靠背的包装方式，背面端子有几毫米凸起，运输过程端子会直接相互摩擦挤压，长途运输过程端子会持续受力 3.运输过程：产品要经过三次装箱及卸货及长途运输 综上所述：灯板采用背面端子凸起面紧靠包装方式，长途运输过程端子持续受力摩擦及多次装卸货，导致端子脱落起翘。 | S32: 包装设计 | T32: 临时措施：与客户沟通，由客户对本批次端子起翘不良灯板进行返工维修，我司提供返工视频指导及所需工具型号（烙铁、锡丝），我司赔偿返工费用或产品进行折扣处理。 维修方案：1.拿小刀对起翘脱落焊盘附近的铜箔线路轻轻刮动，刮掉表面白色绝缘保护层，露出线路铜箔即可；2.用烙铁和锡丝将刮开的铜箔同端子引脚进行加锡焊接，覆盖链接实现串联。 | U32: 更改设计，将端子更改为平口端子，避免铝基本板背面端子凸出部分在运输过程相互摩擦受力而导致端子脱落。包装进行紧凑包装，防止运输途中松动相互碰撞 | V32: 是 | W32: 设计变更-预防 | X32: 宜胜照明1 | Y32: 研发六 | Z32: 45708 | AA32: 45708 | AB32: =IF(A32="","",_xlfn.IFS(AND(Z32=0,AA32=0),"未回复",AND(AA32<>0,Z32=0),"报错",AND(Z32>=NOW(),Z32<>0,AA32=0),"正常进行中",AND(AA32<>0,Z32>=AA32),"按时关闭",AND(Z32<>0,Z32<=AA32),"延期关闭",AND(AA32=0,Z32<NOW()),"延期未关闭")) -> 按时关闭 | AD32: =IF(Z32="","",YEAR(Z32)) -> 2025 | AE32: =IF(Z32="","",TEXT(Z32,"m")) -> 2 | AF32: =IF(Z32="","","W"&WEEKNUM(Z32,2)) -> W8
A33: 45708 | B33: =IF(A33="","",YEAR(A33)) -> 2025 | C33: =IF(A33="","",TEXT(A33,"m")) -> 2 | D33: =IF(A33="","","W"&WEEKNUM(A33,2)) -> W8 | E33: Z24V002-2 | F33: LB101-7W-9W-15W壳体 | G33: 正泰 | H33: 宜胜照明1 | L33: 1. 大批量外箱包含我司产品标贴 2. 7W，9W和15W尾数箱壳体摆放不当，并使用单层外箱导致外箱破损，并且壳体刮花 | M33: 10326 | N33: 10326 | O33: 1 | P33: 售后客诉 | Q33: 包装 | R33: 产品为委外产品，发货使用原供应商包装未进行更换 | S33: 包装设计 | T33: 1.外箱标贴全部更换 2.破损程度大的外箱全部更换 3.轻度破损外箱封箱胶打补丁 4.结构件点货 | X33: 计划采购部 | Y33: 供方管理组 | Z33: 45708 | AA33: 45708 | AB33: =IF(A33="","",_xlfn.IFS(AND(Z33=0,AA33=0),"未回复",AND(AA33<>0,Z33=0),"报错",AND(Z33>=NOW(),Z33<>0,AA33=0),"正常进行中",AND(AA33<>0,Z33>=AA33),"按时关闭",AND(Z33<>0,Z33<=AA33),"延期关闭",AND(AA33=0,Z33<NOW()),"延期未关闭")) -> 按时关闭 | AD33: =IF(Z33="","",YEAR(Z33)) -> 2025 | AE33: =IF(Z33="","",TEXT(Z33,"m")) -> 2 | AF33: =IF(Z33="","","W"&WEEKNUM(Z33,2)) -> W8
A34: 45708 | B34: =IF(A34="","",YEAR(A34)) -> 2025 | C34: =IF(A34="","",TEXT(A34,"m")) -> 2 | D34: =IF(A34="","","W"&WEEKNUM(A34,2)) -> W8 | E34: A119S023 | F34: 180路灯 70W 4000K SPD | G34: 朗德万斯 | H34: 宜胜照明3 | L34: 客户在一个城镇完成了400套路灯的销售。这些灯具安装正确；然而，174只灯遇到了同样的问题。发现的问题是LED短路并烧坏。测试显示，驱动器向LED提供的是正确的电压，因此问题似乎源于LED模块本身; | M34: 400 | N34: 174 | O34: =IFERROR(N34/M34,"") -> 0.435 | P34: 售后客诉 | Q34: 功能 | R34: 目前收到的 3 个客退品，经过分析结果如下：1 个产品测试合格，2 个产品死灯，主要原因为 LED 灯板输入线虚焊导致不良。 电源线虚焊原因： 1：经查原工艺要求电烙铁温度为370±10℃，温度较低，焊接时Pcb焊盘未得到有效预热，导致虚焊。 2：操作人员焊接线到灯板上时，焊接时烙铁先与锡线接触，然后再与焊盘接触，导致虚焊 。 | S34: 过程工艺 | T34: 不良产品更换货或赔偿 | U34: 整改措施:1.焊接温度由19年的370±10℃变更为现在的400±10℃ 2：焊接工位更换为自动出锡电烙铁，自动电烙铁烙铁头会先接触焊盘预热，保证焊点可靠性 3.作业人员按工艺技术要求进行焊接作业，焊接完成后对焊点质量进行检查，确保焊点饱满、圆滑无毛刺、无虚焊、浮高、拉尖现象。 预防措施：1.每日开线前电烙铁温度进行点检，确保温度达到预设范围； 2.IPQC每日开工对设电烙铁点检情况进行核查 。 3.IPQC每2小时一次的巡检，要对重点岗位（焊接岗等）技术要求执行情况如焊接温度、焊接手法、焊接完成是否有进行目检动作等进行检查，确保生产要求执行； 4.对焊接岗位定人定岗，新员工需经过培训，有工程工艺确认合格后方可上岗； 5.准备一些常见不良图片示例放置于各岗位，增强员工质量意识。 | V34: 否 | W34: 工艺优化 | X34: 宜胜照明3 | Y34: 生产三 | Z34: 45708 | AA34: 45708 | AB34: =IF(A34="","",_xlfn.IFS(AND(Z34=0,AA34=0),"未回复",AND(AA34<>0,Z34=0),"报错",AND(Z34>=NOW(),Z34<>0,AA34=0),"正常进行中",AND(AA34<>0,Z34>=AA34),"按时关闭",AND(Z34<>0,Z34<=AA34),"延期关闭",AND(AA34=0,Z34<NOW()),"延期未关闭")) -> 按时关闭 | AD34: =IF(Z34="","",YEAR(Z34)) -> 2025 | AE34: =IF(Z34="","",TEXT(Z34,"m")) -> 2 | AF34: =IF(Z34="","","W"&WEEKNUM(Z34,2)) -> W8
A35: 45710 | B35: =IF(A35="","",YEAR(A35)) -> 2025 | C35: =IF(A35="","",TEXT(A35,"m")) -> 2 | D35: =IF(A35="","","W"&WEEKNUM(A35,2)) -> W8 | E35: T24K062 | F35: USB线路板 | G35: 优耐特 | H35: 宜胜照明1 | L35: 1.客户组装后发现充电时噪音大 2.板子无法给iphone15充电（客户指定要求） | M35: 9000 | N35: 9000 | O35: =IFERROR(N35/M35,"") -> 1 | P35: 售后客诉 | Q35: 功能 | R35: 电子设计方案问题 | S35: 电子设计 | T35: 客户未组装产品运回工厂返工，已组装产品有工厂安排人员至现场随线返工：1.噪音更换贴片电容2.更换C口小板 | U35: 变更电子方案 | V35: 是 | W35: 设计变更-预防 | X35: 宜胜照明1 | Y35: 研发十 | Z35: 45710 | AA35: 45710 | AB35: =IF(A35="","",_xlfn.IFS(AND(Z35=0,AA35=0),"未回复",AND(AA35<>0,Z35=0),"报错",AND(Z35>=NOW(),Z35<>0,AA35=0),"正常进行中",AND(AA35<>0,Z35>=AA35),"按时关闭",AND(Z35<>0,Z35<=AA35),"延期关闭",AND(AA35=0,Z35<NOW()),"延期未关闭")) -> 按时关闭 | AD35: =IF(Z35="","",YEAR(Z35)) -> 2025 | AE35: =IF(Z35="","",TEXT(Z35,"m")) -> 2 | AF35: =IF(Z35="","","W"&WEEKNUM(Z35,2)) -> W8
A36: 45344 | B36: =IF(A36="","",YEAR(A36)) -> 2024 | C36: =IF(A36="","",TEXT(A36,"m")) -> 2 | D36: =IF(A36="","","W"&WEEKNUM(A36,2)) -> W8 | E36: M22H036/M22H037 | F36: 1800W3-WFT-G2 AC100-240V 单开 | G36: 巴西527 | H36: 宜胜照明1 | L36: M2H036+M22H037-共16960ps开关，客户收到货发现玻璃脱落，且比例90%,客户库存5178pecs被封锁，导致客户无法供货给其零售商，造成10-12月销售损失，需赔3744美金，客诉描述此品质问题是由于生产端打胶未打好，导致玻璃大批脱落。 | M36: 16960 | N36: 5178 | O36: =IFERROR(N36/M36,"") -> 0.3053066 | P36: 售后客诉 | Q36: 内部 | R36: 胶水未打好，胶水没有完全固化干透进行组装，导致玻璃与面盖未贴牢。 | S36: 过程工艺 | T36: 需要我司免费提供5178pcs前面盖(玻璃+中框),并空运给客户 | U36: 1.壳体注塑工艺改良后续加强来料管控，整机配合检验；经确认现在来的物料无过紧的情况； 2.已与生产宣导，在组装安装时，如果有发现过紧的，需举手反馈给对应的线组长； 3. 打过胶后的半成品做好标识，时间记录好，确保胶水固化干的时间； 4.针对100PCS以下的尾数产品，线长贴尾数标识，送品质100%检验； 5.固化SOP，产线生产时，按照千分之五比例使用拉力器按照40N拉力进行检验； | V36: 否 | W36: 工艺优化 | X36: 宜胜照明1 | Y36: 生产一 | Z36: 45710 | AA36: 45710 | AB36: =IF(A36="","",_xlfn.IFS(AND(Z36=0,AA36=0),"未回复",AND(AA36<>0,Z36=0),"报错",AND(Z36>=NOW(),Z36<>0,AA36=0),"正常进行中",AND(AA36<>0,Z36>=AA36),"按时关闭",AND(Z36<>0,Z36<=AA36),"延期关闭",AND(AA36=0,Z36<NOW()),"延期未关闭")) -> 按时关闭 | AD36: =IF(Z36="","",YEAR(Z36)) -> 2025 | AE36: =IF(Z36="","",TEXT(Z36,"m")) -> 2 | AF36: =IF(Z36="","","W"&WEEKNUM(Z36,2)) -> W8
A37: 45712 | B37: =IF(A37="","",YEAR(A37)) -> 2025 | C37: =IF(A37="","",TEXT(A37,"m")) -> 2 | D37: =IF(A37="","","W"&WEEKNUM(A37,2)) -> W9 | E37: A122S108 | F37: LTI2711W4 -95W3-G1 | G37: 朗德万斯-巴西 | H37: 宜胜照明1 | L37: 客户反馈：我们面临最终客户索赔，在5月23日安装的154个灯具中，有88个LED HW T 100W 6500K（7019710），批次YS0123。 下面是更多细节： 它们是在安装过程中烧坏了还是同时出现了缺陷？他们是在这段时间烧坏了 灯具和屋顶之间的距离是多少？40厘米 该产品每天使用多少小时？24小时 灯具的电源电压是多少？220伏 灯具周围的环境温度~30℃ 电气装置是否用于连接中性线？这是有根据的吗？是的，它是接地的 电路中安装了多少个灯泡？每条电路22个 除了灯泡，这个电路中还有其他类型的负载吗？不 可以通过DHL向您发送6个样品进行技术分析吗？随附一些安装图片。 | M37: 1000 | N37: 88 | O37: =IFERROR(N37/M37,"") -> 0.088 | P37: 售后客诉 | Q37: 功能 | R37: 对不良样品进行拆机检验发现，侧线与灯头均有打火现象， 推测原因为侧线与灯头之间因接触不良而打火，瞬间电流过大，导致灯珠死灯；侧线与灯头接触不良原因：灯头为旋转灯头，侧线在装配过程未进行固定，灯头在旋转过程中侧线弯曲而进入螺纹间隙，导致接触不良，且此款灯泡功率100W，电流为457-800mA,本身运行过程功率与电流较大。 | S37: 过程工艺 | T37: 与客户沟通，对所有不良品进行补货赔偿处理，以减少客户损失，同时表达诚挚歉意。 | U37: 客户在本司所有大功率T灯采用切线工艺，如下图，侧线在装配过程中，先保证一部分线头露出灯头，待灯头压铆固定后，再将侧线露出灯头部分进行裁剪，保证侧线与灯头紧密接触，且灯头在装配过程中，侧线不会因旋转弯曲而产生间隙。 客户确认方案后，由产品端邮件通知生产进行SOP更新，后续LDWS大功率压铸铝T灯均采用切线工艺模式 | V37: 是 | W37: 防呆防错 | X37: 宜胜照明1 | Y37: 生产一 | Z37: 45713 | AA37: 45713 | AB37: =IF(A37="","",_xlfn.IFS(AND(Z37=0,AA37=0),"未回复",AND(AA37<>0,Z37=0),"报错",AND(Z37>=NOW(),Z37<>0,AA37=0),"正常进行中",AND(AA37<>0,Z37>=AA37),"按时关闭",AND(Z37<>0,Z37<=AA37),"延期关闭",AND(AA37=0,Z37<NOW()),"延期未关闭")) -> 按时关闭 | AD37: =IF(Z37="","",YEAR(Z37)) -> 2025 | AE37: =IF(Z37="","",TEXT(Z37,"m")) -> 2 | AF37: =IF(Z37="","","W"&WEEKNUM(Z37,2)) -> W9
A38: 45715 | B38: =IF(A38="","",YEAR(A38)) -> 2025 | C38: =IF(A38="","",TEXT(A38,"m")) -> 2 | D38: =IF(A38="","","W"&WEEKNUM(A38,2)) -> W9 | E38: S24J0821 | F38: 面壁开关 | G38: 阿根廷235 | H38: 宜胜照明1 | L38: 彩盒里发现其他PCB板子，彩盒有装错货现象 | M38: 17960 | O38: =IFERROR(N38/M38,"") -> 0 | P38: 售后客诉 | Q38: 包装 | R38: 1.物料标识管控不够细致，导致在包装过程彩盒中混入其他型号板子未被发现流出；彩盒装错货现象暂未手相关信息及图片 | S38: 人员作业 | V38: 否 | W38: 人员培训 | X38: 宜胜照明1 | Y38: 生产一 | Z38: 45716 | AA38: 45716 | AB38: =IF(A38="","",_xlfn.IFS(AND(Z38=0,AA38=0),"未回复",AND(AA38<>0,Z38=0),"报错",AND(Z38>=NOW(),Z38<>0,AA38=0),"正常进行中",AND(AA38<>0,Z38>=AA38),"按时关闭",AND(Z38<>0,Z38<=AA38),"延期关闭",AND(AA38=0,Z38<NOW()),"延期未关闭")) -> 按时关闭 | AD38: =IF(Z38="","",YEAR(Z38)) -> 2025 | AE38: =IF(Z38="","",TEXT(Z38,"m")) -> 2 | AF38: =IF(Z38="","","W"&WEEKNUM(Z38,2)) -> W9
A39: 45715 | B39: =IF(A39="","",YEAR(A39)) -> 2025 | C39: =IF(A39="","",TEXT(A39,"m")) -> 2 | D39: =IF(A39="","","W"&WEEKNUM(A39,2)) -> W9 | E39: Z24D042 | F39: LC2221W2-8W3-G1 | G39: 阿联酋689 | H39: 宜胜照明1 | L39: 10月份出货的灯杯，客户售卖出去使用一个月大量灭灯；现客户要求赔货25000只 | M39: 50000 | N39: 25000 | O39: =IFERROR(N39/M39,"") -> 0.5 | P39: 售后客诉 | Q39: 功能 | R39: 委外安富工厂经查是以下问题导致：1：端子松动引线掉落2：端子未焊接牢靠3：铆钉没有压到位 | S39: 过程工艺 | T39: 赔货处理 | U39: 1.针对灯头压铆不良，后续采取压铆两次，两面压铆，避免因压铆不良导致接触不良灯不亮得现象； 2.焊接工艺不良，此批次产品为委外供应商生产，后续对供应商选择，需要经过评估其生产工艺、质量体系是否符合公司标准，并定期进行审核；后续订单安排在宇兴宜胜进行生产。 | V39: 是 | W39: 其它 | X39: 计划采购部 | Y39: 供方管理组 | Z39: 45716 | AA39: 45716 | AB39: =IF(A39="","",_xlfn.IFS(AND(Z39=0,AA39=0),"未回复",AND(AA39<>0,Z39=0),"报错",AND(Z39>=NOW(),Z39<>0,AA39=0),"正常进行中",AND(AA39<>0,Z39>=AA39),"按时关闭",AND(Z39<>0,Z39<=AA39),"延期关闭",AND(AA39=0,Z39<NOW()),"延期未关闭")) -> 按时关闭 | AD39: =IF(Z39="","",YEAR(Z39)) -> 2025 | AE39: =IF(Z39="","",TEXT(Z39,"m")) -> 2 | AF39: =IF(Z39="","","W"&WEEKNUM(Z39,2)) -> W9
A40: 45715 | B40: =IF(A40="","",YEAR(A40)) -> 2025 | C40: =IF(A40="","",TEXT(A40,"m")) -> 2 | D40: =IF(A40="","","W"&WEEKNUM(A40,2)) -> W9 | E40: Z24D044 | F40: LC2221W2-8W3-G1 | G40: 阿联酋689 | H40: 宜胜照明1 | L40: 10月份出货的灯杯，客户售卖出去使用一个月大量灭灯；现客户要求赔货15000只 | M40: 30000 | N40: 15000 | O40: =IFERROR(N40/M40,"") -> 0.5 | P40: 售后客诉 | Q40: 功能 | R40: 委外安富工厂，经查是以下问题导致：1：端子松动引线掉落2：端子未焊接牢靠3：铆钉没有压到位 | S40: 过程工艺 | T40: 赔货处理 | U40: 1.针对灯头压铆不良，后续采取压铆两次，两面压铆，避免因压铆不良导致接触不良灯不亮得现象； 2.焊接工艺不良，此批次产品为委外供应商生产，后续对供应商选择，需要经过评估其生产工艺、质量体系是否符合公司标准，并定期进行审核；后续订单安排在宇兴宜胜进行生产。 | V40: 是 | W40: 其它 | X40: 计划采购部 | Y40: 供方管理组 | Z40: 45716 | AA40: 45716 | AB40: =IF(A40="","",_xlfn.IFS(AND(Z40=0,AA40=0),"未回复",AND(AA40<>0,Z40=0),"报错",AND(Z40>=NOW(),Z40<>0,AA40=0),"正常进行中",AND(AA40<>0,Z40>=AA40),"按时关闭",AND(Z40<>0,Z40<=AA40),"延期关闭",AND(AA40=0,Z40<NOW()),"延期未关闭")) -> 按时关闭 | AD40: =IF(Z40="","",YEAR(Z40)) -> 2025 | AE40: =IF(Z40="","",TEXT(Z40,"m")) -> 2 | AF40: =IF(Z40="","","W"&WEEKNUM(Z40,2)) -> W9
A41: 45715 | B41: =IF(A41="","",YEAR(A41)) -> 2025 | C41: =IF(A41="","",TEXT(A41,"m")) -> 2 | D41: =IF(A41="","","W"&WEEKNUM(A41,2)) -> W9 | E41: D23A016-4 | F41: 铝底盘 | G41: 瑞士070 | H41: 宜胜照明2 | L41: 客户反馈铝底盘螺孔有塑粉无螺孔，目前还有库存800pcs，比例未提供，只是说经第一批次订单改善后还有该现象存在 | O41: =IFERROR(N41/M41,"") | P41: 售后客诉 | Q41: 外观 | R41: 喷涂残留塑粉，无螺纹未发现 | S41: 过程工艺 | T41: 提供处理方案和视频给客户 | U41: 喷涂前加6*2.5mm橡胶塞堵螺孔，堵后用手拉橡胶塞，确保堵严实，喷涂后通止规全检 | V41: 否 | W41: 工艺优化 | X41: 宜胜照明3 | Y41: 生产三 | Z41: 45716 | AA41: 45716 | AB41: =IF(A41="","",_xlfn.IFS(AND(Z41=0,AA41=0),"未回复",AND(AA41<>0,Z41=0),"报错",AND(Z41>=NOW(),Z41<>0,AA41=0),"正常进行中",AND(AA41<>0,Z41>=AA41),"按时关闭",AND(Z41<>0,Z41<=AA41),"延期关闭",AND(AA41=0,Z41<NOW()),"延期未关闭")) -> 按时关闭 | AD41: =IF(Z41="","",YEAR(Z41)) -> 2025 | AE41: =IF(Z41="","",TEXT(Z41,"m")) -> 2 | AF41: =IF(Z41="","","W"&WEEKNUM(Z41,2)) -> W9
A42: 45727 | B42: =IF(A42="","",YEAR(A42)) -> 2025 | C42: =IF(A42="","",TEXT(A42,"m")) -> 3 | D42: =IF(A42="","","W"&WEEKNUM(A42,2)) -> W11 | E42: O23D019/23/34/38/45 | F42: KSD241C控制器 | G42: 捷克028 | H42: 宜胜照明1 | J42: 唐国强 | L42: 户反馈智能驱动在客户端从23年开始陆续出现异常，现退回不良153PCS，查询订单追溯2023年至2024年6月O23D019/23/34/38/45订单累计出货8000PCS，不良率1.91% | M42: 8000 | N42: 153 | O42: =IFERROR(N42/M42,"") -> 0.019125 | P42: 售后客诉 | Q42: 功能 | R42: 对退回不良样品进行拆解分析： 静态检查： 1、打开外壳后目检器件是否存在缺漏、焊接不良，发现有二极管虚焊、散热块未接地现象； 2、用万用表检测输出端MOS管DS脚之间是否导通，发现存在MOS管击穿而导通现象； 上电测试 1、将以上修复驱动上电220V，用万用表测试输出端电解（银色固态电解）为24V，以及DC-DC输出（模块旁小电解）为3.3V，输出电压及工作电压正常； 2、将驱动异常修复后进行连接灯带进行老化测试，以及开关功能测试，驱动功能恢复正常 结论：根据不良样品分析，驱动异常主要原因为二极管虚焊、散热块接地焊接脱落以及MOS管击穿造成；其中二极管虚焊和散热块接地焊点脱落为过炉后修补焊人员遗漏或未修补到位导致流出，MOS管击穿推测原因为修补焊过程锡渣、连锡等造成短路，在测试岗位上电后因短路而造成击穿。 | S42: 人员作业 | T42: 退回不良品返工维修，维修后需连接灯带老化测试其功能 | U42: 1.电子车间贴片上线前需对设备进行检查，仔细核对是否按工艺要求进行设置参数，IPQC首件确认合格后方可批量生产； 2.过炉后对PCBA板进行修补焊与外观目检，以及功能测试，确保产品功能正常； 3.控制器出货前与带进行老化测试，以及开关功能测试。 1.焊接人员定期进行专业技能培训和不良识别能力培训并进行考核； 2.对目检外观定期组织盲考，盲考连续三次不通过调岗处理； 3.与供应商建立信息共享，保证来料质量，如散热块来料油污，也可能导致焊接不牢脱落。 | V42: 否 | W42: 人员培训 | X42: 宜胜照明1 | Y42: 生产一 | Z42: 45727 | AA42: 45727 | AB42: =IF(A42="","",_xlfn.IFS(AND(Z42=0,AA42=0),"未回复",AND(AA42<>0,Z42=0),"报错",AND(Z42>=NOW(),Z42<>0,AA42=0),"正常进行中",AND(AA42<>0,Z42>=AA42),"按时关闭",AND(Z42<>0,Z42<=AA42),"延期关闭",AND(AA42=0,Z42<NOW()),"延期未关闭")) -> 按时关闭 | AD42: =IF(Z42="","",YEAR(Z42)) -> 2025 | AE42: =IF(Z42="","",TEXT(Z42,"m")) -> 3 | AF42: =IF(Z42="","","W"&WEEKNUM(Z42,2)) -> W11
A43: 45741 | B43: =IF(A43="","",YEAR(A43)) -> 2025 | C43: =IF(A43="","",TEXT(A43,"m")) -> 3 | D43: =IF(A43="","","W"&WEEKNUM(A43,2)) -> W13 | E43: Z23T017 | F43: LC1221C-7W2-HL-G2 | G43: 阿尔及利亚075 | H43: 宜胜照明1 | L43: 2024年出货订单， 此灯杯为3年质保 过CE方案，客户收到货后销售半年收到大量退货，故自己测试过后发现存在两种问题： 1. 灯脚接触不良 2. 灯杯低亮，瓦数接近0W 客户共寄5个样品，其中三个低亮，两个接触不良，据客户说目前的不良达到80%以上 样品宇兴测试结果相同，灯脚线过短，元器件存在虚焊（重新焊接后瓦数正常） 客户诉求赔货100% | M43: 15000 | N43: 12000 | O43: =IFERROR(N43/M43,"") -> 0.8 | P43: 售后客诉 | Q43: 功能 | R43: 1.对不良样品拆机分析，三个低亮为电解电容虚焊，补焊后功能正常如图一； 2.灯脚接触不良，为灯脚压铆不良，拆机后发现灯脚线直接脱落，推测原因为生产过程设备压力不足或压铆时间过短等，导致接触不良电气连接异常 | S43: 过程工艺 | T43: 与客户沟通，确认实际不良比例，根据实际不良比例进行赔货 | U43: 纠正措施：1.针对灯头压铆不良，后续采取压铆两次，两面压铆，设备调试完成后前5pcs确认灯脚压铆是否OK,是否有灯脚线脱落现象，避免因压铆不良导致接触不良灯不亮得现象； 2.电解电容虚焊，此批次PCB板为委外供应商插件，后续对供应商选择，需要经过评估其生产工艺、质量体系是否符合公司标准，并定期进行审核。 预防措施：1.定期保养设备，检查压铆设备、贴片设备的气压系统和机械传动部件等，确保设备性能稳定； 2.首件检验与过程巡检：每批次生产前做首件，全面检查焊接质量和压铆深度等，生产过程定时巡检，及时发现和处理异常问题 3.后续使用老化设备进行老化点亮，可自动识别功率异常等不良现象，防批量流出 | V43: 否 | W43: 流程优化 | X43: 宜胜照明1 | Y43: 生产一 | Z43: 45741 | AA43: 45741 | AB43: =IF(A43="","",_xlfn.IFS(AND(Z43=0,AA43=0),"未回复",AND(AA43<>0,Z43=0),"报错",AND(Z43>=NOW(),Z43<>0,AA43=0),"正常进行中",AND(AA43<>0,Z43>=AA43),"按时关闭",AND(Z43<>0,Z43<=AA43),"延期关闭",AND(AA43=0,Z43<NOW()),"延期未关闭")) -> 按时关闭 | AD43: =IF(Z43="","",YEAR(Z43)) -> 2025 | AE43: =IF(Z43="","",TEXT(Z43,"m")) -> 3 | AF43: =IF(Z43="","","W"&WEEKNUM(Z43,2)) -> W13
A44: 45772 | B44: =IF(A44="","",YEAR(A44)) -> 2025 | C44: =IF(A44="","",TEXT(A44,"m")) -> 4 | D44: =IF(A44="","","W"&WEEKNUM(A44,2)) -> W17 | E44: Z24K039 | F44: LC1203C-4.9W2-G7 | G44: 南非729 | H44: 宜胜照明1 | L44: 客诉灯不亮，具体不良比例未提供 | M44: 17935 | P44: 售后客诉 | Q44: 功能 | R44: 灯板端子脱落（委外） | S44: 来料不良 | T44: 赔货处理 | U44: 委外订单，工厂生产产品验证无此问题，非必要不委外生产 | V44: 否 | X44: 其它事业部 | Y44: 供方管理组 | Z44: 45772 | AA44: 45772 | AB44: =IF(A44="","",_xlfn.IFS(AND(Z44=0,AA44=0),"未回复",AND(AA44<>0,Z44=0),"报错",AND(Z44>=NOW(),Z44<>0,AA44=0),"正常进行中",AND(AA44<>0,Z44>=AA44),"按时关闭",AND(Z44<>0,Z44<=AA44),"延期关闭",AND(AA44=0,Z44<NOW()),"延期未关闭")) -> 按时关闭 | AD44: =IF(Z44="","",YEAR(Z44)) -> 2025 | AE44: =IF(Z44="","",TEXT(Z44,"m")) -> 4 | AF44: =IF(Z44="","","W"&WEEKNUM(Z44,2)) -> W17
A45: 45772 | B45: =IF(A45="","",YEAR(A45)) -> 2025 | C45: =IF(A45="","",TEXT(A45,"m")) -> 4 | D45: =IF(A45="","","W"&WEEKNUM(A45,2)) -> W17 | E45: Z24D036 | F45: LC1103L3-7W2-G7/LTC1161L3-50W2-G3H/ LTC1161L3-25W2-G3C | G45: 黎巴嫩130 | H45: 宜胜照明1 | L45: 客诉反馈订单Z24D036 灯杯LC1103L3-7W2-G7/T灯LTC1161L3-50W2-G3H/T灯LTC1161L3-25W2-G3C均发现灯不亮现象,比例约25% | M45: 11000 | O45: 0.25 | P45: 售后客诉 | Q45: 功能 | R45: 均为端子脱落（委外） | S45: 来料不良 | T45: 赔货处理 | U45: 委外订单，工厂生产产品验证无此问题，非必要不委外生产 | V45: 否 | X45: 其它事业部 | Y45: 供方管理组 | Z45: 45772 | AA45: 45772 | AB45: =IF(A45="","",_xlfn.IFS(AND(Z45=0,AA45=0),"未回复",AND(AA45<>0,Z45=0),"报错",AND(Z45>=NOW(),Z45<>0,AA45=0),"正常进行中",AND(AA45<>0,Z45>=AA45),"按时关闭",AND(Z45<>0,Z45<=AA45),"延期关闭",AND(AA45=0,Z45<NOW()),"延期未关闭")) -> 按时关闭 | AD45: =IF(Z45="","",YEAR(Z45)) -> 2025 | AE45: =IF(Z45="","",TEXT(Z45,"m")) -> 4 | AF45: =IF(Z45="","","W"&WEEKNUM(Z45,2)) -> W17
A46: 45814 | B46: =IF(A46="","",YEAR(A46)) -> 2025 | C46: =IF(A46="","",TEXT(A46,"m")) -> 6 | D46: =IF(A46="","","W"&WEEKNUM(A46,2)) -> W23 | E46: R21X0719 | F46: HL118C-150W3-LEN-G1 | G46: IEK | H46: 宜胜照明3 | L46: 客户反馈21年7月订单HL118C-150W3-LEN-G1高顶灯有灯珠烧毁不亮现象，在5年质保期以内 | O46: =IFERROR(N46/M46,"") | P46: 售后客诉 | Q46: 功能 | R46: 灯珠达到寿命周期临界点，内部芯片、荧光粉等核心材料老化导致性能下降发热烧毁，且有可能超过额定工作条件 | S46: 电子设计 | T46: 赔货处理 | U46: 1.研发验证产品使用寿命 2.可要求供应商提供LED灯珠使用寿命报告或可靠性数据 | V46: 否 | X46: 宜胜照明3 | Y46: 研发一 | Z46: 45815 | AA46: 45815 | AB46: =IF(A46="","",_xlfn.IFS(AND(Z46=0,AA46=0),"未回复",AND(AA46<>0,Z46=0),"报错",AND(Z46>=NOW(),Z46<>0,AA46=0),"正常进行中",AND(AA46<>0,Z46>=AA46),"按时关闭",AND(Z46<>0,Z46<=AA46),"延期关闭",AND(AA46=0,Z46<NOW()),"延期未关闭")) -> 按时关闭 | AD46: =IF(Z46="","",YEAR(Z46)) -> 2025 | AE46: =IF(Z46="","",TEXT(Z46,"m")) -> 6 | AF46: =IF(Z46="","","W"&WEEKNUM(Z46,2)) -> W23
A47: 45814 | B47: =IF(A47="","",YEAR(A47)) -> 2025 | C47: =IF(A47="","",TEXT(A47,"m")) -> 6 | D47: =IF(A47="","","W"&WEEKNUM(A47,2)) -> W23 | E47: Z24D054 | F47: LG271C 100W/150W/200W CCT | G47: 沙特阿拉伯426 | H47: 宜胜照明3 | L47: 客户样品间点亮的三款不同瓦数投光灯灯珠有部分不亮，拆机发现内部芯片烧毁（原因不明） | O47: =IFERROR(N47/M47,"") | P47: 售后客诉 | Q47: 功能 | R47: 研发回复为客户样品间电路及不同较多，可能导致瞬间电流过大导致芯片烧毁 | S47: 其它 | T47: 同批次客户卖出产品暂未收到其他不良反馈，洪总已与客户沟通，后续改善 | U47: 1.生产按SOP严格执行产品老化 2.研发改善方案，提升产品适应复杂电路环境方面性能 | V47: 是 | W47: 设计变更-预防 | X47: 宜胜照明3 | Y47: 研发一 | Z47: 45824 | AA47: 45824 | AB47: =IF(A47="","",_xlfn.IFS(AND(Z47=0,AA47=0),"未回复",AND(AA47<>0,Z47=0),"报错",AND(Z47>=NOW(),Z47<>0,AA47=0),"正常进行中",AND(AA47<>0,Z47>=AA47),"按时关闭",AND(Z47<>0,Z47<=AA47),"延期关闭",AND(AA47=0,Z47<NOW()),"延期未关闭")) -> 按时关闭 | AD47: =IF(Z47="","",YEAR(Z47)) -> 2025 | AE47: =IF(Z47="","",TEXT(Z47,"m")) -> 6 | AF47: =IF(Z47="","","W"&WEEKNUM(Z47,2)) -> W25
A48: 45812 | B48: =IF(A48="","",YEAR(A48)) -> 2025 | C48: =IF(A48="","",TEXT(A48,"m")) -> 6 | D48: =IF(A48="","","W"&WEEKNUM(A48,2)) -> W23 | E48: A124S171 | F48: A60 7W 球泡灯 | G48: 中国1796 | H48: 宜胜照明1 | L48: 客户反馈订单A124S171 A60球泡灯有标贴与实物不符，混装现象 | O48: =IFERROR(N48/M48,"") | P48: 售后客诉 | Q48: 其它 | R48: 1.换线未进行清线 2.款数多，客户货号/物料号/产品型号区分困难 | S48: 其它 | T48: 赔货处理 | U48: 1.现场清理：换线产品时先检查生产区域是否有上一款产品与物料未清理干净，清理完成再进行换线生产； 2.标贴使用物料盒进行定点定位放置 3.对于型号较多产品，坚持1小时的资料核对和相关信息的培训 4.后续产品端将客户货号、物料号、产品型号对应表整理好放置工艺单里，方便生产培训核对 | V48: 否 | W48: 流程优化 | X48: 宜胜照明1 | Y48: 生产一 | Z48: 45813 | AA48: 45813 | AB48: =IF(A48="","",_xlfn.IFS(AND(Z48=0,AA48=0),"未回复",AND(AA48<>0,Z48=0),"报错",AND(Z48>=NOW(),Z48<>0,AA48=0),"正常进行中",AND(AA48<>0,Z48>=AA48),"按时关闭",AND(Z48<>0,Z48<=AA48),"延期关闭",AND(AA48=0,Z48<NOW()),"延期未关闭")) -> 按时关闭 | AD48: =IF(Z48="","",YEAR(Z48)) -> 2025 | AE48: =IF(Z48="","",TEXT(Z48,"m")) -> 6 | AF48: =IF(Z48="","","W"&WEEKNUM(Z48,2)) -> W23
A49: 45818 | B49: =IF(A49="","",YEAR(A49)) -> 2025 | C49: =IF(A49="","",TEXT(A49,"m")) -> 6 | D49: =IF(A49="","","W"&WEEKNUM(A49,2)) -> W24 | E49: A25G001 | F49: ST-LB2101 P-9W1-BLB T-G1(A60) | G49: 日本315 | H49: 宜胜照明1 | L49: 从大货抽取100pcs送客户做为产前样，客户反馈如下问题： 1.彩盒开口破损6pcs 2.1pcs彩盒内说明书遗落在内箱彩盒表面 3.泡壳与壳体之间溢胶1pcs 4.彩盒装盒顺序错误1pcs 5.产品表面有毛发、残胶 6.泡壳黑点2pcs 客户要求以上问题不良控制千分之4 | O49: =IFERROR(N49/M49,"") | P49: 样品确认 | Q49: 外观 | R49: 1.泡壳黑点为来料不良； 2.溢胶为固定泡壳胶水在压合过程会有少量溢出，后工序未清理干净 3.彩盒开口破损、彩盒内说明书遗落外箱内、装盒顺序错误等推测为二次拆箱检查过程造成（产线、成品检验或送样前相关人员查验样品情况等） | S49: 其它 | T49: / | U49: 1.来料黑点供应商改善，研发端新建料号，来料检验按千分之4管控（产品端需确认标准后正式通知） 2.产线残胶清理、检验按千分4标准执行（产品端需确认标准后正式通知） 3.成品检验在检验完成后复原包装，并拍照留底 | V49: 否 | X49: 宜胜照明1 | Y49: 生产一 | Z49: 45820 | AA49: 45820 | AB49: =IF(A49="","",_xlfn.IFS(AND(Z49=0,AA49=0),"未回复",AND(AA49<>0,Z49=0),"报错",AND(Z49>=NOW(),Z49<>0,AA49=0),"正常进行中",AND(AA49<>0,Z49>=AA49),"按时关闭",AND(Z49<>0,Z49<=AA49),"延期关闭",AND(AA49=0,Z49<NOW()),"延期未关闭")) -> 按时关闭 | AD49: =IF(Z49="","",YEAR(Z49)) -> 2025 | AE49: =IF(Z49="","",TEXT(Z49,"m")) -> 6 | AF49: =IF(Z49="","","W"&WEEKNUM(Z49,2)) -> W24
A50: 45828 | B50: =IF(A50="","",YEAR(A50)) -> 2025 | C50: =IF(A50="","",TEXT(A50,"m")) -> 6 | D50: =IF(A50="","","W"&WEEKNUM(A50,2)) -> W25 | F50: 2开一插墙壁开关 | G50: 巴西527 | H50: 宜胜照明1 | L50: 客户测试1pcs产品功能异常，经拆机发现为5V继电器用为12V继电器，现客户已维修更换5V继电器，无法查看是否为由焊接痕迹，不能确定是否是维修品 | N50: 1pcs | O50: =IFERROR(N50/M50,"") | P50: 售后客诉 | Q50: 功能 | R50: 维修不良品未测试流出（研发与工艺确认产线测试工装可识别该不良现象） | S50: 人员作业 | T50: / | U50: 1.生产根据不良数量按工单提交维修不良配件需求流程，维修按工单领料并进行不良品的维修（图一为超买申请单示例） 2..开关类产品维修后增加测试确认功能是否正常(图二） 3.维修品需按大货标准重新流线测试，检验后再进行包装； | V50: 否 | W50: 工艺优化 | X50: 宜胜照明1 | Y50: 生产一 | Z50: 45838 | AA50: 45838 | AB50: =IF(A50="","",_xlfn.IFS(AND(Z50=0,AA50=0),"未回复",AND(AA50<>0,Z50=0),"报错",AND(Z50>=NOW(),Z50<>0,AA50=0),"正常进行中",AND(AA50<>0,Z50>=AA50),"按时关闭",AND(Z50<>0,Z50<=AA50),"延期关闭",AND(AA50=0,Z50<NOW()),"延期未关闭")) -> 按时关闭 | AD50: =IF(Z50="","",YEAR(Z50)) -> 2025 | AE50: =IF(Z50="","",TEXT(Z50,"m")) -> 6 | AF50: =IF(Z50="","","W"&WEEKNUM(Z50,2)) -> W27
A51: 45828 | B51: =IF(A51="","",YEAR(A51)) -> 2025 | C51: =IF(A51="","",TEXT(A51,"m")) -> 6 | D51: =IF(A51="","","W"&WEEKNUM(A51,2)) -> W25 | F51: CE2176-18W吸顶灯 | G51: 中国1796 | H51: 宜胜照明3 | L51: 业务端收到朗德万斯反馈，A123S111/S112有部分产品灯珠出现不亮的情况，经初步分析是电子部分0Ω电阻失效所导致 | O51: =IFERROR(N51/M51,"") | P51: 售后客诉 | R51: 灯条装配于圆形壳体侧壁一圈，受应力及长期使用发热影响，导致0R电阻焊点脱落：14W---10030300070---有51010200078 电阻-片阻 RES-SMD-1206-0R-5%-0.25W 18W---10030300024---有51010200078 电阻-片阻 RES-SMD-1206-0R-5%-0.25W 24W---10030300025---无 32W---10030300026---有51010200078 电阻-片阻 RES-SMD-1206-0R-5%-0.25W | S51: 结构设计 | T51: 1.库存排查：宜胜仓库数量0PC 2.在制订单 A125S115+116-2 ，A125S89+91+96+97+98+100-1暂停生产 | U51: 1.灯条上0R电阻更改为跳线结构 2.增加保护电容，预防灯珠在长期工作热胀冷缩的情况下损坏 | V51: 是 | W51: 设计变更-预防 | X51: 宜胜照明2 | Y51: 研发九 | Z51: 45831 | AA51: 45831 | AB51: =IF(A51="","",_xlfn.IFS(AND(Z51=0,AA51=0),"未回复",AND(AA51<>0,Z51=0),"报错",AND(Z51>=NOW(),Z51<>0,AA51=0),"正常进行中",AND(AA51<>0,Z51>=AA51),"按时关闭",AND(Z51<>0,Z51<=AA51),"延期关闭",AND(AA51=0,Z51<NOW()),"延期未关闭")) -> 按时关闭 | AD51: =IF(Z51="","",YEAR(Z51)) -> 2025 | AE51: =IF(Z51="","",TEXT(Z51,"m")) -> 6 | AF51: =IF(Z51="","","W"&WEEKNUM(Z51,2)) -> W26
A52: 45832 | B52: =IF(A52="","",YEAR(A52)) -> 2025 | C52: =IF(A52="","",TEXT(A52,"m")) -> 6 | D52: =IF(A52="","","W"&WEEKNUM(A52,2)) -> W26 | E52: R24P0419-4 | F52: LB1103E1-9W2-G6L | G52: 俄罗斯1804 | H52: 宜胜照明1 | L52: 产品彩盒包装错误。3000K（458841）产品用4000K（458842）彩盒包装，客户统计3000K包装错误数量为1564pcs | N52: 1564 | O52: =IFERROR(N52/M52,"") | P52: 售后客诉 | R52: 彩盒混料，人员未核对彩盒正确性 | S52: 人员作业 | T52: 寄送正确包装。后续寄送费用（5000）、客户索赔金额、客户自行包装费用均由工厂承担。 | U52: 1 物料员在领料时必须每一箱需要查看物料号， 2 操机手在加料时，必须核对瓦数，色温,100个一核对 3 打包岗位必须10个查看瓦数或者条形码 4 同时修改SOP，将以上检查内容添加至SOP 5 车间培训相关岗位，检查落实，定期抽查 | V52: 否 | W52: 人员培训 | X52: 宜胜照明1 | Y52: 生产一 | Z52: 45833 | AA52: 45833 | AB52: =IF(A52="","",_xlfn.IFS(AND(Z52=0,AA52=0),"未回复",AND(AA52<>0,Z52=0),"报错",AND(Z52>=NOW(),Z52<>0,AA52=0),"正常进行中",AND(AA52<>0,Z52>=AA52),"按时关闭",AND(Z52<>0,Z52<=AA52),"延期关闭",AND(AA52=0,Z52<NOW()),"延期未关闭")) -> 按时关闭 | AD52: =IF(Z52="","",YEAR(Z52)) -> 2025 | AE52: =IF(Z52="","",TEXT(Z52,"m")) -> 6 | AF52: =IF(Z52="","","W"&WEEKNUM(Z52,2)) -> W26
A53: 45832 | B53: =IF(A53="","",YEAR(A53)) -> 2025 | C53: =IF(A53="","",TEXT(A53,"m")) -> 6 | D53: =IF(A53="","","W"&WEEKNUM(A53,2)) -> W26 | E53: A124S186 | F53: GU10 3000K | G53: 中国1796 | H53: 宜胜照明1 | L53: 在A124S186订单中，再次发现货物装错的问题： AC602960055：包装方式为5pcs/热缩，包装中有混淆AC603360155 | P53: 售后客诉 | Q53: 包装 | R53: 彩盒混料，人员未核对彩盒正确性 | S53: 人员作业 | T53: / | U53: 1 物料员在领料时必须每一箱需要查看物料号， 2 操机手在加料时，必须核对瓦数，色温,100个一核对 3 打包岗位必须10个查看瓦数或者条形码 4 同时修改SOP，将以上检查内容添加至SOP 5 车间培训相关岗位，检查落实，定期抽查 | V53: 否 | W53: 人员培训 | X53: 宜胜照明1 | Y53: 生产一 | Z53: 45833 | AA53: 45833 | AB53: =IF(A53="","",_xlfn.IFS(AND(Z53=0,AA53=0),"未回复",AND(AA53<>0,Z53=0),"报错",AND(Z53>=NOW(),Z53<>0,AA53=0),"正常进行中",AND(AA53<>0,Z53>=AA53),"按时关闭",AND(Z53<>0,Z53<=AA53),"延期关闭",AND(AA53=0,Z53<NOW()),"延期未关闭")) -> 按时关闭 | AD53: =IF(Z53="","",YEAR(Z53)) -> 2025 | AE53: =IF(Z53="","",TEXT(Z53,"m")) -> 6 | AF53: =IF(Z53="","","W"&WEEKNUM(Z53,2)) -> W26
A54: 45835 | B54: =IF(A54="","",YEAR(A54)) -> 2025 | C54: =IF(A54="","",TEXT(A54,"m")) -> 6 | D54: =IF(A54="","","W"&WEEKNUM(A54,2)) -> W26 | F54: CE2176吸顶灯 | H54: 宜胜照明3 | L54: 发光面白印 | O54: =IFERROR(N54/M54,"") | P54: 售后客诉 | Q54: 功能 | R54: 开始的时候没有加上eva棉片，导致后面的灯体会挤压到反光纸，出现白痕 | S54: 结构设计 | T54: / | U54: 已增加EVA棉 | V54: 是 | W54: 设计变更-预防 | X54: 宜胜照明3 | Y54: 生产三 | Z54: 45842 | AA54: 45842 | AB54: =IF(A54="","",_xlfn.IFS(AND(Z54=0,AA54=0),"未回复",AND(AA54<>0,Z54=0),"报错",AND(Z54>=NOW(),Z54<>0,AA54=0),"正常进行中",AND(AA54<>0,Z54>=AA54),"按时关闭",AND(Z54<>0,Z54<=AA54),"延期关闭",AND(AA54=0,Z54<NOW()),"延期未关闭")) -> 按时关闭 | AD54: =IF(Z54="","",YEAR(Z54)) -> 2025 | AE54: =IF(Z54="","",TEXT(Z54,"m")) -> 7 | AF54: =IF(Z54="","","W"&WEEKNUM(Z54,2)) -> W27
A55: 45868 | B55: =IF(A55="","",YEAR(A55)) -> 2025 | C55: =IF(A55="","",TEXT(A55,"m")) -> 7 | D55: =IF(A55="","","W"&WEEKNUM(A55,2)) -> W31 | E55: A224P012 | F55: BL212SA-1 5W2-PIR-T DC-AUD防潮灯 | G55: 澳大利亚1160 | H55: 宜胜照明3 | I55: 潘凌燕 | J55: 邵心妮 | K55: 王超 | L55: 感应功能失效，无感应情况下40秒后灯熄灭2秒会再次亮起（正常情况是无感应30秒左右会熄灭，再次感应才会再亮），客户终端反馈，客户抽库存两箱发现了两个 | M55: 1100 | O55: =IFERROR(N55/M55,"") -> 0 | P55: 售后客诉 | Q55: 功能 | R55: 防潮灯自身光源干扰感应器，导致感应功能异常：使用不透光纸张将防潮灯光源与感应器探头之间进行遮挡，感应功能恢复正常 | S55: 电子设计 | U55: 菲尼尔透镜更换成黑色透镜，初步验证能有效过滤光强的干扰，但整体灯具外观会有改变 | V55: 是 | W55: 设计变更-预防 | X55: 宜胜照明3 | Y55: 研发二 | Z55: 45879 | AA55: 45879 | AB55: =IF(A55="","",_xlfn.IFS(AND(Z55=0,AA55=0),"未回复",AND(AA55<>0,Z55=0),"报错",AND(Z55>=NOW(),Z55<>0,AA55=0),"正常进行中",AND(AA55<>0,Z55>=AA55),"按时关闭",AND(Z55<>0,Z55<=AA55),"延期关闭",AND(AA55=0,Z55<NOW()),"延期未关闭")) -> 按时关闭 | AD55: =IF(Z55="","",YEAR(Z55)) -> 2025 | AE55: =IF(Z55="","",TEXT(Z55,"m")) -> 8 | AF55: =IF(Z55="","","W"&WEEKNUM(Z55,2)) -> W32
A56: 45881 | B56: =IF(A56="","",YEAR(A56)) -> 2025 | C56: =IF(A56="","",TEXT(A56,"m")) -> 8 | D56: =IF(A56="","","W"&WEEKNUM(A56,2)) -> W33 | E56: M25A002-1 | F56: EWS 1002 BR | G56: 巴西527 | H56: 宜胜照明1 | I56: 徐赢意 | J56: 赖长金 | K56: 丁亚双 | L56: 客诉反馈订单M25A002 客户货号EWS 1002 BR墙壁开关接线螺丝有生锈现象，抽检13pcs，8pcs生锈。 | O56: =IFERROR(N56/M56,"") | P56: 售后客诉 | Q56: 外观 | R56: 墙壁开关接线端子螺丝为铁镀镍，盐雾试验符合要求，装配过程机械损伤镀层，暴露基材吸收水汽导致生锈，接线端子螺丝为供应商装配 | S56: 来料不良 | U56: 库存在制工单客户可接收，每批次验货需提供盐雾实验报告，后续变更为不锈钢螺丝 | V56: 是 | W56: 设计变更-预防 | X56: 宜胜照明1 | Y56: 研发十 | Z56: 45901 | AA56: 45901 | AB56: =IF(A56="","",_xlfn.IFS(AND(Z56=0,AA56=0),"未回复",AND(AA56<>0,Z56=0),"报错",AND(Z56>=NOW(),Z56<>0,AA56=0),"正常进行中",AND(AA56<>0,Z56>=AA56),"按时关闭",AND(Z56<>0,Z56<=AA56),"延期关闭",AND(AA56=0,Z56<NOW()),"延期未关闭")) -> 按时关闭 | AD56: =IF(Z56="","",YEAR(Z56)) -> 2025 | AE56: =IF(Z56="","",TEXT(Z56,"m")) -> 9 | AF56: =IF(Z56="","","W"&WEEKNUM(Z56,2)) -> W36
A57: 45887 | B57: =IF(A57="","",YEAR(A57)) -> 2025 | C57: =IF(A57="","",TEXT(A57,"m")) -> 8 | D57: =IF(A57="","","W"&WEEKNUM(A57,2)) -> W34 | E57: A125S001+002+015+016+017 | F57: AC6787700YSRU(3合1）导轨灯 | G57: 中国1796 | H57: 宜胜照明3 | K57: 王超 | L57: AC6787700YSRU(3合1）导轨灯 - 订单号A125S001+002+015+016+017 装柜总数944pcs，6pcs/装,158箱（157箱+2pcs） 因装柜的时候该产品装在了最下面，纸箱的硬度不足以承受重量，导致收到货的时候有21个外箱破损，合计126个产品，该产品因包装破损，无法销售。 | O57: =IFERROR(N57/M57,"") | P57: 售后客诉 | Q57: 包装 | R57: 因考虑包装成本及运输成本，包装内部无支撑结构，且不同尺寸包装产品混装，下层导轨灯外箱受力不均，超出包装可承受极，造成限结构性损伤； | S57: 包装设计 | T57: 补发包装 | U57: 包装变形产品为出货装柜混装产品，后续下单尽量避免混装现象，如不能避免，工艺单备注不同尺寸包装产品出货装柜混装时，不可相互堆叠，需同种产品单独放置一摞 | V57: 否 | W57: 纠错 | X57: 宜胜照明2 | Y57: 研发三 | Z57: 45888 | AA57: 45888 | AB57: =IF(A57="","",_xlfn.IFS(AND(Z57=0,AA57=0),"未回复",AND(AA57<>0,Z57=0),"报错",AND(Z57>=NOW(),Z57<>0,AA57=0),"正常进行中",AND(AA57<>0,Z57>=AA57),"按时关闭",AND(Z57<>0,Z57<=AA57),"延期关闭",AND(AA57=0,Z57<NOW()),"延期未关闭")) -> 按时关闭 | AD57: =IF(Z57="","",YEAR(Z57)) -> 2025 | AE57: =IF(Z57="","",TEXT(Z57,"m")) -> 8 | AF57: =IF(Z57="","","W"&WEEKNUM(Z57,2)) -> W34
A58: 45887 | B58: =IF(A58="","",YEAR(A58)) -> 2025 | C58: =IF(A58="","",TEXT(A58,"m")) -> 8 | D58: =IF(A58="","","W"&WEEKNUM(A58,2)) -> W34 | E58: A125S043 | F58: GU10 5W 4000K | G58: 中国1796 | H58: 宜胜照明1 | K58: 王超 | L58: 订单号A125S041，AC479150055丢失48pcs，装柜总数量22032pcs，48pcs/箱，共计459箱 订单号A125S001+002+015+016+017，AC594190055丢失58pcs，装柜总数量500pcs，120pcs/箱，共计5箱（4箱+20pcs） 订单号A125S043，AC603360155丢失400pcs，装柜总数量8000pcs，100pcs/箱，共计80箱 | O58: =IFERROR(N58/M58,"") | P58: 售后客诉 | Q58: 其它 | R58: 经复核仓库发货图片确认，订单号A125S043，AC603360155丢失400pcs，装柜总数量8000pcs，100pcs/箱，共计80箱，为漏发，其他发货箱数正确，若为箱内短装需客户提供视频或照片 | T58: 400pcs漏发产品补发 | U58: 货齐后再进行装柜，装柜完成由不同人员点数确认 | V58: 否 | W58: 流程优化 | X58: 其它事业部 | Y58: 快仓科技 | Z58: 45888 | AA58: 45888 | AB58: =IF(A58="","",_xlfn.IFS(AND(Z58=0,AA58=0),"未回复",AND(AA58<>0,Z58=0),"报错",AND(Z58>=NOW(),Z58<>0,AA58=0),"正常进行中",AND(AA58<>0,Z58>=AA58),"按时关闭",AND(Z58<>0,Z58<=AA58),"延期关闭",AND(AA58=0,Z58<NOW()),"延期未关闭")) -> 按时关闭 | AD58: =IF(Z58="","",YEAR(Z58)) -> 2025 | AE58: =IF(Z58="","",TEXT(Z58,"m")) -> 8 | AF58: =IF(Z58="","","W"&WEEKNUM(Z58,2)) -> W34
A59: 45888 | B59: =IF(A59="","",YEAR(A59)) -> 2025 | C59: =IF(A59="","",TEXT(A59,"m")) -> 8 | D59: =IF(A59="","","W"&WEEKNUM(A59,2)) -> W34 | E59: E24L1124 | F59: A60 11W 球泡（3000K/6500K) A60 14W 球泡 （3000K/6500K) | G59: 约旦132 | H59: 宜胜照明1 | I59: 卢蒙 | K59: 童志海 | L59: E24L1124订单客诉，客户发现11W和15W球泡包装出现 1：彩盒用错，2：外箱用错 | O59: 0.05 | P59: 售后客诉 | Q59: 包装 | R59: 1.供应商来料混； 2.来料检验抽样还错； 3.仓库混料,收发过程及仓库备料过程 4.生产环节（领料、现边仓、过程周转、换线切换） | S59: 过程工艺 | T59: 协商赔偿客户损失 | U59: 1.供应商打包前全检； 2.检验完成后抽检彩盒报废不进行归还； 3.a.收发过程标识； b.备料过程区分摆放做标识，一个彩盒物料只允许一个托盘（物料员领料过程查验），不允许物料满框冒尖 4.a.员工自检意识培训（重点检查彩盒功率、色温、条码） b.多能工对完彩盒资料还错风险：抽样核对彩盒报废不进行归还 C.换线换线进行清线，班组长确认后再生产（换型换线清线确认记录表） | V59: 否 | W59: 流程优化 | X59: 宜胜照明1 | Y59: 生产一 | Z59: 45889 | AA59: 45889 | AB59: =IF(A59="","",_xlfn.IFS(AND(Z59=0,AA59=0),"未回复",AND(AA59<>0,Z59=0),"报错",AND(Z59>=NOW(),Z59<>0,AA59=0),"正常进行中",AND(AA59<>0,Z59>=AA59),"按时关闭",AND(Z59<>0,Z59<=AA59),"延期关闭",AND(AA59=0,Z59<NOW()),"延期未关闭")) -> 按时关闭 | AD59: =IF(Z59="","",YEAR(Z59)) -> 2025 | AE59: =IF(Z59="","",TEXT(Z59,"m")) -> 8 | AF59: =IF(Z59="","","W"&WEEKNUM(Z59,2)) -> W34
A60: 45901 | B60: =IF(A60="","",YEAR(A60)) -> 2025 | C60: =IF(A60="","",TEXT(A60,"m")) -> 9 | D60: =IF(A60="","","W"&WEEKNUM(A60,2)) -> W36 | E60: / | F60: 墙壁开关 | G60: 巴西527 | H60: 宜胜照明1 | I60: 徐赢意 | J60: 赖长金 | K60: 丁亚双 | L60: 玻璃面板与中框脱胶 | N60: 7PCS | P60: 售后客诉 | Q60: 内部 | R60: 中框表面油污与胶化学反应 | S60: 来料不良 | U60: 1.供应商改善 2.制程面板拉力测试≥40N，胶固化玻璃面板拆卸验证 3.增加成品检验模拟拆卸玻璃面板动作 | V60: 否 | W60: 流程优化 | X60: 计划采购部 | Y60: 供方管理组 | Z60: 45905 | AA60: 45905 | AB60: =IF(A60="","",_xlfn.IFS(AND(Z60=0,AA60=0),"未回复",AND(AA60<>0,Z60=0),"报错",AND(Z60>=NOW(),Z60<>0,AA60=0),"正常进行中",AND(AA60<>0,Z60>=AA60),"按时关闭",AND(Z60<>0,Z60<=AA60),"延期关闭",AND(AA60=0,Z60<NOW()),"延期未关闭")) -> 按时关闭 | AD60: =IF(Z60="","",YEAR(Z60)) -> 2025 | AE60: =IF(Z60="","",TEXT(Z60,"m")) -> 9 | AF60: =IF(Z60="","","W"&WEEKNUM(Z60,2)) -> W36
A61: 45911 | B61: =IF(A61="","",YEAR(A61)) -> 2025 | C61: =IF(A61="","",TEXT(A61,"m")) -> 9 | D61: =IF(A61="","","W"&WEEKNUM(A61,2)) -> W37 | E61: Z25B005 | F61: BL212-20W | G61: 阿联酋517 | H61: 宜胜照明3 | J61: 邵心妮 | K61: 李冬雪 | L61: 防潮灯在使用一段时间后有频闪问题 | M61: 8000 | N61: 8000 | P61: 售后客诉 | Q61: 功能 | R61: 失效样机续流二极管并联了RC，在芯片温度上升后，JEFT电流能力下降，样机续流二极管并联的RC使芯片开通损耗过高，内部VDD波动过大，引起内部REF比较器电压出现过大波动，在屏蔽时间结束后仍超过CS REF，出现误关断后引起闪灯。 | S61: 电子设计 | T61: 客户退货返工,去掉电源板R14 C3位置元器件 | U61: 变更电子方案，去掉电源板R14 C3位置元器件 | V61: 是 | W61: 设计变更-预防 | X61: 宜胜照明3 | Y61: 研发二 | Z61: 45911 | AA61: 45911 | AB61: =IF(A61="","",_xlfn.IFS(AND(Z61=0,AA61=0),"未回复",AND(AA61<>0,Z61=0),"报错",AND(Z61>=NOW(),Z61<>0,AA61=0),"正常进行中",AND(AA61<>0,Z61>=AA61),"按时关闭",AND(Z61<>0,Z61<=AA61),"延期关闭",AND(AA61=0,Z61<NOW()),"延期未关闭")) -> 按时关闭 | AD61: =IF(Z61="","",YEAR(Z61)) -> 2025 | AE61: =IF(Z61="","",TEXT(Z61,"m")) -> 9 | AF61: =IF(Z61="","","W"&WEEKNUM(Z61,2)) -> W37
A62: 45941 | B62: =IF(A62="","",YEAR(A62)) -> 2025 | C62: =IF(A62="","",TEXT(A62,"m")) -> 10 | D62: =IF(A62="","","W"&WEEKNUM(A62,2)) -> W41 | E62: A125S043 | F62: GU5.3 6W 3000K | G62: 中国1796 | H62: 宜胜照明1 | K62: 王超 | L62: A125S043中丝印MR16打成了PAR16 | M62: 3000 | O62: =IFERROR(N62/M62,"") -> 0 | P62: 售后客诉 | Q62: 外观 | R62: A125S043经分析为扫尾打印时激光资料调用错导致 | S62: 人员作业 | U62: 1.扫尾打印的产品按照正常打印首件要求进行核对2.打印前班组长核对好后再进行打印，包装前全检人员按照工艺单激光资料对灯印进行核对正常后进行包装 | V62: 否 | W62: 流程优化 | X62: 宜胜照明1 | Y62: 生产一 | Z62: 45943 | AA62: 45943 | AB62: =IF(A62="","",_xlfn.IFS(AND(Z62=0,AA62=0),"未回复",AND(AA62<>0,Z62=0),"报错",AND(Z62>=NOW(),Z62<>0,AA62=0),"正常进行中",AND(AA62<>0,Z62>=AA62),"按时关闭",AND(Z62<>0,Z62<=AA62),"延期关闭",AND(AA62=0,Z62<NOW()),"延期未关闭")) -> 按时关闭 | AD62: =IF(Z62="","",YEAR(Z62)) -> 2025 | AE62: =IF(Z62="","",TEXT(Z62,"m")) -> 10 | AF62: =IF(Z62="","","W"&WEEKNUM(Z62,2)) -> W42
A63: 45941 | B63: =IF(A63="","",YEAR(A63)) -> 2025 | C63: =IF(A63="","",TEXT(A63,"m")) -> 10 | D63: =IF(A63="","","W"&WEEKNUM(A63,2)) -> W41 | E63: A125S114 | F63: GU5.3 7.5W 4000K | G63: 中国1796 | H63: 宜胜照明1 | K63: 王超 | L63: 丝印打乱（正反面丝印印到一起）（委外佳昊） | M63: 25000 | O63: =IFERROR(N63/M63,"") -> 0 | P63: 售后客诉 | Q63: 外观 | R63: 两面丝印，印到一面了，第二面印刷时方向放错 | S63: 人员作业 | U63: 更改作业流程，一线流，一面丝印完成后设备自动转向丝印另一面 | V63: 否 | W63: 流程优化 | X63: 计划采购部 | Y63: 供方管理组 | Z63: 45943 | AA63: 45943 | AB63: =IF(A63="","",_xlfn.IFS(AND(Z63=0,AA63=0),"未回复",AND(AA63<>0,Z63=0),"报错",AND(Z63>=NOW(),Z63<>0,AA63=0),"正常进行中",AND(AA63<>0,Z63>=AA63),"按时关闭",AND(Z63<>0,Z63<=AA63),"延期关闭",AND(AA63=0,Z63<NOW()),"延期未关闭")) -> 按时关闭 | AD63: =IF(Z63="","",YEAR(Z63)) -> 2025 | AE63: =IF(Z63="","",TEXT(Z63,"m")) -> 10 | AF63: =IF(Z63="","","W"&WEEKNUM(Z63,2)) -> W42
A64: 45946 | B64: =IF(A64="","",YEAR(A64)) -> 2025 | C64: =IF(A64="","",TEXT(A64,"m")) -> 10 | D64: =IF(A64="","","W"&WEEKNUM(A64,2)) -> W42 | E64: R22X0712 | F64: 型号：RL160C-10 0W3-G4-TJ 客户货号：LDKU1-1004-100-5000-K03 | G64: IEK | H64: 宜胜照明3 | J64: 余元浩 | L64: 客户反馈2207和2209订单有部分灯珠不亮现象，生产时间分别为9月和11月，其中2207订单不亮8pcs，2209订单2pcs，合同质保3年 | N64: 10 | O64: =IFERROR(N64/M64,"") | P64: 售后客诉 | Q64: 功能 | R64: 灯珠达到寿命周期临界点，内部芯片、荧光粉等核心材料老化导致性能下降发热烧毁，且有可能超过额定工作条件 | S64: 电子设计 | T64: / | U64: 1.研发验证产品使用寿命 2.可要求供应商提供LED灯珠使用寿命报告或可靠性数据 | V64: 否 | X64: 宜胜照明3 | Y64: 研发一 | Z64: 45947 | AA64: 45947 | AB64: =IF(A64="","",_xlfn.IFS(AND(Z64=0,AA64=0),"未回复",AND(AA64<>0,Z64=0),"报错",AND(Z64>=NOW(),Z64<>0,AA64=0),"正常进行中",AND(AA64<>0,Z64>=AA64),"按时关闭",AND(Z64<>0,Z64<=AA64),"延期关闭",AND(AA64=0,Z64<NOW()),"延期未关闭")) -> 按时关闭 | AD64: =IF(Z64="","",YEAR(Z64)) -> 2025 | AE64: =IF(Z64="","",TEXT(Z64,"m")) -> 10 | AF64: =IF(Z64="","","W"&WEEKNUM(Z64,2)) -> W42
A65: 45957 | B65: =IF(A65="","",YEAR(A65)) -> 2025 | C65: =IF(A65="","",TEXT(A65,"m")) -> 10 | D65: =IF(A65="","","W"&WEEKNUM(A65,2)) -> W44 | E65: A124S186 | F65: GU10 8W 4000K 客户货号AC603000055 | G65: 中国1796 | H65: 宜胜照明1 | K65: 王超 | L65: 客户反馈订单A124S186，型号GU10 8W 4000K，客户货号AC603000055有引脚变形现象，工单数量10000pcs，不良数量523pcs，不良率5% | M65: 10000 | N65: 523 | O65: =IFERROR(N65/M65,"") -> 0.0523 | P65: 售后客诉 | Q65: 外观 | R65: 包装机设备运行中，设备震动，产品上下移位，灯杯边沿卡入固定灯杯治具中间缝隙，此时推头推产品入彩盒，灯杯引脚受力导致变形歪斜 | U65: 更换包装设备，新设备固定产品位置增加上下挡板，防止设备运行过程震动导致产品移位，固定治具由带缝隙的不锈钢材质更改塑料链条模式等方面进行优化 该新包装设备已于7月20日投入使用 | V65: 是 | W65: 自动化 | X65: 宜胜照明1 | Y65: 生产一 | Z65: 45958 | AA65: 45958 | AB65: =IF(A65="","",_xlfn.IFS(AND(Z65=0,AA65=0),"未回复",AND(AA65<>0,Z65=0),"报错",AND(Z65>=NOW(),Z65<>0,AA65=0),"正常进行中",AND(AA65<>0,Z65>=AA65),"按时关闭",AND(Z65<>0,Z65<=AA65),"延期关闭",AND(AA65=0,Z65<NOW()),"延期未关闭")) -> 按时关闭 | AD65: =IF(Z65="","",YEAR(Z65)) -> 2025 | AE65: =IF(Z65="","",TEXT(Z65,"m")) -> 10 | AF65: =IF(Z65="","","W"&WEEKNUM(Z65,2)) -> W44
A66: 45957 | B66: =IF(A66="","",YEAR(A66)) -> 2025 | C66: =IF(A66="","",TEXT(A66,"m")) -> 10 | D66: =IF(A66="","","W"&WEEKNUM(A66,2)) -> W44 | E66: YL#0824 A124S116 YL#0225 A125S001+S002 | F66: GX53 | G66: 中国1796 | H66: 宜胜照明1（委外佳昊） | K66: 王超 | L66: 电解电容引脚短路 | O66: =IFERROR(N66/M66,"") | P66: 售后客诉 | Q66: 功能 | R66: 根本原因分析：生产过程产品挤压、堆叠导致电解电容引脚连接在一起，通电后短路； 流出原因：成品点亮测试前置到组装泡壳前，未能识别前置测试风险导致漏检流出。 | S66: 过程工艺 | U66: 工艺改善：如右图,在电解电容引脚穿过端子，新增引脚下压工序，特殊塑形使引脚间距≥3mm 流程改善：新增成品检验点亮测试，及包装前测试 | V66: 否 | W66: 供应商改善 | X66: 计划采购部 | Y66: 供方管理组 | Z66: 45961 | AA66: 45961 | AB66: =IF(A66="","",_xlfn.IFS(AND(Z66=0,AA66=0),"未回复",AND(AA66<>0,Z66=0),"报错",AND(Z66>=NOW(),Z66<>0,AA66=0),"正常进行中",AND(AA66<>0,Z66>=AA66),"按时关闭",AND(Z66<>0,Z66<=AA66),"延期关闭",AND(AA66=0,Z66<NOW()),"延期未关闭")) -> 按时关闭 | AD66: =IF(Z66="","",YEAR(Z66)) -> 2025 | AE66: =IF(Z66="","",TEXT(Z66,"m")) -> 10 | AF66: =IF(Z66="","","W"&WEEKNUM(Z66,2)) -> W44
A67: 45994 | B67: =IF(A67="","",YEAR(A67)) -> 2025 | C67: =IF(A67="","",TEXT(A67,"m")) -> 12 | D67: =IF(A67="","","W"&WEEKNUM(A67,2)) -> W49 | E67: R23X1018 | F67: HL133-200W | G67: IEK | H67: 宜胜照明3 | I67: 李玉蓉 | J67: 王华栋 | L67: 灯具闪烁。面板上有两组发光二极管，每组的供电电压为197伏。发光二极管闪烁的原因是其中一组电容器的容量损失 | N67: 7PCS | O67: =IFERROR(N67/M67,"") | P67: 售后客诉 | Q67: 功能 | R67: 产品在方案设计中为考虑效率问题，采用三段性IC方案，第一段电解电容受压最高，受异常浪涌冲击时，第一段受压也最大，产品在长时间使用过程中，电解电容受压能力下降，电压波动超过了电解电容受压，电容损坏，灯具出现闪烁 | S67: 电子设计 | T67: 统计不良数量更换货 | U67: 2310批次出单产品为该方案第一版本产品，该方案版本只出货这一批次，后续方案已陆续迭代更新，目前方案已更新至G3/G4版本，具体改善如下： 1.更换更大容量电解电容（22uf变更至最低68uf），选用电容直径更大（由原φ6.3变更至φ8）； 2.减少电解数量及并联数。电解直径越大承压能力越大，同步电解并数降低，可降低外部产生冲击时内部同步生产的冲击能量，降低风险。 3.更改灯珠配比比（灯珠串比由6：5：4改至4：5：5），降低第一串灯珠的灯串电压，加大电解电压的应力余量； 4.浪涌能力改善，虽标称浪涌未改变，但实际浪涌能力上限调高，增强风险承受能力 | V67: 是 | W67: 设计变更-预防 | X67: 宜胜照明3 | Y67: 研发 | Z67: 45996 | AA67: 45996 | AB67: =IF(A67="","",_xlfn.IFS(AND(Z67=0,AA67=0),"未回复",AND(AA67<>0,Z67=0),"报错",AND(Z67>=NOW(),Z67<>0,AA67=0),"正常进行中",AND(AA67<>0,Z67>=AA67),"按时关闭",AND(Z67<>0,Z67<=AA67),"延期关闭",AND(AA67=0,Z67<NOW()),"延期未关闭")) -> 按时关闭 | AD67: =IF(Z67="","",YEAR(Z67)) -> 2025 | AE67: =IF(Z67="","",TEXT(Z67,"m")) -> 12 | AF67: =IF(Z67="","","W"&WEEKNUM(Z67,2)) -> W49
A68: 46000 | B68: =IF(A68="","",YEAR(A68)) -> 2025 | C68: =IF(A68="","",TEXT(A68,"m")) -> 12 | D68: =IF(A68="","","W"&WEEKNUM(A68,2)) -> W50 | E68: Z24D054 | F68: LG271C-100W2-CCT-G5、LG271C-150W2-CCT-G5、LG271C-200W2-CCT-G5 | G68: 沙特阿拉伯426 | H68: 宜胜照明3 | J68: 王燕赟 | K68: 李冬雪 | L68: LG271C-100W2-CCT-G5、LG271C-150W2-CCT-G5、LG271C-200W2-CCT-G5 客户反馈出现投光灯出现死灯 灯珠烧坏问题 在客户返工使用浪涌保护器后依然无法解决 | O68: =IFERROR(N68/M68,"") | P68: 售后客诉 | Q68: 功能 | R68: 电压异常波动，导致电路电流过大，芯片抗浪涌等级不足，无法承受异常电流冲击而烧毁 | S68: 电子设计 | T68: 客户库存产品退回返工，返工方案：更换浪涌等级更高芯片 | U68: 电子方案变更：更换浪涌等级更高芯片(开关老化冲击验证OK，待Z25F052订单客户市场反馈效果） | V68: 是 | W68: 设计变更-预防 | X68: 宜胜照明3 | Y68: 研发 | Z68: 46002 | AA68: 46002 | AB68: =IF(A68="","",_xlfn.IFS(AND(Z68=0,AA68=0),"未回复",AND(AA68<>0,Z68=0),"报错",AND(Z68>=NOW(),Z68<>0,AA68=0),"正常进行中",AND(AA68<>0,Z68>=AA68),"按时关闭",AND(Z68<>0,Z68<=AA68),"延期关闭",AND(AA68=0,Z68<NOW()),"延期未关闭")) -> 按时关闭 | AD68: =IF(Z68="","",YEAR(Z68)) -> 2025 | AE68: =IF(Z68="","",TEXT(Z68,"m")) -> 12 | AF68: =IF(Z68="","","W"&WEEKNUM(Z68,2)) -> W50
A69: 46002 | B69: =IF(A69="","",YEAR(A69)) -> 2025 | C69: =IF(A69="","",TEXT(A69,"m")) -> 12 | D69: =IF(A69="","","W"&WEEKNUM(A69,2)) -> W50 | F69: 阿根廷215智能开关 | G69: 阿根廷215 | H69: 宜胜照明1 | I69: 朱元笛 | J69: 赖长金 | L69: 长期多次提及智能开关异响 | O69: =IFERROR(N69/M69,"") | P69: 售后客诉 | Q69: 内部 | R69: 异响为电容导致 | S69: 电子设计 | T69: 更换二极管及电容,D11位置号A7二极管拆掉更换成F7二级管，位置号C7电容拆掉换成薄膜电容，薄膜电容底下打白胶 在库订单如下： M25S060T-1 与M25S070T在12/26前完成返工 M25S069T 在12/30前完成返工 在产订单如下： M25S078T半成品返工处理 M25S083T按新方案生产 | U69: D11位置号二极管（A7 SOD-123FL 1A 1000V 泰莱姆）更换为F7二极管 C7位置号电容(1206 222 1KV 10% X7R)更换为薄膜电容 | V69: 是 | W69: 设计变更-预防 | X69: 宜胜照明1 | Y69: 研发十 | Z69: 46021 | AA69: 46021 | AB69: =IF(A69="","",_xlfn.IFS(AND(Z69=0,AA69=0),"未回复",AND(AA69<>0,Z69=0),"报错",AND(Z69>=NOW(),Z69<>0,AA69=0),"正常进行中",AND(AA69<>0,Z69>=AA69),"按时关闭",AND(Z69<>0,Z69<=AA69),"延期关闭",AND(AA69=0,Z69<NOW()),"延期未关闭")) -> 按时关闭 | AD69: =IF(Z69="","",YEAR(Z69)) -> 2025 | AE69: =IF(Z69="","",TEXT(Z69,"m")) -> 12 | AF69: =IF(Z69="","","W"&WEEKNUM(Z69,2)) -> W53
A70: 46027 | B70: =IF(A70="","",YEAR(A70)) -> 2026 | C70: =IF(A70="","",TEXT(A70,"m")) -> 1 | D70: =IF(A70="","","W"&WEEKNUM(A70,2)) -> W2 | F70: 巴西527计量插座系列 | G70: 巴西527 | H70: 宜胜照明1 | I70: 徐赢意 | J70: 赖长金 | K70: 丁亚双 | L70: 插座实际电压与APP计量电压偏差大,客户抽15pcs，6pcs异常，客户重新计量校准后恢复正常 | O70: =IFERROR(N70/M70,"") | P70: 售后客诉 | Q70: 功能 | R70: 产品模块由涂鸦更换为乐橙后，未及时更新SOP，且乐橙模块计量成功状态与涂鸦有明显区别，导致未计量校准产品流出 | S70: 过程工艺 | T70: 库存插座系列产品全部返工，重新计量校准 | U70: 1、更新SOP，明确乐橙模块产品计量成功状态；如右图SOP 2、岗位人员培训，针对SOP更新内容，进行现场演示实操培训，测试人员进行定岗 3、首件确认及过程质量控制；每批次订单产品首件确认5PCS合格后，订单才能上线生产。在制程过程中班组长和IPQC每2小时抽取10pcs进行抽测连接APP验证，确保生产制程中的产品质量符合客户要求。 | V70: 否 | W70: 工艺优化 | X70: 宜胜照明1 | Y70: 生产一 | Z70: 46029 | AA70: 46029 | AB70: =IF(A70="","",_xlfn.IFS(AND(Z70=0,AA70=0),"未回复",AND(AA70<>0,Z70=0),"报错",AND(Z70>=NOW(),Z70<>0,AA70=0),"正常进行中",AND(AA70<>0,Z70>=AA70),"按时关闭",AND(Z70<>0,Z70<=AA70),"延期关闭",AND(AA70=0,Z70<NOW()),"延期未关闭")) -> 按时关闭 | AD70: =IF(Z70="","",YEAR(Z70)) -> 2026 | AE70: =IF(Z70="","",TEXT(Z70,"m")) -> 1 | AF70: =IF(Z70="","","W"&WEEKNUM(Z70,2)) -> W2
A71: 46050 | B71: =IF(A71="","",YEAR(A71)) -> 2026 | C71: =IF(A71="","",TEXT(A71,"m")) -> 1 | D71: =IF(A71="","","W"&WEEKNUM(A71,2)) -> W5 | E71: A125S183 | F71: RL240 AC609400055 AC609390055 | G71: 中国1796-欧洲 | H71: 宜胜照明3 | I71: 王雨晨 | J71: 余元浩 | K71: 王超 | L71: 包装损坏，外箱中部弯曲变形 | N71: 31 | O71: =IFERROR(N71/M71,"") | P71: 售后客诉 | Q71: 包装 | R71: 未按工艺单资料要求进行打托装柜，要求使用1200*800托盘叠放，实际使用大托盘回字型摆放，外箱较长，两边有泡棉支撑，回字型放置中间无支撑 | S71: 其它 | T71: 提供包装材料供客户更换 | U71: 仓库物流按工艺要求进行打托 | V71: 否 | W71: 人员培训 | X71: 其它事业部 | Y71: 快仓科技 | Z71: 46052 | AA71: 46052 | AB71: =IF(A71="","",_xlfn.IFS(AND(Z71=0,AA71=0),"未回复",AND(AA71<>0,Z71=0),"报错",AND(Z71>=NOW(),Z71<>0,AA71=0),"正常进行中",AND(AA71<>0,Z71>=AA71),"按时关闭",AND(Z71<>0,Z71<=AA71),"延期关闭",AND(AA71=0,Z71<NOW()),"延期未关闭")) -> 按时关闭 | AD71: =IF(Z71="","",YEAR(Z71)) -> 2026 | AE71: =IF(Z71="","",TEXT(Z71,"m")) -> 1 | AF71: =IF(Z71="","","W"&WEEKNUM(Z71,2)) -> W5
A72: 46048 | B72: =IF(A72="","",YEAR(A72)) -> 2026 | C72: =IF(A72="","",TEXT(A72,"m")) -> 1 | D72: =IF(A72="","","W"&WEEKNUM(A72,2)) -> W5 | E72: M25A002 | F72: EWS 1006 BR | G72: 巴西527 | H72: 宜胜照明1 | I72: 徐赢意 | J72: 赖长金 | K72: 丁亚双 | L72: 在我们的成品质量检查过程中，检查了 400 个样品后，我们发现有 4 个产品缺少螺丝，并且在返工过程中我们也发现了同样的问题。我们需要您的协助来执行以下操作：1. 对仓库内的物品进行清点，并就所存物品的状况提供反馈意见；2. 查明根本原因，并附上 8D 报告及纠正措施； | M72: 2000 | N72: 4 | O72: 0.01 | P72: 售后客诉 | Q72: 包装 | R72: 人员作业疲劳，少装一颗螺丝 | S72: 人员作业 | T72: 返工全检清点数量 | U72: 增加称重，超上下限报警 | V72: 否 | W72: 工艺优化 | X72: 宜胜照明1 | Y72: 生产一 | Z72: 46051 | AA72: 46051 | AB72: =IF(A72="","",_xlfn.IFS(AND(Z72=0,AA72=0),"未回复",AND(AA72<>0,Z72=0),"报错",AND(Z72>=NOW(),Z72<>0,AA72=0),"正常进行中",AND(AA72<>0,Z72>=AA72),"按时关闭",AND(Z72<>0,Z72<=AA72),"延期关闭",AND(AA72=0,Z72<NOW()),"延期未关闭")) -> 按时关闭 | AD72: =IF(Z72="","",YEAR(Z72)) -> 2026 | AE72: =IF(Z72="","",TEXT(Z72,"m")) -> 1 | AF72: =IF(Z72="","","W"&WEEKNUM(Z72,2)) -> W5
A73: 46085 | B73: =IF(A73="","",YEAR(A73)) -> 2026 | C73: =IF(A73="","",TEXT(A73,"m")) -> 3 | D73: =IF(A73="","","W"&WEEKNUM(A73,2)) -> W10 | E73: M24A008 | F73: ETS 2002 BR | G73: 巴西527 | H73: 宜胜照明1 | I73: 徐赢意 | J73: 赖长金 | K73: 丁亚双 | L73: 客诉反馈订单M24A008 ，ETS 2002 BR 6 件产品内部有噪音，打开产品检查噪音原因后，发现 5 件产品有焊球，1 件产品有一块塑料。该订单产品批次数量3885pcs，不良率0.15% | M73: 3885 | N73: 6 | O73: =IFERROR(N73/M73,"") -> 0.0015444015 | P73: 售后客诉 | Q73: 内部 | R73: 1.锡渣： PCBA元件通过波峰焊进行焊接时，元件中间镂空孔位漏锡，导致锡残留元器件缝隙处 2.塑料：组装过程异物掉落内部 | S73: 过程工艺 | T73: 对有风险批次库存摇异响全检，不良拆机内部清理 | U73: 1.产品工艺变更，波峰焊工位增加工装载具遮挡PCBA板镂空孔位 2.PCBA板目检岗位锡渣风险位置 、不良图片定期宣导 3.组装车间包装前SOP增加摇异响检查 | V73: 否 | W73: 工艺优化 | X73: 宜胜照明1 | Y73: 生产一 | Z73: 46090 | AA73: 46090 | AB73: =IF(A73="","",_xlfn.IFS(AND(Z73=0,AA73=0),"未回复",AND(AA73<>0,Z73=0),"报错",AND(Z73>=NOW(),Z73<>0,AA73=0),"正常进行中",AND(AA73<>0,Z73>=AA73),"按时关闭",AND(Z73<>0,Z73<=AA73),"延期关闭",AND(AA73=0,Z73<NOW()),"延期未关闭")) -> 按时关闭 | AD73: =IF(Z73="","",YEAR(Z73)) -> 2026 | AE73: =IF(Z73="","",TEXT(Z73,"m")) -> 3 | AF73: =IF(Z73="","","W"&WEEKNUM(Z73,2)) -> W11
A74: 46094 | B74: =IF(A74="","",YEAR(A74)) -> 2026 | C74: =IF(A74="","",TEXT(A74,"m")) -> 3 | D74: =IF(A74="","","W"&WEEKNUM(A74,2)) -> W11 | E74: M25A020-1 | F74: EIW 1001 BR | G74: 巴西527 | H74: 宜胜照明1 | I74: 徐赢意 | J74: 赖长金 | K74: 丁亚双 | L74: 玻璃面盖背后黑色图层有缺陷和划痕，客户抽检125pcs，不良5pcs | O74: 0.04 | P74: 售后客诉 | Q74: 外观 | R74: 原因分析: 1.划痕：经划痕痕迹分析，划痕形态呈线性、尖锐、定向特征，判定为生产过程锐器划伤，现场锐器管理缺失，风险未被提前识别与控制。 2.白色不规则透光点：玻璃面板来料丝印过程印刷速度过快导致气泡未充分释放形成的针孔/白点，或者是油墨本身杂质颗粒印刷后形成的透光白点； | S74: 来料不良 | T74: 库存抽检 | U74: 永久纠正措施： 1.划痕： 车间锐器管控，锐器收发管控，固定使用，若有使用SOP备注作业方法，并对工具工装进行防护后再进行使用。 2.来料白点： a.供应商玻璃丝印工艺参数印刷速度调整： 由原来的刮刀速度700、覆墨速度1600、印刷升降速度500调整为刮刀速度500、覆墨速度1000、 印刷升降速度500. b.变更定期更换油墨过滤网频率,，由原72H更换变更为12H更换； c.油墨烘干工序后增加目视全检 | V74: 否 | W74: 供应商改善 | X74: 计划采购部 | Y74: 供方管理组 | Z74: 46099 | AA74: 46099 | AB74: =IF(A74="","",_xlfn.IFS(AND(Z74=0,AA74=0),"未回复",AND(AA74<>0,Z74=0),"报错",AND(Z74>=NOW(),Z74<>0,AA74=0),"正常进行中",AND(AA74<>0,Z74>=AA74),"按时关闭",AND(Z74<>0,Z74<=AA74),"延期关闭",AND(AA74=0,Z74<NOW()),"延期未关闭")) -> 按时关闭 | AD74: =IF(Z74="","",YEAR(Z74)) -> 2026 | AE74: =IF(Z74="","",TEXT(Z74,"m")) -> 3 | AF74: =IF(Z74="","","W"&WEEKNUM(Z74,2)) -> W12
A75: 46099 | B75: =IF(A75="","",YEAR(A75)) -> 2026 | C75: =IF(A75="","",TEXT(A75,"m")) -> 3 | D75: =IF(A75="","","W"&WEEKNUM(A75,2)) -> W12 | E75: M25A020-1 | F75: EIW 1001 PT | G75: 巴西527 | H75: 宜胜照明1 | I75: 徐赢意 | J75: 赖长金 | K75: 丁亚双 | L75: 外箱用错1pcs | O75: =IFERROR(N75/M75,"") | P75: 售后客诉 | Q75: 包装 | R75: 1. M25A020-1 EIW 1001 PT最晚入库9.20、系统结案9.21，配套外箱料号70010101543；错误外箱为M25A018-1 EZS 1002 BR的料号70010101682，该外箱9.22入库、10.11发料，外箱按单数量采购无库存，到料时间晚于正确产品生产入库时间，排除正常生产混料用错可能 2. 10-11月玻璃盖起翘问题处理期间，工厂对相关产品开展大量验证排查工作，过程中同时拿取多款产品操作，M25A020-1 EIW 1001 PT未做返工但被纳入此次验证排查，装回时应为员工未核对产品与外箱的匹配性，导致错用同系列M25A018-1 EZS 1002 BR的外箱。 3.10月份外箱版本更新，新旧版本交替，员工不熟悉订单对应外箱版本，导致用错 结论：外箱版本更新新旧交替；员工未识别；排查/借样未核对，导致外箱用错 | S75: 人员作业 | T75: 1.对10-1月库存产品抽检4款核对外箱匹配度，未发现异常 2.对在途库存外箱排查是否混料，未发现异常 | U75: 永久纠正措施： 1.制定库存排查跟踪记录表，内含产品及包装核对等项目，规范库存排查工作； 2.针对巴西527外箱更新内容人员培训 预防措施： 工艺单发生变更时，业务邮件通知生产、品质及相关人员，附详细变更内容说明，PQE收到邮件后对各责任人培训情况进行确认，右图为《工艺单资料变更记录表》 | V75: 否 | W75: 流程优化 | X75: 宜胜照明1 | Y75: 生产一 | Z75: 46104 | AA75: 46104 | AB75: =IF(A75="","",_xlfn.IFS(AND(Z75=0,AA75=0),"未回复",AND(AA75<>0,Z75=0),"报错",AND(Z75>=NOW(),Z75<>0,AA75=0),"正常进行中",AND(AA75<>0,Z75>=AA75),"按时关闭",AND(Z75<>0,Z75<=AA75),"延期关闭",AND(AA75=0,Z75<NOW()),"延期未关闭")) -> 按时关闭 | AD75: =IF(Z75="","",YEAR(Z75)) -> 2026 | AE75: =IF(Z75="","",TEXT(Z75,"m")) -> 3 | AF75: =IF(Z75="","","W"&WEEKNUM(Z75,2)) -> W13
A76: 46106 | B76: =IF(A76="","",YEAR(A76)) -> 2026 | C76: =IF(A76="","",TEXT(A76,"m")) -> 3 | D76: =IF(A76="","","W"&WEEKNUM(A76,2)) -> W13 | F76: LG189样品 | G76: 正泰 | H76: 宜胜照明1 | L76: 2026年3月5日收到正泰3台LG189退机样品： 1.1#机：产品无法启动，灯不亮 2.2#机：110-130V正常，140V以上规律性闪烁 3.3#机：240V输入掉功率，亮度频繁闪烁 | O76: =IFERROR(N76/M76,"") | P76: 样品确认 | Q76: 功能 | R76: 根本原因：IC拆真空包装后受潮，波峰焊高温产生爆米花效应，导致芯片分层击穿； 直接原因：U1驱动IC内部击穿、芯片分层，导致电路失效 | T76: 1.对3台退机样品检测、不良复现、定位IC失效 2.不良IC送原厂做失效分析，保留样品备查； 3.修复可使用样品并验证，将结果反馈客户 | U76: 1.IC拆封后限时使用，防止受潮 2.超期存放IC必须80-100℃烘烤8小时方可上线 3.焊炉温250-265℃，焊接时间2-6秒，固化参数 | V76: 否 | W76: 工艺优化 | X76: 宜胜照明3 | Y76: 研发 | Z76: 46111 | AA76: 46111 | AB76: =IF(A76="","",_xlfn.IFS(AND(Z76=0,AA76=0),"未回复",AND(AA76<>0,Z76=0),"报错",AND(Z76>=NOW(),Z76<>0,AA76=0),"正常进行中",AND(AA76<>0,Z76>=AA76),"按时关闭",AND(Z76<>0,Z76<=AA76),"延期关闭",AND(AA76=0,Z76<NOW()),"延期未关闭")) -> 按时关闭 | AD76: =IF(Z76="","",YEAR(Z76)) -> 2026 | AE76: =IF(Z76="","",TEXT(Z76,"m")) -> 3 | AF76: =IF(Z76="","","W"&WEEKNUM(Z76,2)) -> W14
A77: 46111 | B77: =IF(A77="","",YEAR(A77)) -> 2026 | C77: =IF(A77="","",TEXT(A77,"m")) -> 3 | D77: =IF(A77="","","W"&WEEKNUM(A77,2)) -> W14 | E77: A124S207-1 | F77: RL182C-100W | G77: 中国1796-木林森 | H77: 宜胜照明3 | K77: 王超 | L77: 2026年1月27日收到俄朗客诉信息 订单号A124S207-1(EAN 4058075678156 ) 不良数量：31 pcs. 客诉描述：灯具装上去后7-10天左右，灯具陆续出现灯珠烧毁的情况，隔2-3天后接连出现，这些灯具装在不同的线路上。 安装地：俄罗斯/中亚地区 | M77: 3000 | N77: 31 | O77: =IFERROR(N77/M77,"") -> 0.010333333 | P77: 售后客诉 | Q77: 功能 | R77: 根本原因分析： 1、客户灯具安装后仅7-10天即批量出现灯珠烧毁，属于典型早期失效，排除自然老化因素； 2、灯珠表面发黑是过流/过压击穿典型特征，LED内部芯片击穿、金线熔断； 3、检测驱动元器件有内部损伤现象，考虑安装地点为中亚，电网环境电压波动+浪涌冲击（如大型设备启停，接地差，线路长，雷暴多等）气候特征（昼夜温差大，温度剧烈变化产生热胀冷缩应力会使LED灯珠金线、焊点疲劳失效），每次上电/电压波动都会造成元器件积累损伤，从而导致驱动输出失控； 4.老化验证：该方案产品在270V电压老化168H，产品未发现异常（右图3图4） 5.低温验证：该方案产品在低温-25℃条件运行2H，产品功能正常； 6.浪涌验证：该方案产品分别在浪涌4000V,4300V,4800V下冲击测试，4800V出现保险电阻损坏失效现象，更换保险电阻后产品功能恢复正常； 结论：该方案灯具为额定电压220-240V，浪涌4000V普通款灯具，灯珠烧毁是俄罗斯（中亚）现场多重复杂应力叠加导致（电压波动+浪涌冲击+温差大），其综合严酷程度远高于单一实验室测试条件，最终造成驱动器件损伤及灯珠永久性烧毁 | S77: 其它 | T77: 1. 完成失效样品分析，明确失效模式。 2. 开展实验室模拟验证，确认产品在各应力条件下的表现。 3. 为客户提供技术支持与现场工况分析，协助排查供电环境。 | U77: 1.明确产品适用工况范围，规范应用场景说明； 2.建议客户现场完善外部浪涌防护、接地及线路稳压措施； 3.后续项目对于客户终端现场工况严酷场景，可根据客户提供实际工况设计产品方案 | V77: 否 | Z77: 46113 | AA77: 46113 | AB77: =IF(A77="","",_xlfn.IFS(AND(Z77=0,AA77=0),"未回复",AND(AA77<>0,Z77=0),"报错",AND(Z77>=NOW(),Z77<>0,AA77=0),"正常进行中",AND(AA77<>0,Z77>=AA77),"按时关闭",AND(Z77<>0,Z77<=AA77),"延期关闭",AND(AA77=0,Z77<NOW()),"延期未关闭")) -> 按时关闭 | AD77: =IF(Z77="","",YEAR(Z77)) -> 2026 | AE77: =IF(Z77="","",TEXT(Z77,"m")) -> 4 | AF77: =IF(Z77="","","W"&WEEKNUM(Z77,2)) -> W14
A78: 46112 | B78: =IF(A78="","",YEAR(A78)) -> 2026 | C78: =IF(A78="","",TEXT(A78,"m")) -> 3 | D78: =IF(A78="","","W"&WEEKNUM(A78,2)) -> W14 | E78: W25M175-2 | F78: A60-9.5W-3000K | G78: 克罗地亚019 | H78: 宜胜照明1 | I78: 颜静雯 | K78: 李宁 | L78: 吸塑标贴大批量贴错（305-713 24新款的贴成了305-812） | M78: 8000 | O78: =IFERROR(N78/M78,"") -> 0 | P78: 售后客诉 | Q78: 包装 | R78: 经调查，9.5W-3000K产品吸膜标贴错误使用8.5W-4000K外箱标贴，两款为同一产线生产，且上线入库时间接近，且两种标贴大小一致，现场未做好标贴管控，导致混用 | S78: 人员作业 | T78: 1.库存排查：无库存 2.待产订单W26M008，暂未上线，计划如右图 3.客诉信息内部宣导培 | U78: 1.物料员在仓库领料到车间备料区，严格核对标签物料号，标签必须放置在外箱托盘上面，吸膜标签与中盒标签放置彩盒托盘上面 2.标签上线时，车间多能工再次核对物料号，上交员工先把外箱标签一次性贴完，损耗多余的在现场马上处理掉，不允许存放，吸膜标签打包工在随线生产； 3.员工在生产时必须自检 | V78: 否 | W78: 人员培训 | X78: 宜胜照明1 | Y78: 生产一 | Z78: 46114 | AA78: 46114 | AB78: =IF(A78="","",_xlfn.IFS(AND(Z78=0,AA78=0),"未回复",AND(AA78<>0,Z78=0),"报错",AND(Z78>=NOW(),Z78<>0,AA78=0),"正常进行中",AND(AA78<>0,Z78>=AA78),"按时关闭",AND(Z78<>0,Z78<=AA78),"延期关闭",AND(AA78=0,Z78<NOW()),"延期未关闭")) -> 按时关闭 | AD78: =IF(Z78="","",YEAR(Z78)) -> 2026 | AE78: =IF(Z78="","",TEXT(Z78,"m")) -> 4 | AF78: =IF(Z78="","","W"&WEEKNUM(Z78,2)) -> W14
A79: 45761 | B79: =IF(A79="","",YEAR(A79)) -> 2025 | C79: =IF(A79="","",TEXT(A79,"m")) -> 4 | D79: =IF(A79="","","W"&WEEKNUM(A79,2)) -> W16 | E79: O25H050-1 | F79: C37 8W 3000K/6500K E14 | G79: 罗马尼亚011 | H79: 宜胜照明1 | L79: 合同要求尺寸高度116±3mm，实测106mm | M79: 5000+4000 | O79: 1 | P79: 售后客诉 | Q79: 外观 | R79: BOM总尺寸:灯头17+灯杯39+泡壳49=105mm，该款与希腊208产品LB1203C-8W2-G8H-208所使用物料（灯头、灯杯、泡壳)一致，而希腊208总尺寸要求为106±3mm 结论：设计尺寸与合同资料不符 | S79: 资料错误 | T79: 客户要求赔偿，与客户协商沟通 | U79: 与客户协商变更合同尺寸高度要求为106±3mm | V79: 是 | W79: 标准升级 | X79: 宜胜照明1 | Y79: 研发六 | Z79: 46135 | AA79: 46135 | AB79: =IF(A79="","",_xlfn.IFS(AND(Z79=0,AA79=0),"未回复",AND(AA79<>0,Z79=0),"报错",AND(Z79>=NOW(),Z79<>0,AA79=0),"正常进行中",AND(AA79<>0,Z79>=AA79),"按时关闭",AND(Z79<>0,Z79<=AA79),"延期关闭",AND(AA79=0,Z79<NOW()),"延期未关闭")) -> 按时关闭 | AD79: =IF(Z79="","",YEAR(Z79)) -> 2026 | AE79: =IF(Z79="","",TEXT(Z79,"m")) -> 4 | AF79: =IF(Z79="","","W"&WEEKNUM(Z79,2)) -> W17
A80: 46141 | B80: =IF(A80="","",YEAR(A80)) -> 2026 | C80: =IF(A80="","",TEXT(A80,"m")) -> 4 | D80: =IF(A80="","","W"&WEEKNUM(A80,2)) -> W18 | E80: M25A020-1 | F80: EIW 1002 BR | G80: 巴西527 | H80: 宜胜照明1 | I80: 徐赢意 | K80: 丁亚双 | L80: 客户反馈打开塑封及彩盒发现内部虫尸及活幼虫 | M80: 售后客诉 | O80: =IFERROR(N80/M80,"") | P80: 售后客诉 | Q80: 包装 | R80: 该异常为单个产品偶发虫害入侵彩盒内部，可能原因如下： 1. 彩盒来料无密封包装，运输、仓储环节存在虫害侵入风险 2. 包材仓储防虫管控缺失，无灭蚊灯等防虫设施及日常点检机制 3. 彩盒来料周期管控不到位，仓储滞留时间过长 4. 现场多余原材料、成品滞留，形成虫害滋生环境 5.客户端拆封后储存环境虫害入侵 | T80: 立即对厂内彩盒来料、包材仓库、生产现场、成品库存开展全面排查，异常物料、成品立即隔离管控。 排查结果：未发现虫害污染现象 | U80: 1.包材仓储固化灭蚊灯及点检表管理，常态化落实防虫管控2. 强制要求彩盒供应商来料必须做密封包装，未密封的来料直接拒收3. 严格执行彩盒来料周期管理，齐套时间前1周到料，严控仓储滞留时间，提前到料仓库拒收4. 产线日清日洁要求标准化，每日例会复盘工单完成情况，分析超期原因，长期刚性执行，避免现场物料及成品长时间滞留车间 | V80: 否 | W80: 存储/防护升级 | X80: 宜胜照明1 | Y80: 生产一 | Z80: 46150 | AA80: 46150 | AB80: =IF(A80="","",_xlfn.IFS(AND(Z80=0,AA80=0),"未回复",AND(AA80<>0,Z80=0),"报错",AND(Z80>=NOW(),Z80<>0,AA80=0),"正常进行中",AND(AA80<>0,Z80>=AA80),"按时关闭",AND(Z80<>0,Z80<=AA80),"延期关闭",AND(AA80=0,Z80<NOW()),"延期未关闭")) -> 按时关闭 | AD80: =IF(Z80="","",YEAR(Z80)) -> 2026 | AE80: =IF(Z80="","",TEXT(Z80,"m")) -> 5 | AF80: =IF(Z80="","","W"&WEEKNUM(Z80,2)) -> W19
A81: 46142 | B81: =IF(A81="","",YEAR(A81)) -> 2026 | C81: =IF(A81="","",TEXT(A81,"m")) -> 4 | D81: =IF(A81="","","W"&WEEKNUM(A81,2)) -> W18 | E81: O25H033-1 | F81: T40-8W | G81: 罗马尼亚011 | H81: 宜胜照明1 | K81: 李宁 | L81: 客诉反馈49PCS灯不亮 | M81: 4000 | N81: 49 | O81: =IFERROR(N81/M81,"") -> 0.01225 | P81: 售后客诉 | Q81: 功能 | R81: 端子引脚脱焊，锡量偏少，趴锡不足，原钢网厚度0.12mm | S81: 电子设计 | T81: 退换货处理 | U81: 重开钢网，增加钢网厚度，由0.12mm变更为0.15mm | V81: 否 | W81: 工艺优化 | X81: 宜胜照明1 | Y81: 生产一 | Z81: 46150 | AA81: 46150 | AB81: =IF(A81="","",_xlfn.IFS(AND(Z81=0,AA81=0),"未回复",AND(AA81<>0,Z81=0),"报错",AND(Z81>=NOW(),Z81<>0,AA81=0),"正常进行中",AND(AA81<>0,Z81>=AA81),"按时关闭",AND(Z81<>0,Z81<=AA81),"延期关闭",AND(AA81=0,Z81<NOW()),"延期未关闭")) -> 按时关闭 | AD81: =IF(Z81="","",YEAR(Z81)) -> 2026 | AE81: =IF(Z81="","",TEXT(Z81,"m")) -> 5 | AF81: =IF(Z81="","","W"&WEEKNUM(Z81,2)) -> W19
A82: 46149 | B82: =IF(A82="","",YEAR(A82)) -> 2026 | C82: =IF(A82="","",TEXT(A82,"m")) -> 5 | D82: =IF(A82="","","W"&WEEKNUM(A82,2)) -> W19 | E82: W25D101 | F82: LG157C-50W2-PC-SH_x0002_G3 | G82: 克罗地亚019 | H82: 宜胜照明3 | K82: 李宁 | L82: 订单数量304，客户反馈短装2pcs | M82: 304 | N82: 2 | O82: =IFERROR(N82/M82,"") -> 0.0065789474 | P82: 售后客诉 | Q82: 包装 | R82: 经查订单304PCS，实际生产305PCS，当日生产完成无维修不良遗留；1月15日上午检验合格入库，仓库留存备品1个。产品标准每箱装8pcs，单箱净重10.7kg、毛重13kg。客户过往有同类数量短装投诉记录，其他客户暂未反馈同类异常： 1.目前依靠人工装箱点数，无重量复核校验手段，存在人为点数疏漏风险。 2.产品单体体积偏大，少装2个的作业失误概率偏低，但缺乏物理核验手段，无法有效规避数量争议。 3.未有整箱称重留底记录，发生客诉时缺少可追溯举证依据。 | S82: 过程工艺 | T82: 产品补货2pcs | U82: 1.强化装箱作业人员数量管控意识，规范操作，减少人为疏忽造成的短装； 2.产品封箱完成后，按箱号对应每箱称重并拍照留底；（车间执行） 3.检验员整理每箱称重照片并上传至系统与验货报告同步保存，做到批次、箱号、重量可追溯（检验员跟踪留底保存） | V82: 否 | W82: 工艺优化 | X82: 宜胜照明3 | Y82: 生产三 | Z82: 46150 | AA82: 46150 | AB82: =IF(A82="","",_xlfn.IFS(AND(Z82=0,AA82=0),"未回复",AND(AA82<>0,Z82=0),"报错",AND(Z82>=NOW(),Z82<>0,AA82=0),"正常进行中",AND(AA82<>0,Z82>=AA82),"按时关闭",AND(Z82<>0,Z82<=AA82),"延期关闭",AND(AA82=0,Z82<NOW()),"延期未关闭")) -> 按时关闭 | AD82: =IF(Z82="","",YEAR(Z82)) -> 2026 | AE82: =IF(Z82="","",TEXT(Z82,"m")) -> 5 | AF82: =IF(Z82="","","W"&WEEKNUM(Z82,2)) -> W19
A83: 46154 | B83: =IF(A83="","",YEAR(A83)) -> 2026 | C83: =IF(A83="","",TEXT(A83,"m")) -> 5 | D83: =IF(A83="","","W"&WEEKNUM(A83,2)) -> W20 | E83: M25A031 | F83: EIW 1006 BR | G83: 巴西527 | H83: 宜胜照明1 | L83: 1. 玻璃面盖有白点 2. 导光板脱落移位到其他导光板上，且产品存在半开状态 | N83: 2 | O83: =IFERROR(N83/M83,"") | P83: 售后客诉 | Q83: 功能 | R83: 产品1月生产，3-4月已反馈过同类问题进行改善，白点为油墨涂层缺陷，导光板位移为a.导光板贴反后装配过程受力位移导致 b.自验及客验面板拆卸后复原过程受力位移导致（本次客诉产品处于半开状态） | T83: 库存六开产品M26A003-1 EIW 1006 PT返工全检玻璃面板外观及功能测试 | U83: 1.供应商改善，产线自检 2.导光板正面增加打点标记 | V83: 否 | W83: 人员培训 | X83: 宜胜照明1 | Y83: 生产一 | Z83: 46154 | AA83: 46154 | AB83: =IF(A83="","",_xlfn.IFS(AND(Z83=0,AA83=0),"未回复",AND(AA83<>0,Z83=0),"报错",AND(Z83>=NOW(),Z83<>0,AA83=0),"正常进行中",AND(AA83<>0,Z83>=AA83),"按时关闭",AND(Z83<>0,Z83<=AA83),"延期关闭",AND(AA83=0,Z83<NOW()),"延期未关闭")) -> 按时关闭 | AD83: =IF(Z83="","",YEAR(Z83)) -> 2026 | AE83: =IF(Z83="","",TEXT(Z83,"m")) -> 5 | AF83: =IF(Z83="","","W"&WEEKNUM(Z83,2)) -> W20
A84: 46157 | B84: =IF(A84="","",YEAR(A84)) -> 2026 | C84: =IF(A84="","",TEXT(A84,"m")) -> 5 | D84: =IF(A84="","","W"&WEEKNUM(A84,2)) -> W20 | E84: F226Z001 | F84: GU10 5W 3000K/4000K/6500K | G84: 中国1224 | H84: 宜胜照明1 | L84: 订单:F226Z001-1 型号:GU10 5W 6500K/4000K/3000K 订单数量：2025+3025+5025PCS 问题描述： 1. 铝基板歪斜，透镜易脱落 2. 个别灯具透镜缺失 3. 部分灯具不亮、敲击闪烁 4. 6500K灯具接触不良不亮 5. 色温混装（4000K混装6500K） 6. 金属插脚不平整、有突出 7. 1000个3000K无灯印产品返工出货 | M84: 5025+3025+2025 | N84: 582 | O84: 0.0578 | P84: 售后客诉 | Q84: 安规 | R84: 1. 交期紧急，胶水未固化即发货，散件倒置运输震动，导致铝基板歪斜、透镜脱落、接触不良、灯不亮/闪烁 2. 无透镜拉力标准，装配不牢，出现透镜缺失 3. 未按色温分区包装，赶货操作疏忽，造成色温混装 4. 工艺单未明确无灯印要求，信息传达不到位，产品返工 | S84: 其它 | T84: 不良退货返工 | U84: 1. 优化排产，预留胶水固化时间，严禁赶交期生产 2. 制定透镜拉力标准≥30N（内控≥40N） 3. 打胶由300°改为360°，增加等离子表面处理（等离子设备增加预期完成时间2026/7/20) 4. 客户特殊要求工艺单资料明确，临时增加要求需正式邮件通知计划、生产、品质等相关人员 | V84: 否 | W84: 工艺优化 | X84: 宜胜照明1 | Y84: 生产一 | Z84: 46162 | AA84: 46162 | AB84: =IF(A84="","",_xlfn.IFS(AND(Z84=0,AA84=0),"未回复",AND(AA84<>0,Z84=0),"报错",AND(Z84>=NOW(),Z84<>0,AA84=0),"正常进行中",AND(AA84<>0,Z84>=AA84),"按时关闭",AND(Z84<>0,Z84<=AA84),"延期关闭",AND(AA84=0,Z84<NOW()),"延期未关闭")) -> 按时关闭 | AD84: =IF(Z84="","",YEAR(Z84)) -> 2026 | AE84: =IF(Z84="","",TEXT(Z84,"m")) -> 5 | AF84: =IF(Z84="","","W"&WEEKNUM(Z84,2)) -> W21
A85: 46160 | B85: =IF(A85="","",YEAR(A85)) -> 2026 | C85: =IF(A85="","",TEXT(A85,"m")) -> 5 | D85: =IF(A85="","","W"&WEEKNUM(A85,2)) -> W21 | E85: W26M008-1 | F85: A80-20W-6500K | G85: 克罗地亚019 | H85: 宜胜照明1 | K85: 李宁 | L85: 订单:W26M008-1 型号:A80-20W-6500K 订单数量：3000pcs 问题描述：包装热缩方式错误，要求每5pcs一包热缩，实际每10pcs一包热缩 | M85: 3000 | N85: 3000 | O85: =IFERROR(N85/M85,"") -> 1 | P85: 售后客诉 | Q85: 包装 | R85: 订单W26M008-1所有款式包装热缩方式除A80-20W-6500K为5pcs/包，其余均为10pcs/包，生产及检验未详细核对工艺单、确认包装热缩方式，导致漏检批量流出 | S85: 人员作业 | T85: 同批次其他款式包装方式排查，在制订单排查（无） | U85: 1.所有订单上线前，生产与IPQC分别核对工艺单包装规格，首件必须确认包装数量； 2.IPQC巡检增加包装数量核对项，每批次不定时抽查，异常立即停线； 3.定期组织检验方法、工艺单核对、质量意识培训，强化全员质量意识 4.检验组长对相关IPQC/FQC单独辅导，连续1周稽查其检验记录，确保执行到位。 | V85: 否 | W85: 人员培训 | X85: 宜胜照明1 | Y85: 生产一 | Z85: 46161 | AA85: 46161 | AB85: =IF(A85="","",_xlfn.IFS(AND(Z85=0,AA85=0),"未回复",AND(AA85<>0,Z85=0),"报错",AND(Z85>=NOW(),Z85<>0,AA85=0),"正常进行中",AND(AA85<>0,Z85>=AA85),"按时关闭",AND(Z85<>0,Z85<=AA85),"延期关闭",AND(AA85=0,Z85<NOW()),"延期未关闭")) -> 按时关闭 | AD85: =IF(Z85="","",YEAR(Z85)) -> 2026 | AE85: =IF(Z85="","",TEXT(Z85,"m")) -> 5 | AF85: =IF(Z85="","","W"&WEEKNUM(Z85,2)) -> W21
B86: =IF(A86="","",YEAR(A86)) | C86: =IF(A86="","",TEXT(A86,"m")) | D86: =IF(A86="","","W"&WEEKNUM(A86,2)) | O86: =IFERROR(N86/M86,"") | AB86: =IF(A86="","",_xlfn.IFS(AND(Z86=0,AA86=0),"未回复",AND(AA86<>0,Z86=0),"报错",AND(Z86>=NOW(),Z86<>0,AA86=0),"正常进行中",AND(AA86<>0,Z86>=AA86),"按时关闭",AND(Z86<>0,Z86<=AA86),"延期关闭",AND(AA86=0,Z86<NOW()),"延期未关闭")) | AD86: =IF(Z86="","",YEAR(Z86)) | AE86: =IF(Z86="","",TEXT(Z86,"m")) | AF86: =IF(Z86="","","W"&WEEKNUM(Z86,2))
B87: =IF(A87="","",YEAR(A87)) | C87: =IF(A87="","",TEXT(A87,"m")) | D87: =IF(A87="","","W"&WEEKNUM(A87,2)) | O87: =IFERROR(N87/M87,"") | AB87: =IF(A87="","",_xlfn.IFS(AND(Z87=0,AA87=0),"未回复",AND(AA87<>0,Z87=0),"报错",AND(Z87>=NOW(),Z87<>0,AA87=0),"正常进行中",AND(AA87<>0,Z87>=AA87),"按时关闭",AND(Z87<>0,Z87<=AA87),"延期关闭",AND(AA87=0,Z87<NOW()),"延期未关闭")) | AD87: =IF(Z87="","",YEAR(Z87)) | AE87: =IF(Z87="","",TEXT(Z87,"m")) | AF87: =IF(Z87="","","W"&WEEKNUM(Z87,2))
B88: =IF(A88="","",YEAR(A88)) | C88: =IF(A88="","",TEXT(A88,"m")) | D88: =IF(A88="","","W"&WEEKNUM(A88,2)) | O88: =IFERROR(N88/M88,"") | AB88: =IF(A88="","",_xlfn.IFS(AND(Z88=0,AA88=0),"未回复",AND(AA88<>0,Z88=0),"报错",AND(Z88>=NOW(),Z88<>0,AA88=0),"正常进行中",AND(AA88<>0,Z88>=AA88),"按时关闭",AND(Z88<>0,Z88<=AA88),"延期关闭",AND(AA88=0,Z88<NOW()),"延期未关闭")) | AD88: =IF(Z88="","",YEAR(Z88)) | AE88: =IF(Z88="","",TEXT(Z88,"m")) | AF88: =IF(Z88="","","W"&WEEKNUM(Z88,2))
B89: =IF(A89="","",YEAR(A89)) | C89: =IF(A89="","",TEXT(A89,"m")) | D89: =IF(A89="","","W"&WEEKNUM(A89,2)) | O89: =IFERROR(N89/M89,"") | AB89: =IF(A89="","",_xlfn.IFS(AND(Z89=0,AA89=0),"未回复",AND(AA89<>0,Z89=0),"报错",AND(Z89>=NOW(),Z89<>0,AA89=0),"正常进行中",AND(AA89<>0,Z89>=AA89),"按时关闭",AND(Z89<>0,Z89<=AA89),"延期关闭",AND(AA89=0,Z89<NOW()),"延期未关闭")) | AD89: =IF(Z89="","",YEAR(Z89)) | AE89: =IF(Z89="","",TEXT(Z89,"m")) | AF89: =IF(Z89="","","W"&WEEKNUM(Z89,2))
B90: =IF(A90="","",YEAR(A90)) | C90: =IF(A90="","",TEXT(A90,"m")) | D90: =IF(A90="","","W"&WEEKNUM(A90,2)) | O90: =IFERROR(N90/M90,"") | AB90: =IF(A90="","",_xlfn.IFS(AND(Z90=0,AA90=0),"未回复",AND(AA90<>0,Z90=0),"报错",AND(Z90>=NOW(),Z90<>0,AA90=0),"正常进行中",AND(AA90<>0,Z90>=AA90),"按时关闭",AND(Z90<>0,Z90<=AA90),"延期关闭",AND(AA90=0,Z90<NOW()),"延期未关闭")) | AD90: =IF(Z90="","",YEAR(Z90)) | AE90: =IF(Z90="","",TEXT(Z90,"m")) | AF90: =IF(Z90="","","W"&WEEKNUM(Z90,2))
B91: =IF(A91="","",YEAR(A91)) | C91: =IF(A91="","",TEXT(A91,"m")) | D91: =IF(A91="","","W"&WEEKNUM(A91,2)) | O91: =IFERROR(N91/M91,"") | AB91: =IF(A91="","",_xlfn.IFS(AND(Z91=0,AA91=0),"未回复",AND(AA91<>0,Z91=0),"报错",AND(Z91>=NOW(),Z91<>0,AA91=0),"正常进行中",AND(AA91<>0,Z91>=AA91),"按时关闭",AND(Z91<>0,Z91<=AA91),"延期关闭",AND(AA91=0,Z91<NOW()),"延期未关闭")) | AD91: =IF(Z91="","",YEAR(Z91)) | AE91: =IF(Z91="","",TEXT(Z91,"m")) | AF91: =IF(Z91="","","W"&WEEKNUM(Z91,2))
B92: =IF(A92="","",YEAR(A92)) | C92: =IF(A92="","",TEXT(A92,"m")) | D92: =IF(A92="","","W"&WEEKNUM(A92,2)) | O92: =IFERROR(N92/M92,"") | AB92: =IF(A92="","",_xlfn.IFS(AND(Z92=0,AA92=0),"未回复",AND(AA92<>0,Z92=0),"报错",AND(Z92>=NOW(),Z92<>0,AA92=0),"正常进行中",AND(AA92<>0,Z92>=AA92),"按时关闭",AND(Z92<>0,Z92<=AA92),"延期关闭",AND(AA92=0,Z92<NOW()),"延期未关闭")) | AD92: =IF(Z92="","",YEAR(Z92)) | AE92: =IF(Z92="","",TEXT(Z92,"m")) | AF92: =IF(Z92="","","W"&WEEKNUM(Z92,2))
B93: =IF(A93="","",YEAR(A93)) | C93: =IF(A93="","",TEXT(A93,"m")) | D93: =IF(A93="","","W"&WEEKNUM(A93,2)) | O93: =IFERROR(N93/M93,"") | AB93: =IF(A93="","",_xlfn.IFS(AND(Z93=0,AA93=0),"未回复",AND(AA93<>0,Z93=0),"报错",AND(Z93>=NOW(),Z93<>0,AA93=0),"正常进行中",AND(AA93<>0,Z93>=AA93),"按时关闭",AND(Z93<>0,Z93<=AA93),"延期关闭",AND(AA93=0,Z93<NOW()),"延期未关闭")) | AD93: =IF(Z93="","",YEAR(Z93)) | AE93: =IF(Z93="","",TEXT(Z93,"m")) | AF93: =IF(Z93="","","W"&WEEKNUM(Z93,2))
B94: =IF(A94="","",YEAR(A94)) | C94: =IF(A94="","",TEXT(A94,"m")) | D94: =IF(A94="","","W"&WEEKNUM(A94,2)) | O94: =IFERROR(N94/M94,"") | AB94: =IF(A94="","",_xlfn.IFS(AND(Z94=0,AA94=0),"未回复",AND(AA94<>0,Z94=0),"报错",AND(Z94>=NOW(),Z94<>0,AA94=0),"正常进行中",AND(AA94<>0,Z94>=AA94),"按时关闭",AND(Z94<>0,Z94<=AA94),"延期关闭",AND(AA94=0,Z94<NOW()),"延期未关闭")) | AD94: =IF(Z94="","",YEAR(Z94)) | AE94: =IF(Z94="","",TEXT(Z94,"m")) | AF94: =IF(Z94="","","W"&WEEKNUM(Z94,2))
B95: =IF(A95="","",YEAR(A95)) | C95: =IF(A95="","",TEXT(A95,"m")) | D95: =IF(A95="","","W"&WEEKNUM(A95,2)) | O95: =IFERROR(N95/M95,"") | AB95: =IF(A95="","",_xlfn.IFS(AND(Z95=0,AA95=0),"未回复",AND(AA95<>0,Z95=0),"报错",AND(Z95>=NOW(),Z95<>0,AA95=0),"正常进行中",AND(AA95<>0,Z95>=AA95),"按时关闭",AND(Z95<>0,Z95<=AA95),"延期关闭",AND(AA95=0,Z95<NOW()),"延期未关闭")) | AD95: =IF(Z95="","",YEAR(Z95)) | AE95: =IF(Z95="","",TEXT(Z95,"m")) | AF95: =IF(Z95="","","W"&WEEKNUM(Z95,2))
B96: =IF(A96="","",YEAR(A96)) | C96: =IF(A96="","",TEXT(A96,"m")) | D96: =IF(A96="","","W"&WEEKNUM(A96,2)) | O96: =IFERROR(N96/M96,"") | AB96: =IF(A96="","",_xlfn.IFS(AND(Z96=0,AA96=0),"未回复",AND(AA96<>0,Z96=0),"报错",AND(Z96>=NOW(),Z96<>0,AA96=0),"正常进行中",AND(AA96<>0,Z96>=AA96),"按时关闭",AND(Z96<>0,Z96<=AA96),"延期关闭",AND(AA96=0,Z96<NOW()),"延期未关闭")) | AD96: =IF(Z96="","",YEAR(Z96)) | AE96: =IF(Z96="","",TEXT(Z96,"m")) | AF96: =IF(Z96="","","W"&WEEKNUM(Z96,2))
B97: =IF(A97="","",YEAR(A97)) | C97: =IF(A97="","",TEXT(A97,"m")) | D97: =IF(A97="","","W"&WEEKNUM(A97,2)) | O97: =IFERROR(N97/M97,"") | AB97: =IF(A97="","",_xlfn.IFS(AND(Z97=0,AA97=0),"未回复",AND(AA97<>0,Z97=0),"报错",AND(Z97>=NOW(),Z97<>0,AA97=0),"正常进行中",AND(AA97<>0,Z97>=AA97),"按时关闭",AND(Z97<>0,Z97<=AA97),"延期关闭",AND(AA97=0,Z97<NOW()),"延期未关闭")) | AD97: =IF(Z97="","",YEAR(Z97)) | AE97: =IF(Z97="","",TEXT(Z97,"m")) | AF97: =IF(Z97="","","W"&WEEKNUM(Z97,2))
... B277: =IF(A277="","",YEAR(A277)) | C277: =IF(A277="","",TEXT(A277,"m")) | D277: =IF(A277="","","W"&WEEKNUM(A277,2)) | O277: =IFERROR(N277/M277,"") | AB277: =IF(A277="","",_xlfn.IFS(AND(Z277=0,AA277=0),"未回复",AND(AA277<>0,Z277=0),"报错",AND(Z277>=NOW(),Z277<>0,AA277=0),"正常进行中",AND(AA277<>0,Z277>=AA277),"按时关闭",AND(Z277<>0,Z277<=AA277),"延期关闭",AND(AA277=0,Z277<NOW()),"延期未关闭")) | AD277: =IF(Z277="","",YEAR(Z277)) | AE277: =IF(Z277="","",TEXT(Z277,"m")) | AF277: =IF(Z277="","","W"&WEEKNUM(Z277,2))

Sheet 宜胜客验台账 
A1: 发生时间 | B1: 年 | C1: 月 | D1: 周 | E1: 订单号 | F1: 产品型号 | G1: 客户 | H1: 事业部 | I1: 业务 | J1: 产品 | K1: CQE | L1: 问题描述 | M1: 问题来源 | N1: 问题类别 | O1: 原因分析 | P1: 原因类别 | Q1: 临时措施 | R1: 长期措施 | S1: 是否根本解 | T1: 措施类型 | U1: 责任部门 | V1: 二级部门3 | W1: 计划完成时间 | X1: 实际完成时间 | Y1: 状态 | Z1: 跟进人 | AA1: 计划完成年 | AB1: 计划完成月 | AC1: 计划完成周
A2: 45467 | B2: =IF(A2="","",YEAR(A2)) -> 2024 | C2: =IF(A2="","",TEXT(A2,"m")) -> 6 | D2: =IF(A2="","","W"&WEEKNUM(A2,2)) -> W26 | E2: M24H004-A | F2: ST-WS70071-1800W3-WFT-G2-单开-黑色 | G2: 巴西527 | H2: 宜胜照明1 | I2: 李佳思 | J2: 赖长金 | K2: 丁亚双 | L2: 客验中发现彩盒上有蓝色油印，不良比例31% | M2: 客户验货 | N2: 包装 | O2: 一、彩盒上有蓝色油印： 1.原因分析：天气潮湿原因，在生产过程中油墨未干，导致部分油墨擦花在在白色纸张上。 2、供应商在制作过程中因环境原因，导致不良流。 | P2: 来料不良 | Q2: 1、针对接到客户验货失败问题组织小组紧急处理，将对不良图片发到供应商，回复改善对策，并通知生产， 来料确认检验制度，针对供应商改善报告确认。 2、组织组长，主任以及生产工艺研讨此次验货失败的根本真因。 3、对于后续供应商彩盒改善跟进，针对后续来料彩盒检验规范，来料，制程 | R2: 1.供应商更改存放工艺。 2.针对供应商改善效果确认，及我司检验人员进行培训。 3.跟进供应商改善效果确认。 1、增加检验人员及生产人员培训外观质量标准，判定标准。 2、持续跟进我司对彩盒供应商评审，来料检验不良问题点记录，按月考察供应商。将问题跟供应商对接。 | S2: 否 | T2: 工艺优化 | U2: 计划采购部 | V2: 供方管理组 | W2: 45468 | X2: 45468 | Y2: =IF(A2="","",_xlfn.IFS(AND(W2=0,X2=0),"未回复",AND(X2<>0,W2=0),"报错",AND(W2>=NOW(),W2<>0,X2=0),"正常进行中",AND(X2<>0,W2>=X2),"按时关闭",AND(W2<>0,W2<=X2),"延期关闭",AND(X2=0,W2<NOW()),"延期未关闭")) -> 按时关闭 | Z2: 李俊林 | AA2: =IF(W2="","",YEAR(W2)) -> 2024 | AB2: =IF(W2="","",TEXT(W2,"m")) -> 6 | AC2: =IF(W2="","","W"&WEEKNUM(W2,2)) -> W26
A3: 45476 | B3: =IF(A3="","",YEAR(A3)) -> 2024 | C3: =IF(A3="","",TEXT(A3,"m")) -> 7 | D3: =IF(A3="","","W"&WEEKNUM(A3,2)) -> W27 | E3: M24H003/M24H009 | G3: 巴西527 | H3: 宜胜照明1 | I3: 李佳思 | J3: 赖长金 | K3: 丁亚双 | L3: 功能问题：1个插座功能紊乱； | M3: 客户验货 | N3: 功能 | O3: 测试时输出电压不稳定，打开发现输入电压位置虚焊导致 | P3: 人员作业 | Q3: 增加外观检验 | R3: 对该插座功能紊乱，增加自动焊锡机。替代人工焊接，提升焊接的质量 | S3: 是 | T3: 自动化 | U3: 宜胜照明1 | V3: 生产一 | W3: 45488 | Y3: =IF(A3="","",_xlfn.IFS(AND(W3=0,X3=0),"未回复",AND(X3<>0,W3=0),"报错",AND(W3>=NOW(),W3<>0,X3=0),"正常进行中",AND(X3<>0,W3>=X3),"按时关闭",AND(W3<>0,W3<=X3),"延期关闭",AND(X3=0,W3<NOW()),"延期未关闭")) -> 延期未关闭 | Z3: 李俊林 | AA3: =IF(W3="","",YEAR(W3)) -> 2024 | AB3: =IF(W3="","",TEXT(W3,"m")) -> 7 | AC3: =IF(W3="","","W"&WEEKNUM(W3,2)) -> W29
A4: 45476 | B4: =IF(A4="","",YEAR(A4)) -> 2024 | C4: =IF(A4="","",TEXT(A4,"m")) -> 7 | D4: =IF(A4="","","W"&WEEKNUM(A4,2)) -> W27 | E4: M24H003/M24H009 | G4: 巴西527 | H4: 宜胜照明1 | I4: 李佳思 | J4: 赖长金 | K4: 丁亚双 | L4: 功能问题：1个插座按键卡死 | M4: 客户验货 | N4: 功能 | O4: 经打开后发现PCB板上轻触按键歪与外壳按钮顶死 | P4: 过程工艺 | Q4: 插座按键死，增加人员在装配外壳后按键测试，不让不良品流出 | R4: 针对按键按不动，工艺增加工装，对开关按键进行焊接作业。防止开关按键歪斜 | S4: 是 | T4: 防呆防错 | U4: 宜胜照明1 | V4: 生产一 | W4: 45488 | Y4: =IF(A4="","",_xlfn.IFS(AND(W4=0,X4=0),"未回复",AND(X4<>0,W4=0),"报错",AND(W4>=NOW(),W4<>0,X4=0),"正常进行中",AND(X4<>0,W4>=X4),"按时关闭",AND(W4<>0,W4<=X4),"延期关闭",AND(X4=0,W4<NOW()),"延期未关闭")) -> 延期未关闭 | Z4: 李俊林 | AA4: =IF(W4="","",YEAR(W4)) -> 2024 | AB4: =IF(W4="","",TEXT(W4,"m")) -> 7 | AC4: =IF(W4="","","W"&WEEKNUM(W4,2)) -> W29
A5: 45476 | B5: =IF(A5="","",YEAR(A5)) -> 2024 | C5: =IF(A5="","",TEXT(A5,"m")) -> 7 | D5: =IF(A5="","","W"&WEEKNUM(A5,2)) -> W27 | E5: M24H003/M24H009 | G5: 巴西527 | H5: 宜胜照明1 | I5: 李佳思 | J5: 赖长金 | K5: 丁亚双 | L5: 外观问题： logo丝印倾斜，参数面丝印不居 | M5: 客户验货 | N5: 外观 | O5: logo丝印倾斜，参数面丝印不居:经确认发现打激光时，定位模具不精确 | P5: 过程工艺 | Q5: 修改定位模具 | R5: 激光打印歪斜：增加工装：1.一个打印LOGO面，利用LN针脚防止员工方向放错。2.一个治具的是产品要反过来，利用中间地针防止员工方向放错。 | S5: 是 | T5: 防呆防错 | U5: 宜胜照明1 | V5: 生产一 | W5: 45488 | Y5: =IF(A5="","",_xlfn.IFS(AND(W5=0,X5=0),"未回复",AND(X5<>0,W5=0),"报错",AND(W5>=NOW(),W5<>0,X5=0),"正常进行中",AND(X5<>0,W5>=X5),"按时关闭",AND(W5<>0,W5<=X5),"延期关闭",AND(X5=0,W5<NOW()),"延期未关闭")) -> 延期未关闭 | Z5: 李俊林 | AA5: =IF(W5="","",YEAR(W5)) -> 2024 | AB5: =IF(W5="","",TEXT(W5,"m")) -> 7 | AC5: =IF(W5="","","W"&WEEKNUM(W5,2)) -> W29
A6: 45475 | B6: =IF(A6="","",YEAR(A6)) -> 2024 | C6: =IF(A6="","",TEXT(A6,"m")) -> 7 | D6: =IF(A6="","","W"&WEEKNUM(A6,2)) -> W27 | E6: C24J0412- | F6: EL2206-10W | G6: 美国1024 | H6: 宜胜照明2 | I6: 罗倩倩 | J6: 史睿 | L6: 磁铁脱落 | M6: 客户验货 | N6: 功能 | O6: 生产时有发现磁铁掉落现象，磁铁牢固性SOP无明确要求，所以生产及检验未做检验，成品检验时也只抽检了几个 | P6: 结构设计 | Q6: 7月6号更改原返工方案磁铁吸力测试3次为测试10次，临时使用496瞬干胶进行返工 | R6: 1.黏磁铁胶水更改为8326结构胶，经验证双85高温高湿加破坏性试验取磁铁，牢固性OK | S6: 是 | T6: 设计变更-预防 | U6: 宜胜照明2 | W6: 45488 | X6: 45488 | Y6: =IF(A6="","",_xlfn.IFS(AND(W6=0,X6=0),"未回复",AND(X6<>0,W6=0),"报错",AND(W6>=NOW(),W6<>0,X6=0),"正常进行中",AND(X6<>0,W6>=X6),"按时关闭",AND(W6<>0,W6<=X6),"延期关闭",AND(X6=0,W6<NOW()),"延期未关闭")) -> 按时关闭 | Z6: 赵纯杰 | AA6: =IF(W6="","",YEAR(W6)) -> 2024 | AB6: =IF(W6="","",TEXT(W6,"m")) -> 7 | AC6: =IF(W6="","","W"&WEEKNUM(W6,2)) -> W29
A7: 45499 | B7: =IF(A7="","",YEAR(A7)) -> 2024 | C7: =IF(A7="","",TEXT(A7,"m")) -> 7 | D7: =IF(A7="","","W"&WEEKNUM(A7,2)) -> W30 | E7: A124R011-1 | F7: Z2-LG189-50W-RGB | G7: 中国907 | H7: 宜胜照明3 | I7: 傅利玮 | J7: 王燕赟 | K7: 王超 | L7: 抽验20PCS防水，发现2PCS产品内部出现流动的水珠 | M7: 客户验货 | N7: 功能 | O7: 壳体沙眼漏水，消耗老壳体库存，新结构壳体未发现漏水现象 | P7: 结构设计 | Q7: 泡水全检 | R7: 壳体结构已变更，老壳体沙眼问题无解决方案不得上线 | S7: 是 | T7: 设计变更-预防 | U7: 宜胜照明3 | V7: 生产三 | W7: 45502 | X7: 45502 | Y7: =IF(A7="","",_xlfn.IFS(AND(W7=0,X7=0),"未回复",AND(X7<>0,W7=0),"报错",AND(W7>=NOW(),W7<>0,X7=0),"正常进行中",AND(X7<>0,W7>=X7),"按时关闭",AND(W7<>0,W7<=X7),"延期关闭",AND(X7=0,W7<NOW()),"延期未关闭")) -> 按时关闭 | Z7: 赵纯杰 | AA7: =IF(W7="","",YEAR(W7)) -> 2024 | AB7: =IF(W7="","",TEXT(W7,"m")) -> 7 | AC7: =IF(W7="","","W"&WEEKNUM(W7,2)) -> W31
A8: 45499 | B8: =IF(A8="","",YEAR(A8)) -> 2024 | C8: =IF(A8="","",TEXT(A8,"m")) -> 7 | D8: =IF(A8="","","W"&WEEKNUM(A8,2)) -> W30 | E8: A124R011-1 | F8: Z2-LG189-50W-RGB | G8: 中国907 | H8: 宜胜照明3 | I8: 傅利玮 | J8: 王燕赟 | K8: 王超 | L8: 测试发现1PCS遥控失灵 | M8: 客户验货 | N8: 功能 | O8: 感应器信号接收异常 | P8: 过程工艺 | Q8: 遥控器一对一全检测试 | R8: 后续生产增加灯具与遥控器一对一测试 | S8: 否 | T8: 工艺优化 | U8: 宜胜照明3 | V8: 生产三 | W8: 45502 | X8: 45502 | Y8: =IF(A8="","",_xlfn.IFS(AND(W8=0,X8=0),"未回复",AND(X8<>0,W8=0),"报错",AND(W8>=NOW(),W8<>0,X8=0),"正常进行中",AND(X8<>0,W8>=X8),"按时关闭",AND(W8<>0,W8<=X8),"延期关闭",AND(X8=0,W8<NOW()),"延期未关闭")) -> 按时关闭 | Z8: 赵纯杰 | AA8: =IF(W8="","",YEAR(W8)) -> 2024 | AB8: =IF(W8="","",TEXT(W8,"m")) -> 7 | AC8: =IF(W8="","","W"&WEEKNUM(W8,2)) -> W31
A9: 45499 | B9: =IF(A9="","",YEAR(A9)) -> 2024 | C9: =IF(A9="","",TEXT(A9,"m")) -> 7 | D9: =IF(A9="","","W"&WEEKNUM(A9,2)) -> W30 | E9: A124R011-1 | F9: Z2-LG189-50W-RGB | G9: 中国907 | H9: 宜胜照明3 | I9: 傅利玮 | J9: 王燕赟 | K9: 王超 | L9: 产品彩盒LOG、彩盒底部二维码LOG与资料不一致，缺少LE，不良率100% | M9: 客户验货 | N9: 包装 | O9: 1.业务资料变更未通知 2.人员未核对出彩盒异常 | P9: 其它 | Q9: 超买标贴覆盖 | R9: 1.资料变更需走变更流程，并通知跟单、生产及品质 2.检验人员培训，漏检记入考核 | S9: 否 | T9: 纠错 | U9: 宜胜照明3 | V9: 研发一 | W9: 45502 | X9: 45502 | Y9: =IF(A9="","",_xlfn.IFS(AND(W9=0,X9=0),"未回复",AND(X9<>0,W9=0),"报错",AND(W9>=NOW(),W9<>0,X9=0),"正常进行中",AND(X9<>0,W9>=X9),"按时关闭",AND(W9<>0,W9<=X9),"延期关闭",AND(X9=0,W9<NOW()),"延期未关闭")) -> 按时关闭 | Z9: 赵纯杰 | AA9: =IF(W9="","",YEAR(W9)) -> 2024 | AB9: =IF(W9="","",TEXT(W9,"m")) -> 7 | AC9: =IF(W9="","","W"&WEEKNUM(W9,2)) -> W31
A10: 45499 | B10: =IF(A10="","",YEAR(A10)) -> 2024 | C10: =IF(A10="","",TEXT(A10,"m")) -> 7 | D10: =IF(A10="","","W"&WEEKNUM(A10,2)) -> W30 | E10: L24Y017/L24Y023 | G10: 墨西哥296 | K10: 丁亚双 | L10: 灯头底座有尖锐毛刺 1.25% 2. 产品有脏污 6.25% | M10: 客户验货 | N10: 外观 | Y10: =IF(A10="","",_xlfn.IFS(AND(W10=0,X10=0),"未回复",AND(X10<>0,W10=0),"报错",AND(W10>=NOW(),W10<>0,X10=0),"正常进行中",AND(X10<>0,W10>=X10),"按时关闭",AND(W10<>0,W10<=X10),"延期关闭",AND(X10=0,W10<NOW()),"延期未关闭")) -> 未回复 | Z10: 李俊林 | AA10: =IF(W10="","",YEAR(W10)) | AB10: =IF(W10="","",TEXT(W10,"m")) | AC10: =IF(W10="","","W"&WEEKNUM(W10,2))
A11: 45511 | B11: =IF(A11="","",YEAR(A11)) -> 2024 | C11: =IF(A11="","",TEXT(A11,"m")) -> 8 | D11: =IF(A11="","","W"&WEEKNUM(A11,2)) -> W32 | E11: M24H009 | F11: 插座 | G11: 巴西527 | H11: 宜胜照明1 | I11: 徐赢意 | J11: 赖长金 | K11: 丁亚双 | L11: 1.产品丝印不良。2.产品标签不良。3.6个彩盒标签方向反了。4.彩盒颜色不一致。 | M11: 客户验货 | N11: 外观 | O11: 1.外观不良： 1.产品丝印不良。2.产品标签不良。 3.6个彩盒标签方向反了。 4.彩盒颜色不一致。 1.产品丝印不良：生产作业人员补尾数打印时，未放平在定位模具里，就开始作业导致激光丝印不良。 2.产品标签不良：排查发现生产尾数时，因标签数量不够，使用机器打印，导致标签未覆膜，造成产品标签不良。 3.6个彩盒标签方向反了：经过确认为生产尾数时未经过流水线作业环节， 导致产品标签贴反。 4.彩盒颜色不一致：仓库物料排查，发现我司彩盒放置在仓库窗口边，导致阳光照射，出现颜色不一致。 | P11: 人员作业 | Q11: 1，针对外观不良的，进行返工。检查产品外观，功能测试。 2、彩盒颜色不一致，经过生产品质采购决定，此批彩盒全部进行更换处理，确保彩盒颜色一致性。 2、针对外观不良，返工发现8台，8台进行外壳更换。丝印不良返工未发现不良品 | R11: 1、生产人员进行培训，后续尾数进行管控处理。 2、针对后续尾数进行100%全检，生产检验完成，尾数报检品质进行100%全检。 3、针对尾数50-100之间，生产、品质进行100%全检。 | S11: 否 | T11: 人员培训 | U11: 宜胜照明1 | V11: 生产一 | W11: 45511 | X11: 45511 | Y11: =IF(A11="","",_xlfn.IFS(AND(W11=0,X11=0),"未回复",AND(X11<>0,W11=0),"报错",AND(W11>=NOW(),W11<>0,X11=0),"正常进行中",AND(X11<>0,W11>=X11),"按时关闭",AND(W11<>0,W11<=X11),"延期关闭",AND(X11=0,W11<NOW()),"延期未关闭")) -> 按时关闭 | Z11: 李俊林 | AA11: =IF(W11="","",YEAR(W11)) -> 2024 | AB11: =IF(W11="","",TEXT(W11,"m")) -> 8 | AC11: =IF(W11="","","W"&WEEKNUM(W11,2)) -> W32
A12: 45516 | B12: =IF(A12="","",YEAR(A12)) -> 2024 | C12: =IF(A12="","",TEXT(A12,"m")) -> 8 | D12: =IF(A12="","","W"&WEEKNUM(A12,2)) -> W33 | E12: P24I004 | F12: LG172L | G12: 俄罗斯1836 | H12: 宜胜照明3 | J12: 王燕赟 | K12: 刘晓慧 | L12: 客验测试IP65时 ，发现3PCS产品进水，分别为： 1.GPLF-30 1pc 小水珠 2.GTMS-60 1pc 三分之一圈未打胶 进水量大 3.GLS-100 1pc 小水珠 | M12: 客户验货 | N12: 功能 | O12: 1.固化夹子不够； 2.打胶设备调机 3.生产员工盖玻璃前未进行检查或检查不仔细； 4.换胶过程 5.胶水来料内部空气； 6.设备气压不稳定 | P12: 人员作业 | Q12: 1.热态泡水5-10S,产品需要全部浸末； 2.浸水后气枪将表面水吹干净后进行仔细检查 | R12: 1.增加固化使用夹子； 2.使用带增压棒的打胶设备（172） 3.打胶人员固定，上岗人员培训教育 4.打胶合玻璃后增加按压动作； 5.大货班组长需要自检防水，IPQC抽检防水 | S12: 是 | T12: 其它 | U12: 宜胜照明3 | V12: 生产三 | W12: 45520 | X12: 45520 | Y12: =IF(A12="","",_xlfn.IFS(AND(W12=0,X12=0),"未回复",AND(X12<>0,W12=0),"报错",AND(W12>=NOW(),W12<>0,X12=0),"正常进行中",AND(X12<>0,W12>=X12),"按时关闭",AND(W12<>0,W12<=X12),"延期关闭",AND(X12=0,W12<NOW()),"延期未关闭")) -> 按时关闭 | Z12: 赵纯杰 | AA12: =IF(W12="","",YEAR(W12)) -> 2024 | AB12: =IF(W12="","",TEXT(W12,"m")) -> 8 | AC12: =IF(W12="","","W"&WEEKNUM(W12,2)) -> W33
A13: 45517 | B13: =IF(A13="","",YEAR(A13)) -> 2024 | C13: =IF(A13="","",TEXT(A13,"m")) -> 8 | D13: =IF(A13="","","W"&WEEKNUM(A13,2)) -> W33 | E13: R24X0517-1 | F13: RL160C-150W | G13: 俄罗斯745 | H13: 宜胜照明3 | J13: 陈中平协助 | K13: 李冬雪 | L13: 低温-40度启动不过，出现闪灯现象 | M13: 客户验货 | N13: 功能 | O13: 按研发方案R5改成51010200300 RES-SMD-1206-160K-5%-0.25W 两个电解电容改成51020400749 电容-电解电容 330uF-80V-10x25-105°-6KH-脚长3.5 云睿 ，经验证-40℃低温测试合格，无闪灯现象 | P13: 电子设计 | Q13: 按验证方案返工 | R13: 按验证方案更改电子设计 | S13: 是 | T13: 设计变更-预防 | U13: 宜胜照明3 | V13: 研发一 | W13: 45524 | X13: 45524 | Y13: =IF(A13="","",_xlfn.IFS(AND(W13=0,X13=0),"未回复",AND(X13<>0,W13=0),"报错",AND(W13>=NOW(),W13<>0,X13=0),"正常进行中",AND(X13<>0,W13>=X13),"按时关闭",AND(W13<>0,W13<=X13),"延期关闭",AND(X13=0,W13<NOW()),"延期未关闭")) -> 按时关闭 | AA13: =IF(W13="","",YEAR(W13)) -> 2024 | AB13: =IF(W13="","",TEXT(W13,"m")) -> 8 | AC13: =IF(W13="","","W"&WEEKNUM(W13,2)) -> W34
A14: 45495 | B14: =IF(A14="","",YEAR(A14)) -> 2024 | C14: =IF(A14="","",TEXT(A14,"m")) -> 7 | D14: =IF(A14="","","W"&WEEKNUM(A14,2)) -> W30 | E14: Y24K014-1 | F14: CE3030_30W | G14: 10030300028 | H14: 宜胜照明2 | J14: 杜捷 | L14: 浪涌测L-N 1KV不过，500V也不过，研发、业务沟通先客验，客验不合格 | M14: 客户验货 | N14: 功能 | O14: 设计原因 | P14: 电子设计 | Q14: 返工成本较高，需要10元/pcs,暂无其他解决方案 | Y14: =IF(A14="","",_xlfn.IFS(AND(W14=0,X14=0),"未回复",AND(X14<>0,W14=0),"报错",AND(W14>=NOW(),W14<>0,X14=0),"正常进行中",AND(X14<>0,W14>=X14),"按时关闭",AND(W14<>0,W14<=X14),"延期关闭",AND(X14=0,W14<NOW()),"延期未关闭")) -> 未回复 | AA14: =IF(W14="","",YEAR(W14)) | AB14: =IF(W14="","",TEXT(W14,"m")) | AC14: =IF(W14="","","W"&WEEKNUM(W14,2))
A15: 45525 | B15: =IF(A15="","",YEAR(A15)) -> 2024 | C15: =IF(A15="","",TEXT(A15,"m")) -> 8 | D15: =IF(A15="","","W"&WEEKNUM(A15,2)) -> W34 | E15: A124S048 | F15: 球泡 | G15: 郎德万斯-俄罗斯 | H15: 宜胜照明1 | I15: 张美娟 | L15: 外箱LOGO 工艺单是不需要印刷的 、客户验货发现 | M15: 客户验货 | N15: 外观 | O15: 经过调查发现，7/19号来料外箱与工艺单不符，此工单外箱IQC检验，已经发现问题，并通知采购进行处理，并通知仓库进行退货处理。已做好不良标识，生产时，仓库将不良外箱发放生产使用，未将重新购买外箱发放。生产作业时，未检验出，导致生产错误，FQC验货未发现，导致货物流出。 | P15: 来料不良 | Q15: 更换外箱 | S15: 否 | T15: 纠错 | U15: 其它事业部 | W15: 45519 | X15: 45527 | Y15: =IF(A15="","",_xlfn.IFS(AND(W15=0,X15=0),"未回复",AND(X15<>0,W15=0),"报错",AND(W15>=NOW(),W15<>0,X15=0),"正常进行中",AND(X15<>0,W15>=X15),"按时关闭",AND(W15<>0,W15<=X15),"延期关闭",AND(X15=0,W15<NOW()),"延期未关闭")) -> 延期关闭 | AA15: =IF(W15="","",YEAR(W15)) -> 2024 | AB15: =IF(W15="","",TEXT(W15,"m")) -> 8 | AC15: =IF(W15="","","W"&WEEKNUM(W15,2)) -> W33
A16: 45527 | B16: =IF(A16="","",YEAR(A16)) -> 2024 | C16: =IF(A16="","",TEXT(A16,"m")) -> 8 | D16: =IF(A16="","","W"&WEEKNUM(A16,2)) -> W34 | E16: O24B009-1 | F16: 路灯_RL160C-50W | G16: 瑞典176 | H16: 宜胜照明3 | I16: 徐陈艳 | J16: 余元浩 | K16: 李宁 | L16: 打耐压后灯不亮，客户拆机发现，内部合压端子头有漏铜线现象，要求全检返工 | M16: 客户验货 | N16: 安规 | O16: 员工操作不当，压端子压合不良 | P16: 人员作业 | Q16: 全检返工 | Y16: =IF(A16="","",_xlfn.IFS(AND(W16=0,X16=0),"未回复",AND(X16<>0,W16=0),"报错",AND(W16>=NOW(),W16<>0,X16=0),"正常进行中",AND(X16<>0,W16>=X16),"按时关闭",AND(W16<>0,W16<=X16),"延期关闭",AND(X16=0,W16<NOW()),"延期未关闭")) -> 未回复 | AA16: =IF(W16="","",YEAR(W16)) | AB16: =IF(W16="","",TEXT(W16,"m")) | AC16: =IF(W16="","","W"&WEEKNUM(W16,2))
A17: 45540 | B17: =IF(A17="","",YEAR(A17)) -> 2024 | C17: =IF(A17="","",TEXT(A17,"m")) -> 9 | D17: =IF(A17="","","W"&WEEKNUM(A17,2)) -> W36 | E17: A24C005-2 | F17: LG168C-50W 10010400208 | G17: 菲律宾429 | H17: 宜胜照明3 | J17: 王燕赟 | K17: 施奉勇 | L17: 客验时发现灯体表面壳体缝隙，冲水后有漏水现象（毛胚料号： 58010100064宝韵） | M17: 客户验货 | N17: 功能 | O17: 壳体变形导致漏水 | P17: 来料不良 | Q17: 全检返工 | R17: 1.物料来料把控变形严重需判不合格 2.订单生产时确认缝隙大小 如缝隙有单不大 胶水打厚确认玻璃与主体粘结密封 订单继续生产 缝隙大的产品 主体退不良 3.针对该问题车间培训 问题点横向展开避免问题点重复发生 | S17: 否 | T17: 纠错 | U17: 计划采购部 | V17: 供方管理组 | W17: 45541 | X17: 45541 | Y17: =IF(A17="","",_xlfn.IFS(AND(W17=0,X17=0),"未回复",AND(X17<>0,W17=0),"报错",AND(W17>=NOW(),W17<>0,X17=0),"正常进行中",AND(X17<>0,W17>=X17),"按时关闭",AND(W17<>0,W17<=X17),"延期关闭",AND(X17=0,W17<NOW()),"延期未关闭")) -> 按时关闭 | AA17: =IF(W17="","",YEAR(W17)) -> 2024 | AB17: =IF(W17="","",TEXT(W17,"m")) -> 9 | AC17: =IF(W17="","","W"&WEEKNUM(W17,2)) -> W36
A18: 45545 | B18: =IF(A18="","",YEAR(A18)) -> 2024 | C18: =IF(A18="","",TEXT(A18,"m")) -> 9 | D18: =IF(A18="","","W"&WEEKNUM(A18,2)) -> W37 | E18: M24W028-3 | F18: LG189L-200W | G18: 阿根廷215 | H18: 宜胜照明3 | J18: 王燕赟 | L18: 彩盒漏印产品LOGO，不良比例100% | M18: 客户验货 | N18: 包装 | O18: 来料漏印刷、漏检 | P18: 来料不良 | Q18: 返工更换彩盒 | R18: 1.IPQC人员检验流程培训 2.来料加强检验 | S18: 否 | T18: 纠错 | U18: 计划采购部 | V18: 供方管理组 | W18: 45550 | Y18: =IF(A18="","",_xlfn.IFS(AND(W18=0,X18=0),"未回复",AND(X18<>0,W18=0),"报错",AND(W18>=NOW(),W18<>0,X18=0),"正常进行中",AND(X18<>0,W18>=X18),"按时关闭",AND(W18<>0,W18<=X18),"延期关闭",AND(X18=0,W18<NOW()),"延期未关闭")) -> 延期未关闭 | AA18: =IF(W18="","",YEAR(W18)) -> 2024 | AB18: =IF(W18="","",TEXT(W18,"m")) -> 9 | AC18: =IF(W18="","","W"&WEEKNUM(W18,2)) -> W37
A19: 45547 | B19: =IF(A19="","",YEAR(A19)) -> 2024 | C19: =IF(A19="","",TEXT(A19,"m")) -> 9 | D19: =IF(A19="","","W"&WEEKNUM(A19,2)) -> W37 | E19: A124R011 | F19: Z2-LG189-15W-RGB | G19: 中国907 | H19: 宜胜照明3 | J19: 王燕赟 | K19: 王超 | L19: 1PCS遥控失灵 | M19: 客户验货 | N19: 功能 | O19: 三极管虚焊 | P19: 过程工艺 | Q19: 全检返工 | R19: 为之前尾数，目前所有产品已经进行遥控一对一测试 | S19: 否 | T19: 纠错 | U19: 宜胜照明3 | V19: 生产三 | W19: 45547 | X19: 45547 | Y19: =IF(A19="","",_xlfn.IFS(AND(W19=0,X19=0),"未回复",AND(X19<>0,W19=0),"报错",AND(W19>=NOW(),W19<>0,X19=0),"正常进行中",AND(X19<>0,W19>=X19),"按时关闭",AND(W19<>0,W19<=X19),"延期关闭",AND(X19=0,W19<NOW()),"延期未关闭")) -> 按时关闭 | AA19: =IF(W19="","",YEAR(W19)) -> 2024 | AB19: =IF(W19="","",TEXT(W19,"m")) -> 9 | AC19: =IF(W19="","","W"&WEEKNUM(W19,2)) -> W37
A20: 45547 | B20: =IF(A20="","",YEAR(A20)) -> 2024 | C20: =IF(A20="","",TEXT(A20,"m")) -> 9 | D20: =IF(A20="","","W"&WEEKNUM(A20,2)) -> W37 | E20: A124R011 | F20: 10W/20W/15W/50W | G20: 中国907 | H20: 宜胜照明3 | J20: 王燕赟 | K20: 王超 | L20: 测试防水IP65后老化1小时，发现灯体玻璃内出现可移动水珠 | M20: 客户验货 | N20: 内部 | O20: 灯体密封，内外温差形成水汽 | P20: 结构设计 | R20: 暂无解决方案 | Y20: =IF(A20="","",_xlfn.IFS(AND(W20=0,X20=0),"未回复",AND(X20<>0,W20=0),"报错",AND(W20>=NOW(),W20<>0,X20=0),"正常进行中",AND(X20<>0,W20>=X20),"按时关闭",AND(W20<>0,W20<=X20),"延期关闭",AND(X20=0,W20<NOW()),"延期未关闭")) -> 未回复 | AA20: =IF(W20="","",YEAR(W20)) | AB20: =IF(W20="","",TEXT(W20,"m")) | AC20: =IF(W20="","","W"&WEEKNUM(W20,2))
A21: 45547 | B21: =IF(A21="","",YEAR(A21)) -> 2024 | C21: =IF(A21="","",TEXT(A21,"m")) -> 9 | D21: =IF(A21="","","W"&WEEKNUM(A21,2)) -> W37 | E21: A124R021 | F21: 10W/50W | G21: 中国907 | H21: 宜胜照明3 | J21: 王燕赟 | K21: 王超 | L21: 测试防水IP65后老化1小时，发现灯体玻璃内出现可移动水珠 | M21: 客户验货 | N21: 内部 | O21: 灯体密封，内外温差形成水汽 | P21: 结构设计 | R21: 暂无解决方案 | Y21: =IF(A21="","",_xlfn.IFS(AND(W21=0,X21=0),"未回复",AND(X21<>0,W21=0),"报错",AND(W21>=NOW(),W21<>0,X21=0),"正常进行中",AND(X21<>0,W21>=X21),"按时关闭",AND(W21<>0,W21<=X21),"延期关闭",AND(X21=0,W21<NOW()),"延期未关闭")) -> 未回复 | AA21: =IF(W21="","",YEAR(W21)) | AB21: =IF(W21="","",TEXT(W21,"m")) | AC21: =IF(W21="","","W"&WEEKNUM(W21,2))
A22: 45547 | B22: =IF(A22="","",YEAR(A22)) -> 2024 | C22: =IF(A22="","",TEXT(A22,"m")) -> 9 | D22: =IF(A22="","","W"&WEEKNUM(A22,2)) -> W37 | E22: A124R021 | F22: 10W感应款 | G22: 中国907 | H22: 宜胜照明3 | J22: 王燕赟 | K22: 王超 | L22: 1PCS彩盒标贴漏贴 | M22: 客户验货 | N22: 包装 | O22: 员工漏贴 | P22: 人员作业 | Q22: 全检返工 | R22: 1.增加包装首件放置于包装线 2.生产前对标贴人员、外观人员进行培训 3.加强员工质量意识 | S22: 否 | T22: 人员培训 | U22: 宜胜照明3 | V22: 生产三 | W22: 45563 | X22: 45563 | Y22: =IF(A22="","",_xlfn.IFS(AND(W22=0,X22=0),"未回复",AND(X22<>0,W22=0),"报错",AND(W22>=NOW(),W22<>0,X22=0),"正常进行中",AND(X22<>0,W22>=X22),"按时关闭",AND(W22<>0,W22<=X22),"延期关闭",AND(X22=0,W22<NOW()),"延期未关闭")) -> 按时关闭 | AA22: =IF(W22="","",YEAR(W22)) -> 2024 | AB22: =IF(W22="","",TEXT(W22,"m")) -> 9 | AC22: =IF(W22="","","W"&WEEKNUM(W22,2)) -> W39
A23: 45558 | B23: =IF(A23="","",YEAR(A23)) -> 2024 | C23: =IF(A23="","",TEXT(A23,"m")) -> 9 | D23: =IF(A23="","","W"&WEEKNUM(A23,2)) -> W39 | E23: P24V002-1 | F23: LG172L-50W/100W | G23: 俄罗斯482 | H23: 宜胜照明3 | J23: 王燕赟 | L23: 防水不过50W、100W各1pcs | M23: 客户验货 | N23: 功能 | O23: 经拆灯发现为进线口打胶未打好 | P23: 人员作业 | R23: 产品个例 初步判定为自动线停止运行胶干 流动性达不到 重新运行后前几个产品胶水可能未打到位 整改措施为每天上班前胶水先放胶一分钟 确认无问题再开始生产 休息时间重新启动也同样检查胶水无问题开始生产 | S23: 否 | T23: 人员培训 | U23: 宜胜照明3 | V23: 生产三 | W23: 45563 | X23: 45563 | Y23: =IF(A23="","",_xlfn.IFS(AND(W23=0,X23=0),"未回复",AND(X23<>0,W23=0),"报错",AND(W23>=NOW(),W23<>0,X23=0),"正常进行中",AND(X23<>0,W23>=X23),"按时关闭",AND(W23<>0,W23<=X23),"延期关闭",AND(X23=0,W23<NOW()),"延期未关闭")) -> 按时关闭 | AA23: =IF(W23="","",YEAR(W23)) -> 2024 | AB23: =IF(W23="","",TEXT(W23,"m")) -> 9 | AC23: =IF(W23="","","W"&WEEKNUM(W23,2)) -> W39
A24: 45558 | B24: =IF(A24="","",YEAR(A24)) -> 2024 | C24: =IF(A24="","",TEXT(A24,"m")) -> 9 | D24: =IF(A24="","","W"&WEEKNUM(A24,2)) -> W39 | E24: P24V002-1 | F24: LG172L-30W/150W | G24: 俄罗斯482 | H24: 宜胜照明3 | J24: 王燕赟 | L24: 接地不通，30W1pcs，150W2pcs | M24: 客户验货 | N24: 安规 | O24: 螺丝松动，人员漏检 | P24: 人员作业 | R24: 1.工艺做测试设备点检SOP 2.对测试人员、班组长、IPQC进行安规标准、测试设备参数调整使用、注意事项进行培训，以及实操演练 3.IPQC人员按点检SOP以及点检记录项目对产线设备点检巡查监督 4.打接地螺丝岗位增加地线扭动动作防止螺丝未打紧 | S24: 否 | T24: 人员培训 | U24: 宜胜照明3 | V24: 生产三 | W24: 45563 | X24: 45563 | Y24: =IF(A24="","",_xlfn.IFS(AND(W24=0,X24=0),"未回复",AND(X24<>0,W24=0),"报错",AND(W24>=NOW(),W24<>0,X24=0),"正常进行中",AND(X24<>0,W24>=X24),"按时关闭",AND(W24<>0,W24<=X24),"延期关闭",AND(X24=0,W24<NOW()),"延期未关闭")) -> 按时关闭 | AA24: =IF(W24="","",YEAR(W24)) -> 2024 | AB24: =IF(W24="","",TEXT(W24,"m")) -> 9 | AC24: =IF(W24="","","W"&WEEKNUM(W24,2)) -> W39
A25: 45558 | B25: =IF(A25="","",YEAR(A25)) -> 2024 | C25: =IF(A25="","",TEXT(A25,"m")) -> 9 | D25: =IF(A25="","","W"&WEEKNUM(A25,2)) -> W39 | E25: P24V002-1 | F25: LG172L-30W | G25: 俄罗斯482 | H25: 宜胜照明3 | J25: 王燕赟 | L25: 漏打呼吸器 | M25: 客户验货 | N25: 内部 | O25: 人员漏打漏检 | P25: 人员作业 | R25: 1 呼吸器安排专人工序 加强培训 2 全检工序加强培训 工位拿到产品首先确认产品是否少料 再进行外观清洁 3 包装检验工序只做检验与清洁动作 增加套pe袋人员 | S25: 否 | T25: 人员培训 | U25: 宜胜照明3 | V25: 生产三 | W25: 45563 | X25: 45563 | Y25: =IF(A25="","",_xlfn.IFS(AND(W25=0,X25=0),"未回复",AND(X25<>0,W25=0),"报错",AND(W25>=NOW(),W25<>0,X25=0),"正常进行中",AND(X25<>0,W25>=X25),"按时关闭",AND(W25<>0,W25<=X25),"延期关闭",AND(X25=0,W25<NOW()),"延期未关闭")) -> 按时关闭 | AA25: =IF(W25="","",YEAR(W25)) -> 2024 | AB25: =IF(W25="","",TEXT(W25,"m")) -> 9 | AC25: =IF(W25="","","W"&WEEKNUM(W25,2)) -> W39
A26: 45558 | B26: =IF(A26="","",YEAR(A26)) -> 2024 | C26: =IF(A26="","",TEXT(A26,"m")) -> 9 | D26: =IF(A26="","","W"&WEEKNUM(A26,2)) -> W39 | E26: P24V002-1 | F26: LG172L-30W | G26: 俄罗斯482 | H26: 宜胜照明3 | J26: 王燕赟 | L26: 灯珠老化有小黑点 | M26: 客户验货 | N26: 功能 | O26: 焊接锡珠松香 | P26: 过程工艺 | R26: 组装生产 焊接工位增加盖板防止锡珠松香蹦到灯珠上 | S26: 否 | T26: 流程优化 | U26: 宜胜照明3 | V26: 生产三 | W26: 45563 | X26: 45563 | Y26: =IF(A26="","",_xlfn.IFS(AND(W26=0,X26=0),"未回复",AND(X26<>0,W26=0),"报错",AND(W26>=NOW(),W26<>0,X26=0),"正常进行中",AND(X26<>0,W26>=X26),"按时关闭",AND(W26<>0,W26<=X26),"延期关闭",AND(X26=0,W26<NOW()),"延期未关闭")) -> 按时关闭 | AA26: =IF(W26="","",YEAR(W26)) -> 2024 | AB26: =IF(W26="","",TEXT(W26,"m")) -> 9 | AC26: =IF(W26="","","W"&WEEKNUM(W26,2)) -> W39
A27: 45558 | B27: =IF(A27="","",YEAR(A27)) -> 2024 | C27: =IF(A27="","",TEXT(A27,"m")) -> 9 | D27: =IF(A27="","","W"&WEEKNUM(A27,2)) -> W39 | E27: P24V002-1 | F27: LG172L-200W | G27: 俄罗斯482 | H27: 宜胜照明3 | J27: 王燕赟 | L27: 反光罩起翘 | M27: 客户验货 | N27: 外观 | O27: 反光罩变形 | P27: 来料不良 | R27: 1.来料加强检验，关注物料变形情况， 2.生产发现不良异常及时反馈 3.外观人员及操作人员不良识别能力培训 | S27: 否 | T27: 供应商改善 | U27: 计划采购部 | V27: 供方管理组 | W27: 45563 | X27: 45563 | Y27: =IF(A27="","",_xlfn.IFS(AND(W27=0,X27=0),"未回复",AND(X27<>0,W27=0),"报错",AND(W27>=NOW(),W27<>0,X27=0),"正常进行中",AND(X27<>0,W27>=X27),"按时关闭",AND(W27<>0,W27<=X27),"延期关闭",AND(X27=0,W27<NOW()),"延期未关闭")) -> 按时关闭 | AA27: =IF(W27="","",YEAR(W27)) -> 2024 | AB27: =IF(W27="","",TEXT(W27,"m")) -> 9 | AC27: =IF(W27="","","W"&WEEKNUM(W27,2)) -> W39
A28: 45559 | B28: =IF(A28="","",YEAR(A28)) -> 2024 | C28: =IF(A28="","",TEXT(A28,"m")) -> 9 | D28: =IF(A28="","","W"&WEEKNUM(A28,2)) -> W39 | E28: M24A002 | F28: 黑色单插/智能插座 | G28: 巴西527 | H28: 宜胜照明1 | I28: 徐赢意 | J28: 赖长金 | K28: 丁亚双 | L28: 客验发现内部插划痕，熔接痕。检验80台，发现11台外观不良。 | M28: 客户验货 | N28: 外观 | O28: 1.划痕排查：经过将不良分析，发现内部划伤是，工人测试时对插导致。调整人员作业可杜绝此问题发生。 2.熔接痕：经过发现以及仓库物料排查，发现熔接痕是供应商在生产过程中造成的熔接痕，已经将此问题反馈供应商看能不能在调试参数是改善。 | P28: 人员作业 | Q28: 返工作业 | R28: 1、划痕不良发现，内部作业可避免，目前在生产订单已经调整作业流出，详情查看图片。 调整如图使视：原作业先安装塑料插座，在进行测试，导致测试过程中，造成插座出现划痕，更改成先测试在安装塑料件，防止塑料件测试过程中划痕。 | S28: 否 | T28: 工艺优化 | U28: 计划采购部 | V28: 供方管理组 | W28: 45560 | X28: 45560 | Y28: =IF(A28="","",_xlfn.IFS(AND(W28=0,X28=0),"未回复",AND(X28<>0,W28=0),"报错",AND(W28>=NOW(),W28<>0,X28=0),"正常进行中",AND(X28<>0,W28>=X28),"按时关闭",AND(W28<>0,W28<=X28),"延期关闭",AND(X28=0,W28<NOW()),"延期未关闭")) -> 按时关闭 | AA28: =IF(W28="","",YEAR(W28)) -> 2024 | AB28: =IF(W28="","",TEXT(W28,"m")) -> 9 | AC28: =IF(W28="","","W"&WEEKNUM(W28,2)) -> W39
A29: 45581 | B29: =IF(A29="","",YEAR(A29)) -> 2024 | C29: =IF(A29="","",TEXT(A29,"m")) -> 10 | D29: =IF(A29="","","W"&WEEKNUM(A29,2)) -> W42 | E29: Y24P0711 | F29: LG155C | G29: 澳大利亚020 | H29: 宜胜照明3 | I29: 邱玉雪 | J29: 王燕赟 | L29: 外观问题：所有有磕碰或者划痕的产品需重新上漆，以确保没有外观缺陷 | M29: 客户验货 | N29: 外观 | O29: 过程划伤 | P29: 人员作业 | Q29: 返工补漆 | R29: 1.现场物料不可叠堆摆放，人员宣导 2.IPQC、FQC每周质量稽核，对违规作业班组进行考核 | S29: 否 | T29: 人员培训 | U29: 宜胜照明3 | V29: 生产三 | W29: 45588 | X29: 45588 | Y29: =IF(A29="","",_xlfn.IFS(AND(W29=0,X29=0),"未回复",AND(X29<>0,W29=0),"报错",AND(W29>=NOW(),W29<>0,X29=0),"正常进行中",AND(X29<>0,W29>=X29),"按时关闭",AND(W29<>0,W29<=X29),"延期关闭",AND(X29=0,W29<NOW()),"延期未关闭")) -> 按时关闭 | AA29: =IF(W29="","",YEAR(W29)) -> 2024 | AB29: =IF(W29="","",TEXT(W29,"m")) -> 10 | AC29: =IF(W29="","","W"&WEEKNUM(W29,2)) -> W43
A30: 45581 | B30: =IF(A30="","",YEAR(A30)) -> 2024 | C30: =IF(A30="","",TEXT(A30,"m")) -> 10 | D30: =IF(A30="","","W"&WEEKNUM(A30,2)) -> W42 | E30: Y24P0711 | F30: LG155C | G30: 澳大利亚020 | H30: 宜胜照明3 | I30: 邱玉雪 | J30: 王燕赟 | L30: 进口线部分： 需在进口线部分打胶，确保达到60N的拉力测试要求 | M30: 客户验货 | N30: 安规 | O30: 拉力60N测试可通过（本批次有合格拉力测试报告，且厂验时拉力测试也通过了），验货时徒手可拉掉电源线，客户想进一步加固电源线 | P30: 其它 | Q30: 返工 | R30: 所有灯具有外漏电源线，增加拉力测试检验项目 | S30: 否 | T30: 流程优化 | U30: 其它事业部 | V30: 优耐特国贸 | W30: 45588 | X30: 45588 | Y30: =IF(A30="","",_xlfn.IFS(AND(W30=0,X30=0),"未回复",AND(X30<>0,W30=0),"报错",AND(W30>=NOW(),W30<>0,X30=0),"正常进行中",AND(X30<>0,W30>=X30),"按时关闭",AND(W30<>0,W30<=X30),"延期关闭",AND(X30=0,W30<NOW()),"延期未关闭")) -> 按时关闭 | AA30: =IF(W30="","",YEAR(W30)) -> 2024 | AB30: =IF(W30="","",TEXT(W30,"m")) -> 10 | AC30: =IF(W30="","","W"&WEEKNUM(W30,2)) -> W43
A31: 45601 | B31: =IF(A31="","",YEAR(A31)) -> 2024 | C31: =IF(A31="","",TEXT(A31,"m")) -> 11 | D31: =IF(A31="","","W"&WEEKNUM(A31,2)) -> W45 | E31: A124R021 | F31: LG172-50W | G31: 中国907 | H31: 宜胜照明3 | J31: 王燕赟 | K31: 王 超 | L31: 1、订单号A124R021 50W常规款PR340003-DW-EU，重验过程发现珍珠棉上漏贴回收标1pc，灯体脏污3pcs，掉漆4pcs，灯罩内有异物 2pcs，产品标贴起翘3pcs，灯体划痕1pc，彩盒破损1pc； 2、订单号A124R011 50W RGB款PR340013-RGB-EU-2，重验过程发现1盒漏装产品，5盒积灰，彩盒封口贴贴错位，11盒彩盒底部条形码偏位； | M31: 客户验货 | N31: 外观 | O31: 外观不良 | P31: 人员作业 | Q31: 返工全检 | S31: 否 | T31: 人员培训 | U31: 宜胜照明3 | V31: 生产三 | Y31: =IF(A31="","",_xlfn.IFS(AND(W31=0,X31=0),"未回复",AND(X31<>0,W31=0),"报错",AND(W31>=NOW(),W31<>0,X31=0),"正常进行中",AND(X31<>0,W31>=X31),"按时关闭",AND(W31<>0,W31<=X31),"延期关闭",AND(X31=0,W31<NOW()),"延期未关闭")) -> 未回复 | AA31: =IF(W31="","",YEAR(W31)) | AB31: =IF(W31="","",TEXT(W31,"m")) | AC31: =IF(W31="","","W"&WEEKNUM(W31,2))
A32: 45597 | B32: =IF(A32="","",YEAR(A32)) -> 2024 | C32: =IF(A32="","",TEXT(A32,"m")) -> 11 | D32: =IF(A32="","","W"&WEEKNUM(A32,2)) -> W44 | E32: A324C006 | F32: LC2A11L2-11W2-TD-GC2 | G32: 阿根廷098 | H32: 宜胜照明1 | I32: 余苏英 | K32: 鲁明明 | L32: 8450PCS,客验抽检120PCS,有7PCS 灯珠不亮， | M32: 客户验货 | N32: 功能 | O32: 功能不良 | P32: 人员作业 | Q32: 返工全检 | R32: 灯珠不亮的那批需要进行返工，返工完成后也需要抽10个进行老化 | S32: 否 | T32: 工艺优化 | U32: 宜胜照明1 | V32: 生产一 | W32: 45601 | X32: 45601 | Y32: =IF(A32="","",_xlfn.IFS(AND(W32=0,X32=0),"未回复",AND(X32<>0,W32=0),"报错",AND(W32>=NOW(),W32<>0,X32=0),"正常进行中",AND(X32<>0,W32>=X32),"按时关闭",AND(W32<>0,W32<=X32),"延期关闭",AND(X32=0,W32<NOW()),"延期未关闭")) -> 按时关闭 | AA32: =IF(W32="","",YEAR(W32)) -> 2024 | AB32: =IF(W32="","",TEXT(W32,"m")) -> 11 | AC32: =IF(W32="","","W"&WEEKNUM(W32,2)) -> W45
A33: 45611 | B33: =IF(A33="","",YEAR(A33)) -> 2024 | C33: =IF(A33="","",TEXT(A33,"m")) -> 11 | D33: =IF(A33="","","W"&WEEKNUM(A33,2)) -> W46 | E33: M24A002 | F33: TS 2002 PT | G33: 巴西527 | H33: 宜胜照明1 | I33: 徐赢意 | J33: 赖长金 | K33: 丁亚双 | L33: 客验时发现开关玻璃面有白点＋外观划痕 | M33: 客户验货 | N33: 外观 | O33: 外观不良 | P33: 人员作业 | Q33: 返工全检 | R33: 8D回复为准 | S33: 否 | T33: 人员培训 | U33: 宜胜照明1 | V33: 生产一 | W33: 45616 | X33: 45616 | Y33: =IF(A33="","",_xlfn.IFS(AND(W33=0,X33=0),"未回复",AND(X33<>0,W33=0),"报错",AND(W33>=NOW(),W33<>0,X33=0),"正常进行中",AND(X33<>0,W33>=X33),"按时关闭",AND(W33<>0,W33<=X33),"延期关闭",AND(X33=0,W33<NOW()),"延期未关闭")) -> 按时关闭 | AA33: =IF(W33="","",YEAR(W33)) -> 2024 | AB33: =IF(W33="","",TEXT(W33,"m")) -> 11 | AC33: =IF(W33="","","W"&WEEKNUM(W33,2)) -> W47
A34: 45575 | B34: =IF(A34="","",YEAR(A34)) -> 2024 | C34: =IF(A34="","",TEXT(A34,"m")) -> 10 | D34: =IF(A34="","","W"&WEEKNUM(A34,2)) -> W41 | E34: M24A002 | F34: 智能插座 | G34: 巴西527 | H34: 宜胜照明1 | I34: 徐赢意 | J34: 赖长金 | K34: 丁亚双 | L34: 1. 外观问题： 1.1.插座划伤，轻微*3。 1. 2.玻璃背部划伤*5。 1. 3.玻璃面板边缘破损*2 。 | M34: 客户验货 | N34: 外观 | O34: 外观不良 | P34: 人员作业 | Q34: 返工全检 | R34: 8D回复为准 | S34: 否 | T34: 人员培训 | U34: 宜胜照明1 | V34: 生产一 | W34: 45611 | X34: 45611 | Y34: =IF(A34="","",_xlfn.IFS(AND(W34=0,X34=0),"未回复",AND(X34<>0,W34=0),"报错",AND(W34>=NOW(),W34<>0,X34=0),"正常进行中",AND(X34<>0,W34>=X34),"按时关闭",AND(W34<>0,W34<=X34),"延期关闭",AND(X34=0,W34<NOW()),"延期未关闭")) -> 按时关闭 | AA34: =IF(W34="","",YEAR(W34)) -> 2024 | AB34: =IF(W34="","",TEXT(W34,"m")) -> 11 | AC34: =IF(W34="","","W"&WEEKNUM(W34,2)) -> W46
A35: 45636 | B35: =IF(A35="","",YEAR(A35)) -> 2024 | C35: =IF(A35="","",TEXT(A35,"m")) -> 12 | D35: =IF(A35="","","W"&WEEKNUM(A35,2)) -> W50 | E35: K24X024 | F35: 球泡 | G35: 德国147 | H35: 宜胜照明1 | I35: 赵婧 | L35: 客人验货发现1. 防割板，工厂放在底部了，应该在中盒标贴那一面，如附件图示。全部返工。 | M35: 客户验货 | N35: 包装 | O35: 包装资料明确防割板，做首件时未发现此问题，导致防割板放在底部。 | P35: 其它 | Q35: 返工处理 | S35: 否 | T35: 人员培训 | U35: 宜胜照明1 | V35: 生产一 | W35: 45637 | X35: 45637 | Y35: =IF(A35="","",_xlfn.IFS(AND(W35=0,X35=0),"未回复",AND(X35<>0,W35=0),"报错",AND(W35>=NOW(),W35<>0,X35=0),"正常进行中",AND(X35<>0,W35>=X35),"按时关闭",AND(W35<>0,W35<=X35),"延期关闭",AND(X35=0,W35<NOW()),"延期未关闭")) -> 按时关闭 | AA35: =IF(W35="","",YEAR(W35)) -> 2024 | AB35: =IF(W35="","",TEXT(W35,"m")) -> 12 | AC35: =IF(W35="","","W"&WEEKNUM(W35,2)) -> W50
A36: 45639 | B36: =IF(A36="","",YEAR(A36)) -> 2024 | C36: =IF(A36="","",TEXT(A36,"m")) -> 12 | D36: =IF(A36="","","W"&WEEKNUM(A36,2)) -> W50 | E36: Y24N0223 | F36: AL2005-9W筒灯 | G36: 澳大利亚1312 | H36: 宜胜照明2 | I36: 施晓刚 | L36: 说明书折叠不规范 | M36: 客户验货 | N36: 包装 | O36: 质量意识不足 | P36: 人员作业 | Q36: 返工 | S36: 否 | T36: 人员培训 | U36: 宜胜照明2 | V36: 生产二 | W36: 45642 | X36: 45642 | Y36: =IF(A36="","",_xlfn.IFS(AND(W36=0,X36=0),"未回复",AND(X36<>0,W36=0),"报错",AND(W36>=NOW(),W36<>0,X36=0),"正常进行中",AND(X36<>0,W36>=X36),"按时关闭",AND(W36<>0,W36<=X36),"延期关闭",AND(X36=0,W36<NOW()),"延期未关闭")) -> 按时关闭 | AA36: =IF(W36="","",YEAR(W36)) -> 2024 | AB36: =IF(W36="","",TEXT(W36,"m")) -> 12 | AC36: =IF(W36="","","W"&WEEKNUM(W36,2)) -> W51
A37: 45649 | B37: =IF(A37="","",YEAR(A37)) -> 2024 | C37: =IF(A37="","",TEXT(A37,"m")) -> 12 | D37: =IF(A37="","","W"&WEEKNUM(A37,2)) -> W52 | E37: A124R041 | F37: LG158C-50W | G37: 中国1674 | H37: 宜胜照明3 | J37: 王燕赟 | K37: 王超 | L37: 1、插头引脚变形（呈八字），不良率10%，需返工挑选； 2、玻璃划痕掉漆与异物2PCS，需返工挑选； 3、产品LED灯板方案与3年前订单不一致，LED灯珠由56PCS变成70PCS； 4、壳体凹陷1PCS； | M37: 客户验货 | N37: 外观 | O37: 外观不良，质量意识不足，包装未发现 插头变形为来料不良 | P37: 来料不良 | Q37: 返工 | S37: 否 | T37: 供应商改善 | U37: 计划采购部 | V37: 供方管理组 | W37: 45652 | X37: 45652 | Y37: =IF(A37="","",_xlfn.IFS(AND(W37=0,X37=0),"未回复",AND(X37<>0,W37=0),"报错",AND(W37>=NOW(),W37<>0,X37=0),"正常进行中",AND(X37<>0,W37>=X37),"按时关闭",AND(W37<>0,W37<=X37),"延期关闭",AND(X37=0,W37<NOW()),"延期未关闭")) -> 按时关闭 | AA37: =IF(W37="","",YEAR(W37)) -> 2024 | AB37: =IF(W37="","",TEXT(W37,"m")) -> 12 | AC37: =IF(W37="","","W"&WEEKNUM(W37,2)) -> W52
A38: 45652 | B38: =IF(A38="","",YEAR(A38)) -> 2024 | C38: =IF(A38="","",TEXT(A38,"m")) -> 12 | D38: =IF(A38="","","W"&WEEKNUM(A38,2)) -> W52 | E38: C24J1029-1 | F38: EL2520口袋灯 | G38: 美国1024 | H38: 宜胜照明2 | I38: 罗倩倩 | J38: 史睿 | L38: 电池标签纸工艺单要求双语版，实际为英语版 | M38: 客户验货 | N38: 内部 | O38: C24J1029-1订单口袋灯EL2520-G2，美国1024因销售地（加拿大和美国)不同，对电池标签有两种要求，分别为双语和英语版本，之前订单无电池特殊标签要求，电池标签为英语版本，本次订单添加新工艺单信息对电池标签做了另外要求（双语版本），业务未通知产品端对电池料号进行变更，电池沿用原返单料号；产品接收订单后未对工艺单要求进行核对确认，未能发现工艺单信息变更 | P38: 其它 | Q38: 返工 | R38: 变更新建电池料号，区分工艺单不同要求电池 | S38: 是 | T38: 设计变更-预防 | U38: 宜胜照明2 | V38: 研发九 | W38: 45652 | X38: 45652 | Y38: =IF(A38="","",_xlfn.IFS(AND(W38=0,X38=0),"未回复",AND(X38<>0,W38=0),"报错",AND(W38>=NOW(),W38<>0,X38=0),"正常进行中",AND(X38<>0,W38>=X38),"按时关闭",AND(W38<>0,W38<=X38),"延期关闭",AND(X38=0,W38<NOW()),"延期未关闭")) -> 按时关闭 | AA38: =IF(W38="","",YEAR(W38)) -> 2024 | AB38: =IF(W38="","",TEXT(W38,"m")) -> 12 | AC38: =IF(W38="","","W"&WEEKNUM(W38,2)) -> W52
A39: 45670 | B39: =IF(A39="","",YEAR(A39)) -> 2025 | C39: =IF(A39="","",TEXT(A39,"m")) -> 1 | D39: =IF(A39="","","W"&WEEKNUM(A39,2)) -> W3 | E39: P24V003-1 | F39: LG172L | G39: 俄罗斯482 | H39: 宜胜照明3 | J39: 王燕赟 | L39: 300W 一个进水 150W 灯板颜色不一致 | M39: 客户验货 | N39: 内部 | O39: 1.LG172L-300W进水，进水原因为胶未干导致进水，经查该款上线日期为2025/1/6,完工日期为2025/1/8，客验异常流程发起时间为2025/1/6,该型号产品为客验临时准备，因时间关系，胶未能完全凝固导致进水。 LG172L-150W灯板颜色不一致：经查该灯板铝基板（料号51080101497） 共有两家供应商，分别为信鸿和邦合美，工艺有所差异导致灯板颜色不一致 | P39: 其它 | Q39: 验货通过 | R39: 1.客验时间提前通知，保证生产周期，若有特殊情况，生产在准备产品时，也需要考虑硅胶的固化时间，以免影响测试结果； 2.同一订单使用同供应商同批次物料，若有异常及时反馈，确认后方可投入生产。 | S39: 否 | T39: 纠错 | U39: 宜胜照明3 | V39: 生产三 | W39: 45671 | X39: 45671 | Y39: =IF(A39="","",_xlfn.IFS(AND(W39=0,X39=0),"未回复",AND(X39<>0,W39=0),"报错",AND(W39>=NOW(),W39<>0,X39=0),"正常进行中",AND(X39<>0,W39>=X39),"按时关闭",AND(W39<>0,W39<=X39),"延期关闭",AND(X39=0,W39<NOW()),"延期未关闭")) -> 按时关闭 | AA39: =IF(W39="","",YEAR(W39)) -> 2025 | AB39: =IF(W39="","",TEXT(W39,"m")) -> 1 | AC39: =IF(W39="","","W"&WEEKNUM(W39,2)) -> W3
A40: 45706 | B40: =IF(A40="","",YEAR(A40)) -> 2025 | C40: =IF(A40="","",TEXT(A40,"m")) -> 2 | D40: =IF(A40="","","W"&WEEKNUM(A40,2)) -> W8 | E40: P24Z028 | F40: LB201WF5-5.5W-E-G5 | G40: 俄罗斯1661 | H40: 宜胜照明1 | K40: 刘晓慧 | L40: 1.丝印不良8只。8/90 不良率8.89% 2.功能测试只显示红、绿、黄三色，选择其他颜色不能切换，1只。1/18 不良率5.56% | M40: 客户验货 | N40: 功能 | O40: 原因：1.这款产品是三面打印，打印时灯头放到模具里旋转产品会有弧度不一样，导致部分丝印模糊 2.原因：灯珠裂痕，程序切换时蓝色灯珠不亮，蓝色缺失，导致测试时只显示红绿黄而其他颜色不能切换 | P40: 过程工艺 | Q40: 丝印不良本批次接收，功能问题返工全检测试 | R40: 改善措施：1.做这种E14产品三面打印的，灯杯打印好在上线 2.加强来料检验与供应商质量管控，保证灯珠来料质量及运输周转过程不会造成损伤； 3.生产过程及车间周转产品不允许叠堆摆放避免灯珠损坏；IPQC对生产过程工艺每日巡查，不良现象上报反馈，车间及时整改； 4.生产在测试检验过程要对灯珠的各功能颜色切换进行确认，避免不良品流出。 | S40: 否 | T40: 工艺优化 | U40: 宜胜照明1 | V40: 生产一 | W40: 45707 | X40: 45707 | Y40: =IF(A40="","",_xlfn.IFS(AND(W40=0,X40=0),"未回复",AND(X40<>0,W40=0),"报错",AND(W40>=NOW(),W40<>0,X40=0),"正常进行中",AND(X40<>0,W40>=X40),"按时关闭",AND(W40<>0,W40<=X40),"延期关闭",AND(X40=0,W40<NOW()),"延期未关闭")) -> 按时关闭 | AA40: =IF(W40="","",YEAR(W40)) -> 2025 | AB40: =IF(W40="","",TEXT(W40,"m")) -> 2 | AC40: =IF(W40="","","W"&WEEKNUM(W40,2)) -> W8
A41: 45713 | B41: =IF(A41="","",YEAR(A41)) -> 2025 | C41: =IF(A41="","",TEXT(A41,"m")) -> 2 | D41: =IF(A41="","","W"&WEEKNUM(A41,2)) -> W9 | E41: M24A002 | F41: ST-WS1002 9-2300W3- WFT-03-G1 | G41: 巴西527 | H41: 宜胜照明1 | I41: 徐赢意 | J41: 赖长金 | L41: M24A002 696.960 4850063 ETS 1001 PT 560pcs 2.24第三次重验，客验不合格。6pcs脏污问题，4pcs划痕问题，1pcs胶痕 | M41: 客户验货 | N41: 外观 | O41: 返工有撕膜检查，产线在撕膜检查用布沾水擦拭后留下的 | P41: 过程工艺 | Q41: 返工 | R41: 擦拭玻璃表面使用干净的无尘布，对全检人员培训玻璃擦拭干净后手不能碰到玻璃表面 | S41: 否 | T41: 人员培训 | U41: 宜胜照明1 | V41: 生产一 | W41: 45713 | X41: 45713 | Y41: =IF(A41="","",_xlfn.IFS(AND(W41=0,X41=0),"未回复",AND(X41<>0,W41=0),"报错",AND(W41>=NOW(),W41<>0,X41=0),"正常进行中",AND(X41<>0,W41>=X41),"按时关闭",AND(W41<>0,W41<=X41),"延期关闭",AND(X41=0,W41<NOW()),"延期未关闭")) -> 按时关闭 | AA41: =IF(W41="","",YEAR(W41)) -> 2025 | AB41: =IF(W41="","",TEXT(W41,"m")) -> 2 | AC41: =IF(W41="","","W"&WEEKNUM(W41,2)) -> W9
A42: 45714 | B42: =IF(A42="","",YEAR(A42)) -> 2025 | C42: =IF(A42="","",TEXT(A42,"m")) -> 2 | D42: =IF(A42="","","W"&WEEKNUM(A42,2)) -> W9 | E42: M24A008 | F42: ST-WS1002 9-2300W3- WFT-01-G1 | G42: 巴西527 | H42: 宜胜照明1 | I42: 徐赢意 | J42: 赖长金 | L42: 订单M24A008 ETS 2001 PT 一开单插黑色插座开关，1200PCS，抽样125pcs， 发现表面划伤9pcs，超出次要缺陷AQL允收标准。 | M42: 客户验货 | N42: 外观 | O42: 对不良样品检查分类，其中玻璃表面缺陷3pcs，插座表面缺陷6pcs： 1.玻璃表面划伤：一是原材料供应商供货质量不稳定，存在来料不良情况；二是生产过程中外观检验环节操作不规范不完善，员工撕膜检查缺乏标准操作指导，因操作不当造成划伤； 2.插座表面模具拉膜印痕：供应商模具维护不到位，生产过程中产生印痕，且我司对该类细微缺陷检验标准定义不明确、检验方法不全面，未能及时发现问题 | P42: 来料不良 | Q42: 车间针对此批产品安排全检返工，对有划痕部件进行更换。 | R42: 1.与原材料供应商重新商讨质量标准，明确玻璃及插座原材料外观缺陷的具体接收标准，按照客户封样检验。 2.生产重新制定外观检验操作的具体流程，明确撕膜检查的正确手法、力度及检验步骤，制作操作步骤指导及员工培训，确保员工熟练掌握操作规范 3.IPQC对外观检验环节进行不定时抽查，发现违规操作及时纠正并记录，纳入员工考核范围 4.要求对模具进行全面检查和维护，并定期进行维护和保养，我司在后续进货检验中加严检查，若有此问题拒绝接收。 | S42: 否 | T42: 供应商改善 | U42: 计划采购部 | V42: 供方管理组 | W42: 45713 | X42: 45713 | Y42: =IF(A42="","",_xlfn.IFS(AND(W42=0,X42=0),"未回复",AND(X42<>0,W42=0),"报错",AND(W42>=NOW(),W42<>0,X42=0),"正常进行中",AND(X42<>0,W42>=X42),"按时关闭",AND(W42<>0,W42<=X42),"延期关闭",AND(X42=0,W42<NOW()),"延期未关闭")) -> 按时关闭 | AA42: =IF(W42="","",YEAR(W42)) -> 2025 | AB42: =IF(W42="","",TEXT(W42,"m")) -> 2 | AC42: =IF(W42="","","W"&WEEKNUM(W42,2)) -> W9
A43: 45723 | B43: =IF(A43="","",YEAR(A43)) -> 2025 | C43: =IF(A43="","",TEXT(A43,"m")) -> 3 | D43: =IF(A43="","","W"&WEEKNUM(A43,2)) -> W10 | E43: P24Z028 | F43: LB201WF5-5.5W-E-G5 | G43: 俄罗斯1661 | H43: 宜胜照明1 | K43: 刘晓慧 | L43: 二次重验，灯头发黑，灯钉脱落 | M43: 客户验货 | N43: 外观 | O43: 该产品为返工产品，一次验货因功能问题进行点亮测试返工，推测原因为返工点亮测试过程员工操作不当，造成灯钉脱落、灯头烧黑、以及划伤现象。 | P43: 人员作业 | Q43: 返工 | R43: 1.针对返工产品，返工前需由工艺制定返工方案，PQE审核通过后由车间车间执行； 2.返工前由车间班组长对返工细节及注意事项，对员工进行培训，确保员工理解； 3.返工过程由IPQC对返工过程进行巡查管控，发现异常及时反馈纠正； 4.返工完成后需重新报检合格后方可入库出货； 5.针对返工二次报检产品，OQC检验需严格按AQL标准检验，除重点关注返工问题点，还需要注意返工过程造成其他外观异常或产品功能损坏等问题； 6.客验客诉不良，责任人及单位纳入月度考核。 | S43: 否 | T43: 人员培训 | U43: 宜胜照明1 | V43: 生产一 | W43: 45727 | X43: 45727 | Y43: =IF(A43="","",_xlfn.IFS(AND(W43=0,X43=0),"未回复",AND(X43<>0,W43=0),"报错",AND(W43>=NOW(),W43<>0,X43=0),"正常进行中",AND(X43<>0,W43>=X43),"按时关闭",AND(W43<>0,W43<=X43),"延期关闭",AND(X43=0,W43<NOW()),"延期未关闭")) -> 按时关闭 | AA43: =IF(W43="","",YEAR(W43)) -> 2025 | AB43: =IF(W43="","",TEXT(W43,"m")) -> 3 | AC43: =IF(W43="","","W"&WEEKNUM(W43,2)) -> W11
A44: 45729 | B44: =IF(A44="","",YEAR(A44)) -> 2025 | C44: =IF(A44="","",TEXT(A44,"m")) -> 3 | D44: =IF(A44="","","W"&WEEKNUM(A44,2)) -> W11 | E44: R24X1121-5 | F44: RL163-TJ-150W2-G1 | H44: 宜胜照明3 | J44: 余元浩 | L44: 橡胶电源线拉力不过,要求60N 25次，位移小于2mm | M44: 客户验货 | N44: 安规 | O44: 橡胶电源线与PVC材质注塑接头黏合性差 | P44: 来料不良 | Q44: 接头与线结合处打胶，50W已生产3804pcs，75W1900pcs | R44: 供应商改善，修模，橡胶线加粗，供应商改善结果不理想，生产还需要打胶处理 | S44: 否 | T44: 供应商改善 | U44: 计划采购部 | V44: 供方管理组 | W44: 45730 | X44: 45730 | Y44: =IF(A44="","",_xlfn.IFS(AND(W44=0,X44=0),"未回复",AND(X44<>0,W44=0),"报错",AND(W44>=NOW(),W44<>0,X44=0),"正常进行中",AND(X44<>0,W44>=X44),"按时关闭",AND(W44<>0,W44<=X44),"延期关闭",AND(X44=0,W44<NOW()),"延期未关闭")) -> 按时关闭 | AA44: =IF(W44="","",YEAR(W44)) -> 2025 | AB44: =IF(W44="","",TEXT(W44,"m")) -> 3 | AC44: =IF(W44="","","W"&WEEKNUM(W44,2)) -> W11
A45: 45729 | B45: =IF(A45="","",YEAR(A45)) -> 2025 | C45: =IF(A45="","",TEXT(A45,"m")) -> 3 | D45: =IF(A45="","","W"&WEEKNUM(A45,2)) -> W11 | E45: R24X1121-5 | F45: RL163-75W/100W/120W | H45: 宜胜照明3 | J45: 余元浩 | L45: 合同要求40/50抱环，BOM为50/60抱环，BOM挂错 | M45: 客户验货 | N45: 内部 | O45: BOM挂错 | P45: 结构设计 | Q45: 75W已包装返工更换附件包 | R45: 更改BOM | S45: 是 | T45: 设计变更-预防 | U45: 宜胜照明3 | V45: 研发一 | W45: 45730 | X45: 45730 | Y45: =IF(A45="","",_xlfn.IFS(AND(W45=0,X45=0),"未回复",AND(X45<>0,W45=0),"报错",AND(W45>=NOW(),W45<>0,X45=0),"正常进行中",AND(X45<>0,W45>=X45),"按时关闭",AND(W45<>0,W45<=X45),"延期关闭",AND(X45=0,W45<NOW()),"延期未关闭")) -> 按时关闭 | AA45: =IF(W45="","",YEAR(W45)) -> 2025 | AB45: =IF(W45="","",TEXT(W45,"m")) -> 3 | AC45: =IF(W45="","","W"&WEEKNUM(W45,2)) -> W11
A46: 45729 | B46: =IF(A46="","",YEAR(A46)) -> 2025 | C46: =IF(A46="","",TEXT(A46,"m")) -> 3 | D46: =IF(A46="","","W"&WEEKNUM(A46,2)) -> W11 | E46: Y24K039-1 | F46: LG189C-20W2-DPIR-G3_40K | G46: 英国927 | H46: 宜胜照明3 | J46: 王燕赟 | L46: 客验发现地线全部直接打在灯板螺孔，内部连接头处闭合端子脱落1pcs | M46: 客户验货 | N46: 安规 | O46: 壳体地线孔无螺纹，组长未反馈直接要求员工操作，闭合段子脱落为操作压合时，线头卷曲未压到线头 | P46: 人员作业 | Q46: 本批次验货通过 | R46: 人员培训，班组长考核 | S46: 否 | T46: 人员培训 | U46: 宜胜照明3 | V46: 生产三 | W46: 45730 | X46: 45730 | Y46: =IF(A46="","",_xlfn.IFS(AND(W46=0,X46=0),"未回复",AND(X46<>0,W46=0),"报错",AND(W46>=NOW(),W46<>0,X46=0),"正常进行中",AND(X46<>0,W46>=X46),"按时关闭",AND(W46<>0,W46<=X46),"延期关闭",AND(X46=0,W46<NOW()),"延期未关闭")) -> 按时关闭 | AA46: =IF(W46="","",YEAR(W46)) -> 2025 | AB46: =IF(W46="","",TEXT(W46,"m")) -> 3 | AC46: =IF(W46="","","W"&WEEKNUM(W46,2)) -> W11
A47: 45742 | B47: =IF(A47="","",YEAR(A47)) -> 2025 | C47: =IF(A47="","",TEXT(A47,"m")) -> 3 | D47: =IF(A47="","","W"&WEEKNUM(A47,2)) -> W13 | E47: P24R016 | F47: LR4512-15m/20m灯带 | G47: 俄罗斯482-3 | H47: 宜胜照明1 | J47: 刘子明 | K47: 刘晓慧 | L47: 多条缺色、一节不亮 | M47: 客户验货 | N47: 功能 | O47: 灯珠虚焊、灯带接头虚焊 | P47: 过程工艺 | Q47: 返工 | S47: 否 | T47: 流程优化 | U47: 宜胜照明1 | V47: 生产一 | W47: 45747 | X47: 45745 | Y47: =IF(A47="","",_xlfn.IFS(AND(W47=0,X47=0),"未回复",AND(X47<>0,W47=0),"报错",AND(W47>=NOW(),W47<>0,X47=0),"正常进行中",AND(X47<>0,W47>=X47),"按时关闭",AND(W47<>0,W47<=X47),"延期关闭",AND(X47=0,W47<NOW()),"延期未关闭")) -> 按时关闭 | AA47: =IF(W47="","",YEAR(W47)) -> 2025 | AB47: =IF(W47="","",TEXT(W47,"m")) -> 3 | AC47: =IF(W47="","","W"&WEEKNUM(W47,2)) -> W14
A48: 45742 | B48: =IF(A48="","",YEAR(A48)) -> 2025 | C48: =IF(A48="","",TEXT(A48,"m")) -> 3 | D48: =IF(A48="","","W"&WEEKNUM(A48,2)) -> W13 | E48: M24A002 | F48: ST-WS1002 9-2300W3- WFT-03-G1 | G48: 巴西527 | H48: 宜胜照明1 | I48: 徐赢意 | J48: 赖长金 | L48: 连接线脱落*1，脏污*6 | M48: 客户验货 | N48: 外观 | O48: 1.跌落测试后产品未检验直接包装 2.验货及返工撕膜检查时手指印及脏污污染 | P48: 人员作业 | Q48: 返工 | R48: 1.震动及跌落测试产品统一管理，全检合格后再进行包装 2.验货及返工产品更换表面覆膜 | S48: 否 | T48: 流程优化 | U48: 宜胜照明1 | V48: 生产一 | W48: 45744 | X48: 45744 | Y48: =IF(A48="","",_xlfn.IFS(AND(W48=0,X48=0),"未回复",AND(X48<>0,W48=0),"报错",AND(W48>=NOW(),W48<>0,X48=0),"正常进行中",AND(X48<>0,W48>=X48),"按时关闭",AND(W48<>0,W48<=X48),"延期关闭",AND(X48=0,W48<NOW()),"延期未关闭")) -> 按时关闭 | AA48: =IF(W48="","",YEAR(W48)) -> 2025 | AB48: =IF(W48="","",TEXT(W48,"m")) -> 3 | AC48: =IF(W48="","","W"&WEEKNUM(W48,2)) -> W13
A49: 45742 | B49: =IF(A49="","",YEAR(A49)) -> 2025 | C49: =IF(A49="","",TEXT(A49,"m")) -> 3 | D49: =IF(A49="","","W"&WEEKNUM(A49,2)) -> W13 | E49: M24A008 | F49: ST-WS1002 9-2300W3- WFT-01-G1 | G49: 巴西527 | H49: 宜胜照明1 | I49: 徐赢意 | J49: 赖长金 | L49: 脏污*6 | M49: 客户验货 | N49: 外观 | O49: 2.验货及返工撕膜检查时手指印及脏污污染 | P49: 人员作业 | Q49: 返工 | R49: 验货及返工产品更换表面覆膜 | S49: 否 | T49: 流程优化 | U49: 宜胜照明1 | V49: 生产一 | W49: 45744 | X49: 45744 | Y49: =IF(A49="","",_xlfn.IFS(AND(W49=0,X49=0),"未回复",AND(X49<>0,W49=0),"报错",AND(W49>=NOW(),W49<>0,X49=0),"正常进行中",AND(X49<>0,W49>=X49),"按时关闭",AND(W49<>0,W49<=X49),"延期关闭",AND(X49=0,W49<NOW()),"延期未关闭")) -> 按时关闭 | AA49: =IF(W49="","",YEAR(W49)) -> 2025 | AB49: =IF(W49="","",TEXT(W49,"m")) -> 3 | AC49: =IF(W49="","","W"&WEEKNUM(W49,2)) -> W13
A50: 45758 | B50: =IF(A50="","",YEAR(A50)) -> 2025 | C50: =IF(A50="","",TEXT(A50,"m")) -> 4 | D50: =IF(A50="","","W"&WEEKNUM(A50,2)) -> W15 | E50: M24A018 | F50: ST-WS7007 3-1800W3- WFT-G1 | G50: 巴西527 | H50: 宜胜照明1 | I50: 徐赢意 | J50: 赖长金 | K50: 施奉勇 | L50: 1.彩盒周期02.24与检查清单信息01.23不同 2.跌落测试后2pcs不亮 3.附件包螺钉尖头缺料4pcs | M50: 客户验货 | N50: 包装 | O50: 1.包装信息均以以业务提供工艺单信息为准，查彩盒工艺单信息为02.24，实际也为02.24,与工艺单信息一致。 2.包装设计缺陷，不能保证跌落测试一定合格 3.螺丝设计及供应商制程工艺不合理 | P50: 结构设计 | Q50: 附件包螺丝尖头缺料返工 | R50: 1.更改彩盒内衬 2.附件包尖头螺钉变更为平头 | S50: 是 | T50: 设计变更-预防 | U50: 宜胜照明1 | V50: 研发十 | W50: 45762 | X50: 45762 | Y50: =IF(A50="","",_xlfn.IFS(AND(W50=0,X50=0),"未回复",AND(X50<>0,W50=0),"报错",AND(W50>=NOW(),W50<>0,X50=0),"正常进行中",AND(X50<>0,W50>=X50),"按时关闭",AND(W50<>0,W50<=X50),"延期关闭",AND(X50=0,W50<NOW()),"延期未关闭")) -> 按时关闭 | AA50: =IF(W50="","",YEAR(W50)) -> 2025 | AB50: =IF(W50="","",TEXT(W50,"m")) -> 4 | AC50: =IF(W50="","","W"&WEEKNUM(W50,2)) -> W16
A51: 45763 | B51: =IF(A51="","",YEAR(A51)) -> 2025 | C51: =IF(A51="","",TEXT(A51,"m")) -> 4 | D51: =IF(A51="","","W"&WEEKNUM(A51,2)) -> W16 | E51: M24W027 | F51: LC2323IN- 10W3-G1 | G51: 巴西332 | H51: 宜胜照明1 | J51: 何海卿 | L51: 1.此款客验问题点电压220V/60HZ 功率偏低 （点亮2分钟直接掉到5.8W左右） 2.中盒箱数写错，下单总数为1020pcs，中盒（10pcs一中盒）应填写102，实际填写100 | M51: 客户验货 | N51: 功能 | O51: 1.电解电容接反 2.人员填写错误 | P51: 人员作业 | Q51: 返工 | R51: 1.电解电容正负极相关知识人员培训 2.班组长首件确认 3.测试点亮岗位必须确认功率 4.相关人员追责处理 5.包装箱数需核对包装清单 | S51: 否 | T51: 纠错 | U51: 宜胜照明1 | V51: 生产一 | W51: 45764 | X51: 45766 | Y51: =IF(A51="","",_xlfn.IFS(AND(W51=0,X51=0),"未回复",AND(X51<>0,W51=0),"报错",AND(W51>=NOW(),W51<>0,X51=0),"正常进行中",AND(X51<>0,W51>=X51),"按时关闭",AND(W51<>0,W51<=X51),"延期关闭",AND(X51=0,W51<NOW()),"延期未关闭")) -> 延期关闭 | AA51: =IF(W51="","",YEAR(W51)) -> 2025 | AB51: =IF(W51="","",TEXT(W51,"m")) -> 4 | AC51: =IF(W51="","","W"&WEEKNUM(W51,2)) -> W16
A52: 45763 | B52: =IF(A52="","",YEAR(A52)) -> 2025 | C52: =IF(A52="","",TEXT(A52,"m")) -> 4 | D52: =IF(A52="","","W"&WEEKNUM(A52,2)) -> W16 | E52: O25Y002-2 | F52: WL2106-10W-CCT-G1-黑色 | G52: 英国1063 | H52: 宜胜照明3 | I52: 李燕萍 | L52: 1.防水未过，玻璃处漏水 2.1PCS测试时死灯 | M52: 客户验货 | N52: 功能 | O52: 1.对防水不过产品拆机发现玻璃贴合密封胶有断胶现象，其气密性测试岗位充气时长与5W一致，因5W与10W其容量不同，10W充气时长以5W定制标准进行测试导致充气量不足，未能检测出断胶问题； 2.对点亮测试过程中死灯的产品拆机检查，灯板C1/C2位置贴片电容有虚焊现象，加锡补焊后功能恢复正常。在测试过程使用调光测试至最小检测是否有频闪死灯，可检测电容是否虚焊； | P52: 过程工艺 | Q52: 1.更改10W气密性测试充气时长标准，由原充气2秒更变为5秒，对气密性测试合格和不合格的分别进行防水测试，验证结果气密性测试合格的防水OK，气密性测试不合格的防水NG; 2.对该批次500PCS产品按5秒充气时长重新进行气密性测试； 3.该批次产品使用调光测试至最小检测是否有频闪死灯； 4.随机抽50PCS进行老化测试48小时，未发现异常 5.对已入库5W产品抽检两箱重新进行气密性测试，未发现异常。 | R52: 1.更改SOP100%进行气密性测试； 2.更改SOP，分别规定5W与10W气密性测试时长为3秒/5秒； 3.更改SOP,增加调光测试至最小检测是否有频闪死灯。 | S52: 否 | T52: 流程优化 | U52: 宜胜照明3 | V52: 生产三 | W52: 45766 | X52: 45766 | Y52: =IF(A52="","",_xlfn.IFS(AND(W52=0,X52=0),"未回复",AND(X52<>0,W52=0),"报错",AND(W52>=NOW(),W52<>0,X52=0),"正常进行中",AND(X52<>0,W52>=X52),"按时关闭",AND(W52<>0,W52<=X52),"延期关闭",AND(X52=0,W52<NOW()),"延期未关闭")) -> 按时关闭 | AA52: =IF(W52="","",YEAR(W52)) -> 2025 | AB52: =IF(W52="","",TEXT(W52,"m")) -> 4 | AC52: =IF(W52="","","W"&WEEKNUM(W52,2)) -> W16
A53: 45763 | B53: =IF(A53="","",YEAR(A53)) -> 2025 | C53: =IF(A53="","",TEXT(A53,"m")) -> 4 | D53: =IF(A53="","","W"&WEEKNUM(A53,2)) -> W16 | E53: A125S026 | F53: R182C路灯 | G53: 朗德万斯-香港 | H53: 宜胜照明3 | L53: 1、150W产品标贴丝印244颗灯珠，实际只有224颗，标贴错误100%； | M53: 客户验货 | N53: 包装 | O53: 工艺单标贴信息错误 | P53: 资料错误 | Q53: 更换标贴 | R53: 更改工艺单资料 | S53: 是 | T53: 标准升级 | U53: 宜胜照明3 | V53: 研发一 | W53: 45765 | X53: 45765 | Y53: =IF(A53="","",_xlfn.IFS(AND(W53=0,X53=0),"未回复",AND(X53<>0,W53=0),"报错",AND(W53>=NOW(),W53<>0,X53=0),"正常进行中",AND(X53<>0,W53>=X53),"按时关闭",AND(W53<>0,W53<=X53),"延期关闭",AND(X53=0,W53<NOW()),"延期未关闭")) -> 按时关闭 | AA53: =IF(W53="","",YEAR(W53)) -> 2025 | AB53: =IF(W53="","",TEXT(W53,"m")) -> 4 | AC53: =IF(W53="","","W"&WEEKNUM(W53,2)) -> W16
A54: 45787 | B54: =IF(A54="","",YEAR(A54)) -> 2025 | C54: =IF(A54="","",TEXT(A54,"m")) -> 5 | D54: =IF(A54="","","W"&WEEKNUM(A54,2)) -> W19 | E54: P24R016-3 | F54: LR4512灯带 | G54: 俄罗斯482 | H54: 宜胜照明1 | K54: 刘晓慧 | L54: 1.5m 1pc 4.5m均没有蓝光 2.10m 1pc只有5m 1pc电源电解未插好 （1pc 没有绿色、1pc 没有红 老化后又好了） 3.15m 1PC 没有蓝 4.25m 其中15m产品1pc 没有蓝 1pc电源断路 5.40m 1pc没有红绿 1pc没有蓝 | M54: 客户验货 | N54: 功能 | O54: 不亮原因：1.RGB脚假焊 2.RGB脚铜皮破损 3.电阻铜皮破损 具体原因分析： 1.RGB灯珠元件脚锡膏缺失 2.通过回流焊进行固化焊接时收卷机拉力不均 3.分板时RGB灯珠受外力撞击 4.测试段测试长度不足，有盲区 5.底部拍打测试力度不足 | P54: 过程工艺 | Q54: 返工 | R54: 1.锡膏印刷钢网孔径，椭圆形改为方形，确保锡膏爬锡充足 2.延长贴片机与回流焊之间接驳运输线距离，确保产品进入回流焊时与炉后收卷机保持匀速 3.现有手工分板改为设备侧压分板 4.延长维修测试线长度，线路板平摊表面测试，测试前后进行底部拍打。 | S54: 否 | T54: 工艺优化 | U54: 宜胜照明1 | V54: 生产一 | W54: 45790 | X54: 45790 | Y54: =IF(A54="","",_xlfn.IFS(AND(W54=0,X54=0),"未回复",AND(X54<>0,W54=0),"报错",AND(W54>=NOW(),W54<>0,X54=0),"正常进行中",AND(X54<>0,W54>=X54),"按时关闭",AND(W54<>0,W54<=X54),"延期关闭",AND(X54=0,W54<NOW()),"延期未关闭")) -> 按时关闭 | AA54: =IF(W54="","",YEAR(W54)) -> 2025 | AB54: =IF(W54="","",TEXT(W54,"m")) -> 5 | AC54: =IF(W54="","","W"&WEEKNUM(W54,2)) -> W20
A55: 45793 | B55: =IF(A55="","",YEAR(A55)) -> 2025 | C55: =IF(A55="","",TEXT(A55,"m")) -> 5 | D55: =IF(A55="","","W"&WEEKNUM(A55,2)) -> W20 | E55: A225J001 | F55: BL229C/BL230C | G55: 德国756 | H55: 宜胜照明3 | I55: 潘凌燕 | J55: 邵心妮 | L55: 1.主体两边收缩导致卡扣卡不紧 2.防水测试1pcs不过 3.打开后盖后硅胶圈粘在盖子上 抽检18 不良2pcs 4.彩盒鼓包（彩盒较薄+配件塞入后有点撑起来） | M55: 客户验货 | N55: 内部 | O55: 1.PP料灯体收缩，卡扣卡不紧，防水不过 2.密封圈接头处打胶未干及进行包装 3.附件包偏大 | P55: 结构设计 | Q55: 返工 | R55: 1.修改模具 2.更改工艺流程，工序前置 3.附件包改小 | S55: 否 | T55: 模具维修 | U55: 宜胜照明3 | V55: 研发二 | W55: 45793 | X55: 45793 | Y55: =IF(A55="","",_xlfn.IFS(AND(W55=0,X55=0),"未回复",AND(X55<>0,W55=0),"报错",AND(W55>=NOW(),W55<>0,X55=0),"正常进行中",AND(X55<>0,W55>=X55),"按时关闭",AND(W55<>0,W55<=X55),"延期关闭",AND(X55=0,W55<NOW()),"延期未关闭")) -> 按时关闭 | AA55: =IF(W55="","",YEAR(W55)) -> 2025 | AB55: =IF(W55="","",TEXT(W55,"m")) -> 5 | AC55: =IF(W55="","","W"&WEEKNUM(W55,2)) -> W20
A56: 45805 | B56: =IF(A56="","",YEAR(A56)) -> 2025 | C56: =IF(A56="","",TEXT(A56,"m")) -> 5 | D56: =IF(A56="","","W"&WEEKNUM(A56,2)) -> W22 | E56: M25A003 | F56: 4开墙壁开关 黑色 | G56: 巴西527 | H56: 宜胜照明1 | J56: 赖长金 | K56: 施奉勇 | L56: 彩盒鼓包 | M56: 客户验货 | N56: 包装 | O56: 因跌落测试不过更换彩盒内衬，内衬方案与彩盒不匹配,导致彩盒鼓包 | P56: 包装设计 | Q56: 返工（克服生产） | R56: 修改内衬方案 | S56: 是 | T56: 设计变更-预防 | U56: 宜胜照明1 | V56: 研发十 | W56: 45811 | X56: 45811 | Y56: =IF(A56="","",_xlfn.IFS(AND(W56=0,X56=0),"未回复",AND(X56<>0,W56=0),"报错",AND(W56>=NOW(),W56<>0,X56=0),"正常进行中",AND(X56<>0,W56>=X56),"按时关闭",AND(W56<>0,W56<=X56),"延期关闭",AND(X56=0,W56<NOW()),"延期未关闭")) -> 按时关闭 | AA56: =IF(W56="","",YEAR(W56)) -> 2025 | AB56: =IF(W56="","",TEXT(W56,"m")) -> 6 | AC56: =IF(W56="","","W"&WEEKNUM(W56,2)) -> W23
A57: 45812 | B57: =IF(A57="","",YEAR(A57)) -> 2025 | C57: =IF(A57="","",TEXT(A57,"m")) -> 6 | D57: =IF(A57="","","W"&WEEKNUM(A57,2)) -> W23 | E57: Y24K039-1 | F57: LG261C | G57: 英国927 | H57: 宜胜照明3 | L57: 感应接头松动 | M57: 客户验货 | N57: 内部 | O57: 1.感应器接头定位孔公差偏大 2.感应接头未拧紧 | P57: 结构设计 | Q57: 在感应接头螺纹上打胶201 | R57: 修改SOP，增加感应接头螺纹打胶工艺 | S57: 否 | T57: 工艺优化 | U57: 宜胜照明3 | V57: 生产三 | W57: 45815 | X57: 45815 | Y57: =IF(A57="","",_xlfn.IFS(AND(W57=0,X57=0),"未回复",AND(X57<>0,W57=0),"报错",AND(W57>=NOW(),W57<>0,X57=0),"正常进行中",AND(X57<>0,W57>=X57),"按时关闭",AND(W57<>0,W57<=X57),"延期关闭",AND(X57=0,W57<NOW()),"延期未关闭")) -> 按时关闭 | AA57: =IF(W57="","",YEAR(W57)) -> 2025 | AB57: =IF(W57="","",TEXT(W57,"m")) -> 6 | AC57: =IF(W57="","","W"&WEEKNUM(W57,2)) -> W23
A58: 45818 | B58: =IF(A58="","",YEAR(A58)) -> 2025 | C58: =IF(A58="","",TEXT(A58,"m")) -> 6 | D58: =IF(A58="","","W"&WEEKNUM(A58,2)) -> W24 | E58: A224D053 | F58: EL2520-1W7-G1 | G58: 荷兰146 | H58: 宜胜照明3 | J58: 史睿 | L58: 内部连接线与CDF不同 工作灯脏污 | M58: 客户验货 | N58: 内部 | O58: 1.实物正确，CDF证书资料错误，产品端向宁波沃特机构提供资料为28AWG线，宁波沃特机构在做证书时填写错误22AWG线，证书为客户所做，最后正本直接到客户手中，故在客户验货时与CDF核对才发现错误 2.打胶后未干直接进行包装，残胶污染 | P58: 过程工艺 | Q58: 1.机构更改客户证书 2.返工 | R58: 更改SOP，工作灯打胶后晾干再进行包装 | S58: 否 | T58: 工艺优化 | U58: 宜胜照明3 | V58: 生产三 | W58: 45818 | X58: 45818 | Y58: =IF(A58="","",_xlfn.IFS(AND(W58=0,X58=0),"未回复",AND(X58<>0,W58=0),"报错",AND(W58>=NOW(),W58<>0,X58=0),"正常进行中",AND(X58<>0,W58>=X58),"按时关闭",AND(W58<>0,W58<=X58),"延期关闭",AND(X58=0,W58<NOW()),"延期未关闭")) -> 按时关闭 | AA58: =IF(W58="","",YEAR(W58)) -> 2025 | AB58: =IF(W58="","",TEXT(W58,"m")) -> 6 | AC58: =IF(W58="","","W"&WEEKNUM(W58,2)) -> W24
A59: 45824 | B59: =IF(A59="","",YEAR(A59)) -> 2025 | C59: =IF(A59="","",TEXT(A59,"m")) -> 6 | D59: =IF(A59="","","W"&WEEKNUM(A59,2)) -> W25 | E59: M25A003 | F59: 4开墙壁开关 黑色 | G59: 巴西527 | H59: 宜胜照明1 | J59: 赖长金 | K59: 丁亚双 | L59: 客验抽检80pcs，彩盒鼓包7pcs，内衬破损23pcs | M59: 客户验货 | N59: 包装 | O59: 1.该型号开关为6月3日客验不合格产品，不合格项为彩盒鼓包，不良原因为内衬方案与彩盒不匹配，因客户急需发货返工措施为产线临时克服生产，故在二次返工过程未能完全避免彩盒鼓包现象； 2.内衬破损：该产品包装方式为开关先用塑料袋包装后再嵌入内衬进行彩盒包装， 内衬内尺寸偏小，产品套入塑料会有气泡产生，嵌入内衬过程导致内衬破损 | P59: 包装设计 | Q59: 1.对本批次产品彩盒鼓包产品进行挑选，对鼓包、变形、折痕的彩盒直接更换； 2.内衬破损的返工直接更换内衬 | R59: 变更彩盒内衬方案，增加内衬内尺寸，避免包装过程内衬内尺寸偏小受力导致破损。 | S59: 否 | T59: 设计变更-优化 | U59: 宜胜照明1 | V59: 研发十 | W59: 45824 | X59: 45824 | Y59: =IF(A59="","",_xlfn.IFS(AND(W59=0,X59=0),"未回复",AND(X59<>0,W59=0),"报错",AND(W59>=NOW(),W59<>0,X59=0),"正常进行中",AND(X59<>0,W59>=X59),"按时关闭",AND(W59<>0,W59<=X59),"延期关闭",AND(X59=0,W59<NOW()),"延期未关闭")) -> 按时关闭 | AA59: =IF(W59="","",YEAR(W59)) -> 2025 | AB59: =IF(W59="","",TEXT(W59,"m")) -> 6 | AC59: =IF(W59="","","W"&WEEKNUM(W59,2)) -> W25
A60: 45824 | B60: =IF(A60="","",YEAR(A60)) -> 2025 | C60: =IF(A60="","",TEXT(A60,"m")) -> 6 | D60: =IF(A60="","","W"&WEEKNUM(A60,2)) -> W25 | E60: M25A002 | F60: 6开墙壁开关 | G60: 巴西527 | H60: 宜胜照明1 | J60: 赖长金 | K60: 施奉勇 | L60: 订单M24A002订单EWS1006 PT，抽检80pcs，内衬破损43pcs，面板边缘破裂1pcs，跌落测试后1pcs指示灯不亮 | M60: 客户验货 | N60: 包装 | O60: 1.内衬破损：内衬的尺寸按照产品的尺寸来设计，设计过程中未考虑到塑料袋带来的尺寸影响，导致塞入时内衬受损 2.面板边缘破损：生产过程损伤，外观漏检 3.跌落测试1pcs指示灯不亮：经拆机发现为导光板贴歪，导致指示灯遮挡不亮 | P60: 包装设计 | Q60: 1.内衬破损的返工直接更换内衬，且返工过程塑料袋需排出空气，并轻轻放入内衬，避免受力过大导致内衬破损。 2.玻璃面板边缘破损，全检挑选 3.指示灯不亮：检查导光板是否贴歪和功能全检指示灯是否有不亮现象 | R60: 1.内衬破损：变更彩盒内衬方案，增加内衬内尺寸，由原70*88mm变更为71*89mm，避免包装过程内衬内尺寸偏小受力导致破损。 2.玻璃面板边缘破损：产线按SOP作业要求轻拿轻放 3.指示灯不亮：贴导光板方法及相关要求更新至SOP作业指导书，测试岗位测试方法及质量要求在SOP上进行明确 | S60: 否 | T60: 设计变更-优化 | U60: 宜胜照明1 | V60: 研发十 | W60: 45824 | X60: 45824 | Y60: =IF(A60="","",_xlfn.IFS(AND(W60=0,X60=0),"未回复",AND(X60<>0,W60=0),"报错",AND(W60>=NOW(),W60<>0,X60=0),"正常进行中",AND(X60<>0,W60>=X60),"按时关闭",AND(W60<>0,W60<=X60),"延期关闭",AND(X60=0,W60<NOW()),"延期未关闭")) -> 按时关闭 | AA60: =IF(W60="","",YEAR(W60)) -> 2025 | AB60: =IF(W60="","",TEXT(W60,"m")) -> 6 | AC60: =IF(W60="","","W"&WEEKNUM(W60,2)) -> W25
A61: 45827 | B61: =IF(A61="","",YEAR(A61)) -> 2025 | C61: =IF(A61="","",TEXT(A61,"m")) -> 6 | D61: =IF(A61="","","W"&WEEKNUM(A61,2)) -> W25 | E61: M25A005 | F61: ETS1001 PT | G61: 巴西527 | H61: 宜胜照明1 | J61: 赖长金 | K61: 丁亚双 | L61: 1. 附件包螺钉与清单不符 2. 1pcs产品标签与彩盒标签不符 3. 6PCS彩盒与产品不符，单开混用双开彩盒 | M61: 客户验货 | N61: 包装 | O61: 1.附件包螺钉与清单不符：经查附件包螺钉与BOM一致，客户检验清单未更新 2.1pcs产品标签与彩盒标签不符：产品有堆积导致2个产品之间装错彩盒 3.彩盒用错：换线未清理现场，上一款产品遗留彩盒混入其中 | P61: 人员作业 | Q61: 返工 | R61: 1.产品标签与彩盒标贴不符：节拍调整，产品与产品间保留距离10CM，产品与彩盒对应放置，装入彩盒前核对标签信息是否一致 2.彩盒用错：换线清理现场，需由班组长确认OK后，再上线下一款产品 | S61: 否 | T61: 流程优化 | U61: 宜胜照明1 | V61: 生产一 | W61: 45827 | X61: 45827 | Y61: =IF(A61="","",_xlfn.IFS(AND(W61=0,X61=0),"未回复",AND(X61<>0,W61=0),"报错",AND(W61>=NOW(),W61<>0,X61=0),"正常进行中",AND(X61<>0,W61>=X61),"按时关闭",AND(W61<>0,W61<=X61),"延期关闭",AND(X61=0,W61<NOW()),"延期未关闭")) -> 按时关闭 | AA61: =IF(W61="","",YEAR(W61)) -> 2025 | AB61: =IF(W61="","",TEXT(W61,"m")) -> 6 | AC61: =IF(W61="","","W"&WEEKNUM(W61,2)) -> W25
A62: 45836 | B62: =IF(A62="","",YEAR(A62)) -> 2025 | C62: =IF(A62="","",TEXT(A62,"m")) -> 6 | D62: =IF(A62="","","W"&WEEKNUM(A62,2)) -> W26 | E62: M24A012 | F62: ETS 2001 BR ETS 2002 BR | G62: 巴西527 | H62: 宜胜照明1 | J62: 赖长金 | K62: 丁亚双 | L62: 使用螺丝刀拆卸前面板时，玻璃会脱离（ETS 2001 BR拆卸2pcs，ETS 2002 BR拆卸3pcs均出现该情况） | M62: 客户验货 | N62: 内部 | O62: 玻璃面板与面盖粘合不牢固，为供应商修模后，模具上残留油污污染面盖，与胶水发生化学反应导致 | P62: 来料不良 | Q62: 返工 | R62: 供应商改善措施（右图）： 1.修模后对模具进行清洁，去除修模残留的金属碎霄、油污 2.修模后开机前300模标识“试模报废品”，不可流出使用； 3. IQC检验该供应商物料时要求供应商提供出厂检验报告和试模报废记录表。 | S62: 否 | T62: 供应商改善 | U62: 宜胜照明1 | V62: 生产一 | W62: 45843 | X62: 45843 | Y62: =IF(A62="","",_xlfn.IFS(AND(W62=0,X62=0),"未回复",AND(X62<>0,W62=0),"报错",AND(W62>=NOW(),W62<>0,X62=0),"正常进行中",AND(X62<>0,W62>=X62),"按时关闭",AND(W62<>0,W62<=X62),"延期关闭",AND(X62=0,W62<NOW()),"延期未关闭")) -> 按时关闭 | AA62: =IF(W62="","",YEAR(W62)) -> 2025 | AB62: =IF(W62="","",TEXT(W62,"m")) -> 7 | AC62: =IF(W62="","","W"&WEEKNUM(W62,2)) -> W27
A63: 45847 | B63: =IF(A63="","",YEAR(A63)) -> 2025 | C63: =IF(A63="","",TEXT(A63,"m")) -> 7 | D63: =IF(A63="","","W"&WEEKNUM(A63,2)) -> W28 | E63: A125S063-1 | F63: LB1101E1-9W2-G2-4000K | G63: 中国1796 | H63: 宜胜照明1 | K63: 王超 | L63: 客验发现1pcs死灯、响灯 | M63: 客户验货 | N63: 内部 | O63: 灯板在电子车间生产完成后，使用的是灯板缠绕泡泡袋侧放静电框的方式进行周转，周转过程电感受力断裂，电感铜线连接正常，自动线测试功能正产（电感脱落可识别），在包装及移库周转过程振动导致铜线连接完全脱落，导致死灯异响 | P63: 过程工艺 | Q63: 返工 | R63: 使用灯板分层专用周转架可有效避免周转过程元器件碰撞挤压 | S63: 否 | T63: 工艺优化 | U63: 宜胜照明1 | V63: 生产一 | W63: 45849 | X63: 45849 | Y63: =IF(A63="","",_xlfn.IFS(AND(W63=0,X63=0),"未回复",AND(X63<>0,W63=0),"报错",AND(W63>=NOW(),W63<>0,X63=0),"正常进行中",AND(X63<>0,W63>=X63),"按时关闭",AND(W63<>0,W63<=X63),"延期关闭",AND(X63=0,W63<NOW()),"延期未关闭")) -> 按时关闭 | AA63: =IF(W63="","",YEAR(W63)) -> 2025 | AB63: =IF(W63="","",TEXT(W63,"m")) -> 7 | AC63: =IF(W63="","","W"&WEEKNUM(W63,2)) -> W28
A64: 45849 | B64: =IF(A64="","",YEAR(A64)) -> 2025 | C64: =IF(A64="","",TEXT(A64,"m")) -> 7 | D64: =IF(A64="","","W"&WEEKNUM(A64,2)) -> W28 | E64: A125S063-1 | F64: GU10 7W 4000K | G64: 中国1796 | H64: 宜胜照明1 | K64: 王超 | L64: 客验发现1pcs彩盒混料GU5.3彩盒 | M64: 客户验货 | N64: 包装 | O64: GU10 产品混GU5.3彩盒1PCS，不同班组线体生产，且生产时间相差超过一星期，彩盒来料均为金瑞生产，应为来料混料 | P64: 来料不良 | Q64: 返工 | R64: 供应商打包前对彩盒全检 | S64: 否 | T64: 供应商改善 | U64: 计划采购部 | V64: 供方管理组 | W64: 45853 | X64: 45853 | Y64: =IF(A64="","",_xlfn.IFS(AND(W64=0,X64=0),"未回复",AND(X64<>0,W64=0),"报错",AND(W64>=NOW(),W64<>0,X64=0),"正常进行中",AND(X64<>0,W64>=X64),"按时关闭",AND(W64<>0,W64<=X64),"延期关闭",AND(X64=0,W64<NOW()),"延期未关闭")) -> 按时关闭 | AA64: =IF(W64="","",YEAR(W64)) -> 2025 | AB64: =IF(W64="","",TEXT(W64,"m")) -> 7 | AC64: =IF(W64="","","W"&WEEKNUM(W64,2)) -> W29
A65: 45862 | B65: =IF(A65="","",YEAR(A65)) -> 2025 | C65: =IF(A65="","",TEXT(A65,"m")) -> 7 | D65: =IF(A65="","","W"&WEEKNUM(A65,2)) -> W30 | E65: A125R022 | F65: LG162C-50W2-PIR | G65: 中国907 | H65: 宜胜照明3 | K65: 王超 | L65: 防水等级IP54,测试后发现1PCS感应器进水，2PCS为点亮后内部有雾气形成水珠 | M65: 客户验货 | N65: 安规 | O65: 感应器进水，为感应器转动接头位置密封圈未放到位，水雾为冷凝水 | P65: 来料不良 | Q65: 抽检10PCS泡水老化 | R65: / | S65: 否 | T65: 供应商改善 | U65: 计划采购部 | V65: 供方管理组 | W65: 45866 | X65: 45866 | Y65: =IF(A65="","",_xlfn.IFS(AND(W65=0,X65=0),"未回复",AND(X65<>0,W65=0),"报错",AND(W65>=NOW(),W65<>0,X65=0),"正常进行中",AND(X65<>0,W65>=X65),"按时关闭",AND(W65<>0,W65<=X65),"延期关闭",AND(X65=0,W65<NOW()),"延期未关闭")) -> 按时关闭 | AA65: =IF(W65="","",YEAR(W65)) -> 2025 | AB65: =IF(W65="","",TEXT(W65,"m")) -> 7 | AC65: =IF(W65="","","W"&WEEKNUM(W65,2)) -> W31
A66: 45891 | B66: =IF(A66="","",YEAR(A66)) -> 2025 | C66: =IF(A66="","",TEXT(A66,"m")) -> 8 | D66: =IF(A66="","","W"&WEEKNUM(A66,2)) -> W34 | E66: A125S060 | F66: LC2121W-5 W3-G1-6500K灯杯 | G66: 中国1796 | H66: 宜胜照明1 | I66: 史超 | K66: 王超 | L66: 1、A125S060客户型号85142灯杯，点亮80pcs发现2个灯杯不亮，1个功率偏低，不良率3.75% 2、A125S060客户型号85142灯杯，灯体丝印少印一个数字5，不良率100% | M66: 客户验货 | N66: 功能 | O66: 1.电源板输出端插针焊点脱落，波峰焊爬锡不足 2.功率低，灯珠死灯，印刷锡渣导致短路 3.电脑丝印模版调试错误 | P66: 过程工艺 | Q66: 返工测试点亮，补印丝印 | S66: 否 | T66: 流程优化 | U66: 宜胜照明1 | V66: 生产一 | W66: 45897 | X66: 45897 | Y66: =IF(A66="","",_xlfn.IFS(AND(W66=0,X66=0),"未回复",AND(X66<>0,W66=0),"报错",AND(W66>=NOW(),W66<>0,X66=0),"正常进行中",AND(X66<>0,W66>=X66),"按时关闭",AND(W66<>0,W66<=X66),"延期关闭",AND(X66=0,W66<NOW()),"延期未关闭")) -> 按时关闭 | AA66: =IF(W66="","",YEAR(W66)) -> 2025 | AB66: =IF(W66="","",TEXT(W66,"m")) -> 8 | AC66: =IF(W66="","","W"&WEEKNUM(W66,2)) -> W35
A67: 45891 | B67: =IF(A67="","",YEAR(A67)) -> 2025 | C67: =IF(A67="","",TEXT(A67,"m")) -> 8 | D67: =IF(A67="","","W"&WEEKNUM(A67,2)) -> W34 | E67: A125S123 | F67: T70-20W-6500K | G67: 中国1796 | H67: 宜胜照明1 | I67: 史超 | K67: 王超 | L67: A125S123客户型号91367T灯，测试5PCS扭矩，有3PCS扭矩不满足大于4N要求，不良率60% | M67: 客户验货 | N67: 其它 | O67: 设备异常，成品检验有发现，群里有反馈记录，车间无返工记录 | P67: 设备问题 | Q67: 让步接收 | R67: 更换钢针 | S67: 否 | T67: 设备维修 | U67: 宜胜照明1 | V67: 生产一 | W67: 45897 | X67: 45897 | Y67: =IF(A67="","",_xlfn.IFS(AND(W67=0,X67=0),"未回复",AND(X67<>0,W67=0),"报错",AND(W67>=NOW(),W67<>0,X67=0),"正常进行中",AND(X67<>0,W67>=X67),"按时关闭",AND(W67<>0,W67<=X67),"延期关闭",AND(X67=0,W67<NOW()),"延期未关闭")) -> 按时关闭 | AA67: =IF(W67="","",YEAR(W67)) -> 2025 | AB67: =IF(W67="","",TEXT(W67,"m")) -> 8 | AC67: =IF(W67="","","W"&WEEKNUM(W67,2)) -> W35
A68: 45901 | B68: =IF(A68="","",YEAR(A68)) -> 2025 | C68: =IF(A68="","",TEXT(A68,"m")) -> 9 | D68: =IF(A68="","","W"&WEEKNUM(A68,2)) -> W36 | E68: A225J004-1 | F68: LR471 10m灯带 | G68: 德国756 | H68: 宜胜照明1 | J68: 邢学文 | K68: 王超 | L68: 1、10米灯带表面有凹痕，不良率100%； 2、灯带内部有明显气泡，不良率100% 3、测试发现音乐律动模式下，感应失灵（初步分析元件焊接不良） | M68: 客户验货 | N68: 功能 | O68: 1.双面胶离型纸卷盘后褶皱造成滴胶表面有凹痕 2.胶水固化时元器件底部气体造成气泡产生 3.控制器贴装麦克风时，锡膏印刷不均匀导致浮高，元件接触器与线路板焊接不牢固造成失灵 | P68: 过程工艺 | Q68: 返工 | R68: 1.滴胶19g±1g降至17g±1g，放置过厚造成挤压 2.根据目前滴胶行业进行调研，制定滴胶产品气泡管理规范，每米气泡小于3个，单个气泡小于0.6mm,胶水固化后进行100%外观检验，如大于标准需进行修复作业 3.控制器电子贴片后进行100%测试，测试工装以设计完成(采购中，9月24日完成） | S68: 否 | T68: 工艺优化 | U68: 宜胜照明1 | V68: 生产一 | W68: 45924 | X68: 45924 | Y68: =IF(A68="","",_xlfn.IFS(AND(W68=0,X68=0),"未回复",AND(X68<>0,W68=0),"报错",AND(W68>=NOW(),W68<>0,X68=0),"正常进行中",AND(X68<>0,W68>=X68),"按时关闭",AND(W68<>0,W68<=X68),"延期关闭",AND(X68=0,W68<NOW()),"延期未关闭")) -> 按时关闭 | AA68: =IF(W68="","",YEAR(W68)) -> 2025 | AB68: =IF(W68="","",TEXT(W68,"m")) -> 9 | AC68: =IF(W68="","","W"&WEEKNUM(W68,2)) -> W39
A69: 45905 | B69: =IF(A69="","",YEAR(A69)) -> 2025 | C69: =IF(A69="","",TEXT(A69,"m")) -> 9 | D69: =IF(A69="","","W"&WEEKNUM(A69,2)) -> W36 | E69: A225D012 | F69: 3开墙壁开关 | G69: 阿根廷089 | H69: 宜胜照明1 | J69: 赖长金 | K69: 王超 | L69: 1pcs手机WIFF连接不上 | M69: 客户验货 | N69: 功能 | O69: 模块功能异常，电子工程师寄供应商分析中（bit位异常，一般为静电或异常上电导致） | P69: 来料不良 | Q69: 5款产品每款抽一箱连接手机WIFF测试 | R69: 1.ESD静电管控，上电按标准作业 2.质量稽核ESD静电防护，SOP作业手法 | S69: 否 | T69: 人员培训 | U69: 宜胜照明1 | V69: 生产一 | W69: 45909 | X69: 45909 | Y69: =IF(A69="","",_xlfn.IFS(AND(W69=0,X69=0),"未回复",AND(X69<>0,W69=0),"报错",AND(W69>=NOW(),W69<>0,X69=0),"正常进行中",AND(X69<>0,W69>=X69),"按时关闭",AND(W69<>0,W69<=X69),"延期关闭",AND(X69=0,W69<NOW()),"延期未关闭")) -> 按时关闭 | AA69: =IF(W69="","",YEAR(W69)) -> 2025 | AB69: =IF(W69="","",TEXT(W69,"m")) -> 9 | AC69: =IF(W69="","","W"&WEEKNUM(W69,2)) -> W37
A70: 45911 | B70: =IF(A70="","",YEAR(A70)) -> 2025 | C70: =IF(A70="","",TEXT(A70,"m")) -> 9 | D70: =IF(A70="","","W"&WEEKNUM(A70,2)) -> W37 | E70: M25A016-1 | F70: 4开墙壁开关 白色 | G70: 巴西527 | H70: 宜胜照明1 | J70: 赖长金 | K70: 丁亚双 | L70: 3000pcs客验抽检125pcs，每个产品至少有一个端子螺丝裂痕 | M70: 客户验货 | N70: 外观 | O70: 来料不良 | P70: 来料不良 | R70: 修订来料检验螺丝外观标准 | S70: 否 | T70: 供应商改善 | U70: 计划采购部 | V70: 供方管理组 | W70: 45916 | X70: 45916 | Y70: =IF(A70="","",_xlfn.IFS(AND(W70=0,X70=0),"未回复",AND(X70<>0,W70=0),"报错",AND(W70>=NOW(),W70<>0,X70=0),"正常进行中",AND(X70<>0,W70>=X70),"按时关闭",AND(W70<>0,W70<=X70),"延期关闭",AND(X70=0,W70<NOW()),"延期未关闭")) -> 按时关闭 | AA70: =IF(W70="","",YEAR(W70)) -> 2025 | AB70: =IF(W70="","",TEXT(W70,"m")) -> 9 | AC70: =IF(W70="","","W"&WEEKNUM(W70,2)) -> W38
A71: 45922 | B71: =IF(A71="","",YEAR(A71)) -> 2025 | C71: =IF(A71="","",TEXT(A71,"m")) -> 9 | D71: =IF(A71="","","W"&WEEKNUM(A71,2)) -> W39 | E71: A125S132+137 | F71: AC830720055/AC829740055 | G71: 中国1796 | H71: 宜胜照明3 | J71: 邵心妮 | K71: 王超 | L71: AC830720055/AC829740055:中盒有PE04标识，实际包装无PE袋；TDS中配件数与实际不符；功率偏高1PCS；标签功率因素＞0.9，实际产品＞0.8； | M71: 客户验货 | N71: 其它 | O71: 工艺单/TDS/CDF资料错误，IPC功率高为灯珠异常漏检流出 | P71: 资料错误 | Q71: 功率复测 | R71: 更改工艺单资料、TDS资料、CDF 资料 | S71: 否 | T71: 纠错 | U71: 宜胜照明3 | V71: 研发二 | W71: 45924 | X71: 45924 | Y71: =IF(A71="","",_xlfn.IFS(AND(W71=0,X71=0),"未回复",AND(X71<>0,W71=0),"报错",AND(W71>=NOW(),W71<>0,X71=0),"正常进行中",AND(X71<>0,W71>=X71),"按时关闭",AND(W71<>0,W71<=X71),"延期关闭",AND(X71=0,W71<NOW()),"延期未关闭")) -> 按时关闭 | AA71: =IF(W71="","",YEAR(W71)) -> 2025 | AB71: =IF(W71="","",TEXT(W71,"m")) -> 9 | AC71: =IF(W71="","","W"&WEEKNUM(W71,2)) -> W39
A72: 45922 | B72: =IF(A72="","",YEAR(A72)) -> 2025 | C72: =IF(A72="","",TEXT(A72,"m")) -> 9 | D72: =IF(A72="","","W"&WEEKNUM(A72,2)) -> W39 | E72: A225J006 | F72: LR481-E-15W-2D-44-10M | G72: 德国756 | H72: 宜胜照明3 | J72: 邢学文 | K72: 王超 | L72: 1、点亮了144pcs 在点亮过程发现一个控制器与灯带接触的地方接触不良 2、外观看了20pcs，发现1pcs有一处少胶 3、滴胶表面距离控制器2米处开始出现滴胶表面磨砂感，离尾部越近约明显 | M72: 客户验货 | N72: 功能 | O72: 1.灯带卷盘时控制器与灯带受外力影响导致断裂 2.线路板上型材后偏移导致滴胶流淌性不足，未覆盖完全，目检漏检 3.滴胶完成后立即卷盘导致内芯位置挤压型材倒影 | P72: 过程工艺 | Q72: 返工 | R72: 1.卷盘槽模式墙纸，减少卷盘时控制器的阻力，卷盘后进行直流，减少堆积 2.目检重点关注IC脚，收板岗位进行二次目检，上型材需进行100%检查 3.滴胶后静置60分钟以后进行卷盘，改造卷盘槽减少卷盘槽造成拉力导致卷盘过紧 | S72: 否 | T72: 工艺优化 | U72: 宜胜照明1 | V72: 生产一 | W72: 45928 | X72: 45928 | Y72: =IF(A72="","",_xlfn.IFS(AND(W72=0,X72=0),"未回复",AND(X72<>0,W72=0),"报错",AND(W72>=NOW(),W72<>0,X72=0),"正常进行中",AND(X72<>0,W72>=X72),"按时关闭",AND(W72<>0,W72<=X72),"延期关闭",AND(X72=0,W72<NOW()),"延期未关闭")) -> 按时关闭 | AA72: =IF(W72="","",YEAR(W72)) -> 2025 | AB72: =IF(W72="","",TEXT(W72,"m")) -> 9 | AC72: =IF(W72="","","W"&WEEKNUM(W72,2)) -> W39
A73: 45924 | B73: =IF(A73="","",YEAR(A73)) -> 2025 | C73: =IF(A73="","",TEXT(A73,"m")) -> 9 | D73: =IF(A73="","","W"&WEEKNUM(A73,2)) -> W39 | E73: A225J009 | F73: LR481-E-15W-2D-44-10M | G73: 德国756 | H73: 宜胜照明3 | J73: 邢学文 | K73: 王超 | L73: 1、PT7009435适配器用错4PCS，应用HS24J-240075-AG型号，实际用错成HS24J-240100-AG； 2、DE1024942测试发现1PCS点亮异常，初步分析铜箔断； 3、PO5752500447测试发现1PCS点亮异常，初步分析铜箔断； 4、适配器CDF表显示min24AWG，实际线径26AWG，与证书不一致； 5、遥控器板子颜色与认证不一致 | M73: 客户验货 | N73: 包装 | O73: 1.电源适配器剩余混料 2.FPC板子受外力断裂 3.资料错误 | P73: 人员作业 | Q73: 返工全检挑选 | R73: 卷盘1.物料标识，人员宣导培训；2.卷盘槽模式墙纸，减少卷盘时控制器的阻力 ，卷盘后进行直流，减少堆积 3.修改资料 | S73: 否 | T73: 人员培训 | U73: 宜胜照明1 | V73: 生产一 | W73: 45926 | X73: 45926 | Y73: =IF(A73="","",_xlfn.IFS(AND(W73=0,X73=0),"未回复",AND(X73<>0,W73=0),"报错",AND(W73>=NOW(),W73<>0,X73=0),"正常进行中",AND(X73<>0,W73>=X73),"按时关闭",AND(W73<>0,W73<=X73),"延期关闭",AND(X73=0,W73<NOW()),"延期未关闭")) -> 按时关闭 | AA73: =IF(W73="","",YEAR(W73)) -> 2025 | AB73: =IF(W73="","",TEXT(W73,"m")) -> 9 | AC73: =IF(W73="","","W"&WEEKNUM(W73,2)) -> W39
A74: 45924 | B74: =IF(A74="","",YEAR(A74)) -> 2025 | C74: =IF(A74="","",TEXT(A74,"m")) -> 9 | D74: =IF(A74="","","W"&WEEKNUM(A74,2)) -> W39 | E74: K25U035 | F74: HL230C-15W-4000K防潮灯 | G74: 德国1240 | H74: 宜胜照明3 | J74: 邵心妮 | L74: 防潮灯（椭圆）卡扣未到位 | M74: 客户验货 | N74: 外观 | O74: 设计异常 | P74: 结构设计 | R74: 修改模具 | S74: 否 | T74: 设计变更-优化 | U74: 宜胜照明3 | V74: 研发二 | W74: 45960 | Y74: =IF(A74="","",_xlfn.IFS(AND(W74=0,X74=0),"未回复",AND(X74<>0,W74=0),"报错",AND(W74>=NOW(),W74<>0,X74=0),"正常进行中",AND(X74<>0,W74>=X74),"按时关闭",AND(W74<>0,W74<=X74),"延期关闭",AND(X74=0,W74<NOW()),"延期未关闭")) -> 延期未关闭 | AA74: =IF(W74="","",YEAR(W74)) -> 2025 | AB74: =IF(W74="","",TEXT(W74,"m")) -> 10 | AC74: =IF(W74="","","W"&WEEKNUM(W74,2)) -> W44
A75: 45923 | B75: =IF(A75="","",YEAR(A75)) -> 2025 | C75: =IF(A75="","",TEXT(A75,"m")) -> 9 | D75: =IF(A75="","","W"&WEEKNUM(A75,2)) -> W39 | E75: M25N063 | F75: T70 30W 6500K | G75: 巴西332 | H75: 宜胜照明1 | I75: 叶锦楠 | K75: 丁亚双 | L75: 光通量偏低，标准2400±10%，下限2160，实测2130 | M75: 客户验货 | N75: 功能 | O75: 灯珠功能异常 | P75: 来料不良 | Q75: 让步接收 | R75: 灯珠变更 | S75: 否 | U75: 宜胜照明1 | V75: 研发六 | W75: 45945 | X75: 45945 | Y75: =IF(A75="","",_xlfn.IFS(AND(W75=0,X75=0),"未回复",AND(X75<>0,W75=0),"报错",AND(W75>=NOW(),W75<>0,X75=0),"正常进行中",AND(X75<>0,W75>=X75),"按时关闭",AND(W75<>0,W75<=X75),"延期关闭",AND(X75=0,W75<NOW()),"延期未关闭")) -> 按时关闭 | AA75: =IF(W75="","",YEAR(W75)) -> 2025 | AB75: =IF(W75="","",TEXT(W75,"m")) -> 10 | AC75: =IF(W75="","","W"&WEEKNUM(W75,2)) -> W42
A76: 45925 | B76: =IF(A76="","",YEAR(A76)) -> 2025 | C76: =IF(A76="","",TEXT(A76,"m")) -> 9 | D76: =IF(A76="","","W"&WEEKNUM(A76,2)) -> W39 | E76: M25N066 | F76: GU10 FCOB 7W 4000K | G76: 巴西332 | H76: 宜胜照明1 | I76: 叶锦楠 | K76: 丁亚双 | L76: 死灯2pcs，端子虚焊（少锡）脱落 | M76: 客户验货 | N76: 功能 | O76: 端子虚焊（少锡）脱落 | P76: 过程工艺 | Q76: 返工全检测试 | R76: 1.炉温监控（每天炉温曲线记录）地址发夏琛 2.焊锡饱满度（人工目检） 3.焊接推力测试 4.板子必须使用分层静电周转筐 | S76: 否 | T76: 纠错 | U76: 宜胜照明1 | V76: 生产一 | W76: 45926 | X76: 45926 | Y76: =IF(A76="","",_xlfn.IFS(AND(W76=0,X76=0),"未回复",AND(X76<>0,W76=0),"报错",AND(W76>=NOW(),W76<>0,X76=0),"正常进行中",AND(X76<>0,W76>=X76),"按时关闭",AND(W76<>0,W76<=X76),"延期关闭",AND(X76=0,W76<NOW()),"延期未关闭")) -> 按时关闭 | AA76: =IF(W76="","",YEAR(W76)) -> 2025 | AB76: =IF(W76="","",TEXT(W76,"m")) -> 9 | AC76: =IF(W76="","","W"&WEEKNUM(W76,2)) -> W39
A77: 45943 | B77: =IF(A77="","",YEAR(A77)) -> 2025 | C77: =IF(A77="","",TEXT(A77,"m")) -> 10 | D77: =IF(A77="","","W"&WEEKNUM(A77,2)) -> W42 | E77: M25N067-2 M25N067-3 | F77: LTC1623IN-20WX3-G1H-Q_PT4523D_6500K | G77: 巴西332 | H77: 宜胜照明1 | I77: 叶锦楠 | K77: 丁亚双 | L77: 20W泡壳易脱落 | M77: 客户验货 | N77: 内部 | O77: 胶量偏少，扭力1.8N不合格：1.设备等离子没有全部把灯罩吹到，2.治具磨损太松 | P77: 过程工艺 | Q77: 返工 | R77: 更改治具，1小时监测等离子效果 | S77: 否 | T77: 工艺优化 | U77: 宜胜照明1 | V77: 生产一 | W77: 45953 | X77: 45953 | Y77: =IF(A77="","",_xlfn.IFS(AND(W77=0,X77=0),"未回复",AND(X77<>0,W77=0),"报错",AND(W77>=NOW(),W77<>0,X77=0),"正常进行中",AND(X77<>0,W77>=X77),"按时关闭",AND(W77<>0,W77<=X77),"延期关闭",AND(X77=0,W77<NOW()),"延期未关闭")) -> 按时关闭 | AA77: =IF(W77="","",YEAR(W77)) -> 2025 | AB77: =IF(W77="","",TEXT(W77,"m")) -> 10 | AC77: =IF(W77="","","W"&WEEKNUM(W77,2)) -> W43
A78: 45950 | B78: =IF(A78="","",YEAR(A78)) -> 2025 | C78: =IF(A78="","",TEXT(A78,"m")) -> 10 | D78: =IF(A78="","","W"&WEEKNUM(A78,2)) -> W43 | E78: A225J011 | F78: LR481-E-15W-2D-44-10M | G78: 德国756 | H78: 宜胜照明1 | K78: 王超 | L78: 1.灯带中间一节不亮1PCS 2.连接器未组装完成1PCS | M78: 客户验货 | N78: 功能 | O78: 根因分析：卷盘时速度过快拉扯，与卷盘槽发生摩擦和碰撞导致灯带断裂现象。流出原因分析：员工漏装，漏检。 | P78: 过程工艺 | Q78: 1、卷盘槽增加墙纸减少摩擦 2、卷盘速度降低到20 3.《质量意识培训》 《不良和现场培训》 | R78: 1.SOP变更：卷盘速度由40-50变更为18-22 2.SOP增加要求：在测试时停留3-5秒观察灯带是否有未亮现象，有则挑出。 3.SOP要求员工自检，并要求下工序检查上工序 | S78: 否 | T78: 工艺优化 | U78: 宜胜照明1 | V78: 生产一 | W78: 45954 | X78: 45954 | Y78: =IF(A78="","",_xlfn.IFS(AND(W78=0,X78=0),"未回复",AND(X78<>0,W78=0),"报错",AND(W78>=NOW(),W78<>0,X78=0),"正常进行中",AND(X78<>0,W78>=X78),"按时关闭",AND(W78<>0,W78<=X78),"延期关闭",AND(X78=0,W78<NOW()),"延期未关闭")) -> 按时关闭 | AA78: =IF(W78="","",YEAR(W78)) -> 2025 | AB78: =IF(W78="","",TEXT(W78,"m")) -> 10 | AC78: =IF(W78="","","W"&WEEKNUM(W78,2)) -> W43
A79: 45960 | B79: =IF(A79="","",YEAR(A79)) -> 2025 | C79: =IF(A79="","",TEXT(A79,"m")) -> 10 | D79: =IF(A79="","","W"&WEEKNUM(A79,2)) -> W44 | E79: W25D077英国 | F79: EL027挂脖灯 | G79: 德国1502—英国GB-1 | H79: 宜胜照明3 | I79: 王樱 | L79: 灯杆脱落 | M79: 客户验货 | N79: 内部 | O79: 胶未打好，未完全覆盖 | P79: 人员作业 | Q79: 返工 | R79: 作业标准及人员技能培训 | S79: 否 | T79: 人员培训 | U79: 宜胜照明3 | V79: 生产三 | W79: 45961 | X79: 45961 | Y79: =IF(A79="","",_xlfn.IFS(AND(W79=0,X79=0),"未回复",AND(X79<>0,W79=0),"报错",AND(W79>=NOW(),W79<>0,X79=0),"正常进行中",AND(X79<>0,W79>=X79),"按时关闭",AND(W79<>0,W79<=X79),"延期关闭",AND(X79=0,W79<NOW()),"延期未关闭")) -> 按时关闭 | AA79: =IF(W79="","",YEAR(W79)) -> 2025 | AB79: =IF(W79="","",TEXT(W79,"m")) -> 10 | AC79: =IF(W79="","","W"&WEEKNUM(W79,2)) -> W44
A80: 45965 | B80: =IF(A80="","",YEAR(A80)) -> 2025 | C80: =IF(A80="","",TEXT(A80,"m")) -> 11 | D80: =IF(A80="","","W"&WEEKNUM(A80,2)) -> W45 | E80: A225J017 A225J018 | F80: LR481-E-10.5W | G80: 德国756 | H80: 宜胜照明1 | J80: 邢学文 | K80: 王超 | L80: A225J017遥控器用错4PCS（标贴） A225J018灯带1.5米彩盒用错4PCS | M80: 客户验货 | N80: 包装 | O80: 清尾人员未进行核对 | P80: 人员作业 | Q80: 特采接收（不良更换） | R80: 1.尾数严格按照生产尾数管理办法规定执行 2.对员工进行《生产尾数管理办法规定》培训 3.生产物料开线前需由专人（班组长、物料员）领取，由IPQC巡检确认后方可流转到对应工位使用并填写尾数记录表 | S80: 否 | T80: 人员培训 | U80: 宜胜照明3 | V80: 生产三 | W80: 45969 | X80: 45969 | Y80: =IF(A80="","",_xlfn.IFS(AND(W80=0,X80=0),"未回复",AND(X80<>0,W80=0),"报错",AND(W80>=NOW(),W80<>0,X80=0),"正常进行中",AND(X80<>0,W80>=X80),"按时关闭",AND(W80<>0,W80<=X80),"延期关闭",AND(X80=0,W80<NOW()),"延期未关闭")) -> 按时关闭 | AA80: =IF(W80="","",YEAR(W80)) -> 2025 | AB80: =IF(W80="","",TEXT(W80,"m")) -> 11 | AC80: =IF(W80="","","W"&WEEKNUM(W80,2)) -> W45
A81: 45981 | B81: =IF(A81="","",YEAR(A81)) -> 2025 | C81: =IF(A81="","",TEXT(A81,"m")) -> 11 | D81: =IF(A81="","","W"&WEEKNUM(A81,2)) -> W47 | E81: M25A016-1 | F81: ETS 2002 | G81: 巴西527 | H81: 宜胜照明1 | I81: 徐赢意 | K81: 丁亚双 | L81: 玻璃面板与中框分层起翘 | M81: 客户验货 | N81: 内部 | O81: 贴合面玻璃保护膜残留 | P81: 人员作业 | Q81: 撬玻璃+外观全检 | R81: SOP增加不良图片，贴合前增加目检要求 | S81: 否 | T81: 工艺优化 | U81: 宜胜照明1 | V81: 生产一 | W81: 45981 | X81: 45981 | Y81: =IF(A81="","",_xlfn.IFS(AND(W81=0,X81=0),"未回复",AND(X81<>0,W81=0),"报错",AND(W81>=NOW(),W81<>0,X81=0),"正常进行中",AND(X81<>0,W81>=X81),"按时关闭",AND(W81<>0,W81<=X81),"延期关闭",AND(X81=0,W81<NOW()),"延期未关闭")) -> 按时关闭 | AA81: =IF(W81="","",YEAR(W81)) -> 2025 | AB81: =IF(W81="","",TEXT(W81,"m")) -> 11 | AC81: =IF(W81="","","W"&WEEKNUM(W81,2)) -> W47
A82: 45982 | B82: =IF(A82="","",YEAR(A82)) -> 2025 | C82: =IF(A82="","",TEXT(A82,"m")) -> 11 | D82: =IF(A82="","","W"&WEEKNUM(A82,2)) -> W47 | E82: M25N076-1 （属于订单 M25N076-3） | F82: T70 30W 6500K | G82: 巴西332 | H82: 宜胜照明1 | I82: 叶锦楠 | K82: 丁亚双 | L82: 彩盒开裂，订单数量45000pcs，不良比例21%（彩盒料号70020105025） | M82: 客户验货 | N82: 包装 | O82: 来料检验日期11/11（该订单其他批次未发现该异常，为万兴供应商）本批次为金瑞供应商 | P82: 来料不良 | Q82: 让步接收 | R82: 来料检验人员宣导 | S82: 否 | T82: 供应商改善 | U82: 计划采购部 | V82: 供方管理组 | W82: 45992 | X82: 45992 | Y82: =IF(A82="","",_xlfn.IFS(AND(W82=0,X82=0),"未回复",AND(X82<>0,W82=0),"报错",AND(W82>=NOW(),W82<>0,X82=0),"正常进行中",AND(X82<>0,W82>=X82),"按时关闭",AND(W82<>0,W82<=X82),"延期关闭",AND(X82=0,W82<NOW()),"延期未关闭")) -> 按时关闭 | AA82: =IF(W82="","",YEAR(W82)) -> 2025 | AB82: =IF(W82="","",TEXT(W82,"m")) -> 12 | AC82: =IF(W82="","","W"&WEEKNUM(W82,2)) -> W49
A83: 45994 | B83: =IF(A83="","",YEAR(A83)) -> 2025 | C83: =IF(A83="","",TEXT(A83,"m")) -> 12 | D83: =IF(A83="","","W"&WEEKNUM(A83,2)) -> W49 | E83: A125S195+S196+198+199 | F83: LG175C-150W2-G6 | G83: 中国1796-木林森 | H83: 宜胜照明3 | K83: 王超 | L83: 木林森客户在我司验货过程发现LG175C-150W2-G6投光灯的玻璃有较透明现象，抽检20PCS发现2PCS | M83: 客户验货 | N83: 外观 | O83: 玻璃表面布纹来料透光不一致 | P83: 来料不良 | Q83: 返工全检 | R83: 1.与供应商明确一致性要求，玻璃来料检验SIP透明度项增加“纹理透明度一致性”检查 2.SOP增加技术要求：检查玻璃表面纹理透明度一致，新增不良图片 | S83: 否 | T83: 供应商改善 | U83: 计划采购部 | V83: 供方管理组 | W83: 45997 | X83: 45997 | Y83: =IF(A83="","",_xlfn.IFS(AND(W83=0,X83=0),"未回复",AND(X83<>0,W83=0),"报错",AND(W83>=NOW(),W83<>0,X83=0),"正常进行中",AND(X83<>0,W83>=X83),"按时关闭",AND(W83<>0,W83<=X83),"延期关闭",AND(X83=0,W83<NOW()),"延期未关闭")) -> 按时关闭 | AA83: =IF(W83="","",YEAR(W83)) -> 2025 | AB83: =IF(W83="","",TEXT(W83,"m")) -> 12 | AC83: =IF(W83="","","W"&WEEKNUM(W83,2)) -> W49
A84: 45994 | B84: =IF(A84="","",YEAR(A84)) -> 2025 | C84: =IF(A84="","",TEXT(A84,"m")) -> 12 | D84: =IF(A84="","","W"&WEEKNUM(A84,2)) -> W49 | E84: A225Z026-Z029 | F84: DEB1001C-5W3-RGB-G5氛围灯 | G84: 德国756 | H84: 宜胜照明3 | I84: 周春艳 | K84: 贾世东 | L84: 1.A225Z028彩盒包错1PCS 2.A225Z028外箱破损严重1PCS 3.A225Z027外箱型号包错用牛皮纸覆盖1PCS 4.A225Z028电池与底板未粘贴双面胶2PCS 5.A225Z029杆子螺纹柱脱离2pcs | M84: 客户验货 | N84: 包装 | O84: 1.新进员工，作业不熟练，疏忽大意用错 2.周转过程划破 3.该外箱产品多包装一箱，与原箱不匹配，牛皮纸覆盖原信息 4.新进员工，作业不熟练，漏贴 5.胶水用量不足 | P84: 人员作业 | Q84: 库存吉生产现场排查，未发现异常 更换不良产品或包装 | R84: 1.新员工培训合格后上岗，每月定期培训相关质量标准、要求 2.工艺优化，混包产品，两条线物料分区域放置（物理隔断，避免拿错用错） 3.规范胶水用量及打胶具体作业标准 | S84: 否 | T84: 工艺优化 | U84: 宜胜照明3 | V84: 生产三 | W84: 45997 | X84: 45997 | Y84: =IF(A84="","",_xlfn.IFS(AND(W84=0,X84=0),"未回复",AND(X84<>0,W84=0),"报错",AND(W84>=NOW(),W84<>0,X84=0),"正常进行中",AND(X84<>0,W84>=X84),"按时关闭",AND(W84<>0,W84<=X84),"延期关闭",AND(X84=0,W84<NOW()),"延期未关闭")) -> 按时关闭 | AA84: =IF(W84="","",YEAR(W84)) -> 2025 | AB84: =IF(W84="","",TEXT(W84,"m")) -> 12 | AC84: =IF(W84="","","W"&WEEKNUM(W84,2)) -> W49
A85: 46030 | B85: =IF(A85="","",YEAR(A85)) -> 2026 | C85: =IF(A85="","",TEXT(A85,"m")) -> 1 | D85: =IF(A85="","","W"&WEEKNUM(A85,2)) -> W2 | E85: P25V006-1-1 | F85: 花园灯GL047/048 | G85: 俄罗斯482-3 | H85: 宜胜照明3 | K85: 刘晓慧 | L85: 灯头易掉落 | M85: 客户验货 | N85: 内部 | O85: 其中两款打胶，其余产品端确认不打胶 | P85: 其它 | Q85: 未打胶其余几款返工打胶 | R85: 更新SOP，灯头均需打胶 | S85: 否 | T85: 其它 | U85: 宜胜照明3 | V85: 产品二分司 | W85: 46037 | X85: 46037 | Y85: =IF(A85="","",_xlfn.IFS(AND(W85=0,X85=0),"未回复",AND(X85<>0,W85=0),"报错",AND(W85>=NOW(),W85<>0,X85=0),"正常进行中",AND(X85<>0,W85>=X85),"按时关闭",AND(W85<>0,W85<=X85),"延期关闭",AND(X85=0,W85<NOW()),"延期未关闭")) -> 按时关闭 | AA85: =IF(W85="","",YEAR(W85)) -> 2026 | AB85: =IF(W85="","",TEXT(W85,"m")) -> 1 | AC85: =IF(W85="","","W"&WEEKNUM(W85,2)) -> W3
A86: 46030 | B86: =IF(A86="","",YEAR(A86)) -> 2026 | C86: =IF(A86="","",TEXT(A86,"m")) -> 1 | D86: =IF(A86="","","W"&WEEKNUM(A86,2)) -> W2 | E86: P25V004 | F86: HL138C-150W | G86: 俄罗斯482-3 | H86: 宜胜照明3 | K86: 刘晓慧 | L86: 防水不过，客户抽检64,7PCS不过 | M86: 客户验货 | N86: 安规 | O86: 该款因闪灯问题，要求组装完成后长时间老化，内部空气受热膨胀，玻璃密封胶未干形成排气孔 | P86: 过程工艺 | Q86: P25V004及P25V007订单HL138C-150W均需进行返工 | R86: 若需长时间老化需要在打胶前老化或胶水完全固化在进行老化 | S86: 否 | T86: 工艺优化 | U86: 宜胜照明3 | V86: 生产三 | W86: 46037 | X86: 46037 | Y86: =IF(A86="","",_xlfn.IFS(AND(W86=0,X86=0),"未回复",AND(X86<>0,W86=0),"报错",AND(W86>=NOW(),W86<>0,X86=0),"正常进行中",AND(X86<>0,W86>=X86),"按时关闭",AND(W86<>0,W86<=X86),"延期关闭",AND(X86=0,W86<NOW()),"延期未关闭")) -> 按时关闭 | AA86: =IF(W86="","",YEAR(W86)) -> 2026 | AB86: =IF(W86="","",TEXT(W86,"m")) -> 1 | AC86: =IF(W86="","","W"&WEEKNUM(W86,2)) -> W3
A87: 46034 | B87: =IF(A87="","",YEAR(A87)) -> 2026 | C87: =IF(A87="","",TEXT(A87,"m")) -> 1 | D87: =IF(A87="","","W"&WEEKNUM(A87,2)) -> W3 | E87: A225J025-1 | F87: BL212SA-15W2-PIR | G87: 澳大利亚1160 | H87: 宜胜照明3 | K87: 王超 | L87: 客验感应功能抽检20pcs，1pcs感应功能失效，灭灯后再次感应不亮 | M87: 客户验货 | N87: 功能 | O87: 感应器插件反导致感应功能失效，校正感应器插件方向后，感应功能恢复正常，过程及成品抽检未发现异常 | P87: 过程工艺 | Q87: 返工全检感应功能 | R87: 电子：1.插件SOP更新，增加感应器插件方向要求说明； 2.人员培训，作业前由班组长培训插件位置号及方向要求，作业过程定时抽查。 组装：1.测试岗位增加感应功能测试工序，产线100%全检 2.组包SOP更新，增加感应功能测试要求 | S87: 否 | T87: 工艺优化 | U87: 宜胜照明3 | V87: 生产三 | W87: 46035 | X87: 46035 | Y87: =IF(A87="","",_xlfn.IFS(AND(W87=0,X87=0),"未回复",AND(X87<>0,W87=0),"报错",AND(W87>=NOW(),W87<>0,X87=0),"正常进行中",AND(X87<>0,W87>=X87),"按时关闭",AND(W87<>0,W87<=X87),"延期关闭",AND(X87=0,W87<NOW()),"延期未关闭")) -> 按时关闭 | AA87: =IF(W87="","",YEAR(W87)) -> 2026 | AB87: =IF(W87="","",TEXT(W87,"m")) -> 1 | AC87: =IF(W87="","","W"&WEEKNUM(W87,2)) -> W3
A88: 46036 | B88: =IF(A88="","",YEAR(A88)) -> 2026 | C88: =IF(A88="","",TEXT(A88,"m")) -> 1 | D88: =IF(A88="","","W"&WEEKNUM(A88,2)) -> W3 | E88: A225D042-2 | F88: LG172C-WL（带三角支架） | G88: 荷兰146 | H88: 宜胜照明3 | K88: 王超 | L88: 三角支架上产品标贴起翘 | M88: 客户验货 | N88: 外观 | O88: 标贴材质粘性不足 | P88: 包装设计 | Q88: 返工 | R88: 产品经理与业务沟通更换标贴材质，增加粘性 | S88: 否 | T88: 设计变更-优化 | U88: 宜胜照明3 | V88: 产品一分司 | W88: 46038 | X88: 46038 | Y88: =IF(A88="","",_xlfn.IFS(AND(W88=0,X88=0),"未回复",AND(X88<>0,W88=0),"报错",AND(W88>=NOW(),W88<>0,X88=0),"正常进行中",AND(X88<>0,W88>=X88),"按时关闭",AND(W88<>0,W88<=X88),"延期关闭",AND(X88=0,W88<NOW()),"延期未关闭")) -> 按时关闭 | AA88: =IF(W88="","",YEAR(W88)) -> 2026 | AB88: =IF(W88="","",TEXT(W88,"m")) -> 1 | AC88: =IF(W88="","","W"&WEEKNUM(W88,2)) -> W3
A89: 46045 | B89: =IF(A89="","",YEAR(A89)) -> 2026 | C89: =IF(A89="","",TEXT(A89,"m")) -> 1 | D89: =IF(A89="","","W"&WEEKNUM(A89,2)) -> W4 | E89: F625L003 F625L004 | F89: LB066-SA-2.5W12V | G89: 中国台湾082 | H89: 宜胜照明3 | K89: 王超 | L89: 在客验过程中发现壳体针脚处开孔过大，导致针脚晃动 | M89: 客户验货 | N89: 内部 | O89: 设计原因，试产及大货均有提出，产品端回复针脚推力＞10N符合安规要求，且MR11因为玻璃杯成型工艺的限制，下面的两个孔很难改小 | P89: 结构设计 | Q89: 针脚开孔处打UV胶固定 | R89: 因玻璃杯成型工艺限制，开孔很难改小，工艺变更，内部板子上打半透明胶进行固定 | S89: 否 | T89: 工艺优化 | U89: 其它事业部 | V89: 富沃特科技产品三分司 | W89: 46056 | X89: 46056 | Y89: =IF(A89="","",_xlfn.IFS(AND(W89=0,X89=0),"未回复",AND(X89<>0,W89=0),"报错",AND(W89>=NOW(),W89<>0,X89=0),"正常进行中",AND(X89<>0,W89>=X89),"按时关闭",AND(W89<>0,W89<=X89),"延期关闭",AND(X89=0,W89<NOW()),"延期未关闭")) -> 按时关闭 | AA89: =IF(W89="","",YEAR(W89)) -> 2026 | AB89: =IF(W89="","",TEXT(W89,"m")) -> 2 | AC89: =IF(W89="","","W"&WEEKNUM(W89,2)) -> W6
A90: 46050 | B90: =IF(A90="","",YEAR(A90)) -> 2026 | C90: =IF(A90="","",TEXT(A90,"m")) -> 1 | D90: =IF(A90="","","W"&WEEKNUM(A90,2)) -> W5 | E90: A22D040 | F90: WL208壁灯 | G90: 阿根廷089 | H90: 宜胜照明3 | I90: 周春艳 | J90: 邵心妮 | K90: 王超 | L90: 内部灯杯发光面与外部玻璃透光区域移位 | M90: 客户验货 | N90: 功能 | P90: 结构设计 | S90: 否 | Y90: =IF(A90="","",_xlfn.IFS(AND(W90=0,X90=0),"未回复",AND(X90<>0,W90=0),"报错",AND(W90>=NOW(),W90<>0,X90=0),"正常进行中",AND(X90<>0,W90>=X90),"按时关闭",AND(W90<>0,W90<=X90),"延期关闭",AND(X90=0,W90<NOW()),"延期未关闭")) -> 未回复 | AA90: =IF(W90="","",YEAR(W90)) | AB90: =IF(W90="","",TEXT(W90,"m")) | AC90: =IF(W90="","","W"&WEEKNUM(W90,2))
A91: 46052 | B91: =IF(A91="","",YEAR(A91)) -> 2026 | C91: =IF(A91="","",TEXT(A91,"m")) -> 1 | D91: =IF(A91="","","W"&WEEKNUM(A91,2)) -> W5 | E91: M25A022 | F91: EIW 1006 BR | G91: 巴西527 | H91: 宜胜照明1 | K91: 丁亚双 | L91: 订单EIW 1006 BR BR，客验共检测80个psc样本的前面板，发现使用螺丝刀难以打开，过大力度会损坏产品插槽（6件*轻微缺陷），但面板玻璃不会脱落 | M91: 客户验货 | N91: 其它 | O91: 天气转冷，PC材料热胀冷缩，因面盖与中框因型状结构不同， 收缩程度略有不同，导致部分产品配合过紧，拆卸略为困难。 | P91: 其它 | Q91: 对本批次880pcs进行面板拆卸全检，有客户反馈现象产品进行维修更换 | R91: 经研发技术评估，面盖四个搭扣，外侧面修模，修进0.15-0.2mm，避免因热胀冷缩导致部分产品配合过紧，拆卸较困难现象。 | S91: 是 | T91: 设计变更-预防 | U91: 宜胜照明1 | V91: 生产一 | W91: 46053 | X91: 46053 | Y91: =IF(A91="","",_xlfn.IFS(AND(W91=0,X91=0),"未回复",AND(X91<>0,W91=0),"报错",AND(W91>=NOW(),W91<>0,X91=0),"正常进行中",AND(X91<>0,W91>=X91),"按时关闭",AND(W91<>0,W91<=X91),"延期关闭",AND(X91=0,W91<NOW()),"延期未关闭")) -> 按时关闭 | AA91: =IF(W91="","",YEAR(W91)) -> 2026 | AB91: =IF(W91="","",TEXT(W91,"m")) -> 1 | AC91: =IF(W91="","","W"&WEEKNUM(W91,2)) -> W5
A92: 46098 | B92: =IF(A92="","",YEAR(A92)) -> 2026 | C92: =IF(A92="","",TEXT(A92,"m")) -> 3 | D92: =IF(A92="","","W"&WEEKNUM(A92,2)) -> W12 | E92: E25Y056-1 E25Y064-B-1 | F92: ST-LH202-100W3-WF-G1智能控制及传感器 | G92: 墨西哥296 | H92: 宜胜照明1 | K92: 童志海 | L92: 标贴起翘，二次重验不合格 | M92: 客户验货 | N92: 外观 | O92: 1.标贴起翘原因： 车间标签黏贴后边角未按压 2.二次重验不良原因： 未按要求进行全部返工，只是返工了每拖上面几层 | P92: 人员作业 | Q92: 100%按要求执行返工 | R92: 后续订单已跟客户协商激光打印标签信息激光打印 | S92: 是 | T92: 设计变更-预防 | U92: 宜胜照明1 | V92: 生产一 | W92: 46099 | X92: 46099 | Y92: =IF(A92="","",_xlfn.IFS(AND(W92=0,X92=0),"未回复",AND(X92<>0,W92=0),"报错",AND(W92>=NOW(),W92<>0,X92=0),"正常进行中",AND(X92<>0,W92>=X92),"按时关闭",AND(W92<>0,W92<=X92),"延期关闭",AND(X92=0,W92<NOW()),"延期未关闭")) -> 按时关闭 | AA92: =IF(W92="","",YEAR(W92)) -> 2026 | AB92: =IF(W92="","",TEXT(W92,"m")) -> 3 | AC92: =IF(W92="","","W"&WEEKNUM(W92,2)) -> W12
A93: 46104 | B93: =IF(A93="","",YEAR(A93)) -> 2026 | C93: =IF(A93="","",TEXT(A93,"m")) -> 3 | D93: =IF(A93="","","W"&WEEKNUM(A93,2)) -> W13 | E93: F525R002-1 | F93: LB2101C-8.5W2-GK-G1 | G93: 英国0999 | H93: 宜胜照明1 | K93: 王晨 | L93: 订单F625R002 在客验过程中发现4pcs灯不亮 | M93: 客户验货 | N93: 内部 | O93: 发生原因：1pcs端子贴歪，1pcs C3位置少件，1pcs电解电容连锡（电子） 1pcs铆钉松动脱落（组装） 电子：测试仅使用低压通断检测，无带载功率测试，连锡、少件不良无法识别； 组装：铆钉压接设备压力/行程不稳定，导致铆钉松动、脱落 流出原因： 1.产品由手工线转自动线生产，包装前无100%点亮全检，设备按普通球泡调试，无法识别功能不良； 2.规格书功能描述错误模糊“光控功能，每30分钟间隔对环境监测”，生产无判定依据 | P93: 过程工艺 | Q93: 返工 | R93: 1.电子车间增加带载功率测试，筛除少件、连锡 2.端子孔宽度减小0.3mm 防止偏移 3.组装车间校正设备铆钉压接压力/行程，做工位点检，避免铆钉松动脱落 | S93: 否 | T93: 工艺优化 | U93: 宜胜照明1 | V93: 生产一 | W93: 46107 | X93: 46107 | Y93: =IF(A93="","",_xlfn.IFS(AND(W93=0,X93=0),"未回复",AND(X93<>0,W93=0),"报错",AND(W93>=NOW(),W93<>0,X93=0),"正常进行中",AND(X93<>0,W93>=X93),"按时关闭",AND(W93<>0,W93<=X93),"延期关闭",AND(X93=0,W93<NOW()),"延期未关闭")) -> 按时关闭 | AA93: =IF(W93="","",YEAR(W93)) -> 2026 | AB93: =IF(W93="","",TEXT(W93,"m")) -> 3 | AC93: =IF(W93="","","W"&WEEKNUM(W93,2)) -> W13
A94: 46120 | B94: =IF(A94="","",YEAR(A94)) -> 2026 | C94: =IF(A94="","",TEXT(A94,"m")) -> 4 | D94: =IF(A94="","","W"&WEEKNUM(A94,2)) -> W15 | E94: M25A031-1 | F94: EIW 1004 BR_x000b_ | G94: 巴西527 | H94: 宜胜照明1 | I94: 徐赢意 | K94: 丁亚双 | L94: 客验抽测30pcs做单个彩盒跌落（1m/6面），其中2pcs内部电源板L2位置电感脱落 | M94: 客户验货 | N94: 其它 | O94: 1.原选型工字电感仅通过焊锡与绕组/磁芯实现电气连接，无额外机械固定结构，在跌落冲击下，引脚与本体的结合力无法承受瞬时应力，导致引脚从本体脱出。 2.该订单四开产品规格书及合同无相关跌落测试要求，成品及巡检过程未进行相关跌落测试 | P94: 电子设计 | Q94: 1.本批次1000pcs隔离处理（已隔离），禁止出货； 2.对该批次全部返工增加彩盒防护处理； 3.同结构其他批次抽检跌落，结果合格 | R94: 1.该4开结构产品原L2位置工字电感（料号51030200004图1）变更为骨架电感（料号51030300084图2），骨架电感有骨架支撑，可分散冲击力，引脚被骨架牢牢锁死，可满足跌落测试要求 2.规格书变更：4开产品增加外箱跌落测试要求 3.合同变更：验货合同增加外箱及彩盒跌落要求（业务端提供变更后验货合同） | S94: 是 | T94: 设计变更-预防 | U94: 宜胜照明1 | V94: 研发十 | W94: 46123 | X94: 46122 | Y94: =IF(A94="","",_xlfn.IFS(AND(W94=0,X94=0),"未回复",AND(X94<>0,W94=0),"报错",AND(W94>=NOW(),W94<>0,X94=0),"正常进行中",AND(X94<>0,W94>=X94),"按时关闭",AND(W94<>0,W94<=X94),"延期关闭",AND(X94=0,W94<NOW()),"延期未关闭")) -> 按时关闭 | AA94: =IF(W94="","",YEAR(W94)) -> 2026 | AB94: =IF(W94="","",TEXT(W94,"m")) -> 4 | AC94: =IF(W94="","","W"&WEEKNUM(W94,2)) -> W15
A95: 46125 | B95: =IF(A95="","",YEAR(A95)) -> 2026 | C95: =IF(A95="","",TEXT(A95,"m")) -> 4 | D95: =IF(A95="","","W"&WEEKNUM(A95,2)) -> W16 | E95: UWC260074 | F95: BDM8005/8004镜子灯 | G95: 乐愿 | H95: 宜胜照明3 | L95: 底座螺丝与螺帽固定不紧 | M95: 客户验货 | N95: 其它 | O95: 螺丝偏短，余量不足 | P95: 结构设计 | Q95: 目前挑选 | R95: 变更螺丝长度 | S95: 是 | T95: 设计变更-预防 | U95: 宜胜照明2 | V95: 研发三 | W95: 46137 | X95: 46137
A96: 46126 | B96: =IF(A96="","",YEAR(A96)) -> 2026 | C96: =IF(A96="","",TEXT(A96,"m")) -> 4 | D96: =IF(A96="","","W"&WEEKNUM(A96,2)) -> W16 | E96: M26A003-1 | F96: EIW 1006 PT | G96: 巴西527 | H96: 宜胜照明1 | I96: 徐赢意 | K96: 丁亚双 | L96: 订单号:M26A003-1 产品型号：EIW 1006 PT_x000b_批次数量：1400PCS 不良数量： 4pcs 不良问题描述： 1. 1pcs附件包螺丝短缺； 2. 2pcs指示灯偏暗，特定角度开关按钮失效；1pcs开关按钮失效 | M96: 客户验货 | N96: 功能 | O96: 1.指示灯偏暗/开关功能失效 经现场拆机分析，指示灯偏暗，开关功能失效均为导光板贴反导致：导光板虽设计有防呆缺口，但正面外观无明显差异，作业过程出现方向识别偏差，导致导光板贴反 a.导光板贴反，指示灯珠顶在导光板非透光位置，光线无法正常导出，且不能完全贴合，造成指示灯偏暗，且特定角度开关失效； b.因导光板贴反后装配过程受力位移导致开关功能失效 2.附件包少螺丝 包装工位采用称重防错，但现场电子称精度不足，螺丝数量偏差未被及时有效拦截，导致少装流出 | P96: 人员作业 | Q96: 本批次1400pcs产品全部返工： 1.100%全检附件包螺丝数量 2.100%功能全检：开关导通、指示灯亮度，剔除导光板贴反/位移不良 | R96: 永久措施： 1.更换高精度电子称，装完附件包称重合格后放入指定的物料盒中，严格执行称重报警校验流程，异常时立即核对数量，确保防错有效； 2.导光板正面使用记号笔增加目视识别标记（如图红点标记位置），降低识别偏差 预防措施： 1.对装配、包装、测试岗位标准进行再培训与实操确认，详细讲解本次客验不良现象、原因及后续作业过程注意事项 2.巡检加严导光板、附件包的检查与稽核 | S96: 否 | T96: 人员培训 | U96: 宜胜照明1 | V96: 生产一 | W96: 46128 | X96: 46128 | Y96: =IF(A96="","",_xlfn.IFS(AND(W96=0,X96=0),"未回复",AND(X96<>0,W96=0),"报错",AND(W96>=NOW(),W96<>0,X96=0),"正常进行中",AND(X96<>0,W96>=X96),"按时关闭",AND(W96<>0,W96<=X96),"延期关闭",AND(X96=0,W96<NOW()),"延期未关闭")) -> 按时关闭 | AA96: =IF(W96="","",YEAR(W96)) -> 2026 | AB96: =IF(W96="","",TEXT(W96,"m")) -> 4 | AC96: =IF(W96="","","W"&WEEKNUM(W96,2)) -> W16
A97: 46129 | B97: =IF(A97="","",YEAR(A97)) -> 2026 | C97: =IF(A97="","",TEXT(A97,"m")) -> 4 | D97: =IF(A97="","","W"&WEEKNUM(A97,2)) -> W16 | E97: E26Y001-B | F97: PL2803W-45W1P910-312B7F23WA | G97: 墨西哥245-1 | H97: 宜胜照明3 | K97: 童志海 | L97: 1.面板框架短边处有不同程度掉漆现象 2..面板灯背部螺丝扭力测试3PCS，其中一张面板灯6颗螺丝扭力不到0.6N， 3.暗装配件包检查16包，1包少螺丝1颗 4.明装配件包电镀不良比例80%左右 | M97: 客户验货 | N97: 外观 | O97: 1.流水线传送过程摩擦导致 2.规格书及合同无相关要求 3.来料短装 4.来料不良，研发封样也有电镀不良现象 | P97: 其它 | Q97: 掉漆返工，2、3、4让步接收 | R97: 1.产线流水线台面增加缓冲垫防护，夹子增加橡胶防护垫 2.规格书及合同增加相关标准要求，产线管控设备扭矩，制程及成品按要求进行检验 3.供应商改善，产线自检+品质抽检 4.供应商改善，研发重新封样，后续批次来料检验跟踪，不得有电镀不良现象 | S97: 否 | T97: 工艺优化 | U97: 宜胜照明3 | V97: 生产三 | W97: 46135 | X97: 46135 | Y97: =IF(A97="","",_xlfn.IFS(AND(W97=0,X97=0),"未回复",AND(X97<>0,W97=0),"报错",AND(W97>=NOW(),W97<>0,X97=0),"正常进行中",AND(X97<>0,W97>=X97),"按时关闭",AND(W97<>0,W97<=X97),"延期关闭",AND(X97=0,W97<NOW()),"延期未关闭")) -> 按时关闭 | AA97: =IF(W97="","",YEAR(W97)) -> 2026 | AB97: =IF(W97="","",TEXT(W97,"m")) -> 4 | AC97: =IF(W97="","","W"&WEEKNUM(W97,2)) -> W17
A98: 46136 | B98: =IF(A98="","",YEAR(A98)) -> 2026 | C98: =IF(A98="","",TEXT(A98,"m")) -> 4 | D98: =IF(A98="","","W"&WEEKNUM(A98,2)) -> W17 | E98: M26A004-1 | F98: ETW 3001 | G98: 巴西527 | H98: 宜胜照明1 | I98: 徐赢意 | K98: 丁亚双 | L98: 1.APP显示电压 2.PCB版本与检查表不符 | M98: 客户验货 | N98: 功能 | O98: 计量岗位未使用稳压电源进行计量，电压波动偏差导致显示电压偏差 | P98: 过程工艺 | Q98: 使用稳压电源重新计量测试 | R98: 生产采购稳压电源，无稳压电源不得上线生产 | S98: 否 | T98: 工艺优化 | U98: 宜胜照明1 | V98: 生产一 | W98: 46142 | X98: 46142 | Y98: =IF(A98="","",_xlfn.IFS(AND(W98=0,X98=0),"未回复",AND(X98<>0,W98=0),"报错",AND(W98>=NOW(),W98<>0,X98=0),"正常进行中",AND(X98<>0,W98>=X98),"按时关闭",AND(W98<>0,W98<=X98),"延期关闭",AND(X98=0,W98<NOW()),"延期未关闭")) -> 按时关闭 | AA98: =IF(W98="","",YEAR(W98)) -> 2026 | AB98: =IF(W98="","",TEXT(W98,"m")) -> 4 | AC98: =IF(W98="","","W"&WEEKNUM(W98,2)) -> W18
A99: 46134 | B99: =IF(A99="","",YEAR(A99)) -> 2026 | C99: =IF(A99="","",TEXT(A99,"m")) -> 4 | D99: =IF(A99="","","W"&WEEKNUM(A99,2)) -> W17 | E99: A126S033 | F99: LG158C-50W | G99: 中国1674 | H99: 宜胜照明3 | I99: 周梦婷 | K99: 王超 | L99: 支架铆钉生锈 | M99: 客户验货 | N99: 外观 | O99: 来料不良，铆钉压铆后表面塑粉有损伤现象 | P99: 来料不良 | Q99: 本批次让步接收 | R99: 供应商变更铆钉材质 | S99: 是 | T99: 供应商改善 | U99: 计划采购部 | V99: 供方管理组 | W99: 46142 | X99: 46142 | Y99: =IF(A99="","",_xlfn.IFS(AND(W99=0,X99=0),"未回复",AND(X99<>0,W99=0),"报错",AND(W99>=NOW(),W99<>0,X99=0),"正常进行中",AND(X99<>0,W99>=X99),"按时关闭",AND(W99<>0,W99<=X99),"延期关闭",AND(X99=0,W99<NOW()),"延期未关闭")) -> 按时关闭 | AA99: =IF(W99="","",YEAR(W99)) -> 2026 | AB99: =IF(W99="","",TEXT(W99,"m")) -> 4 | AC99: =IF(W99="","","W"&WEEKNUM(W99,2)) -> W18
A100: 46141 | B100: =IF(A100="","",YEAR(A100)) -> 2026 | C100: =IF(A100="","",TEXT(A100,"m")) -> 4 | D100: =IF(A100="","","W"&WEEKNUM(A100,2)) -> W18 | E100: A126S052+055-1 | F100: BL214C-24W2-G1-TDC | G100: 中国1796-欧洲 | H100: 宜胜照明3 | I100: 张美娟 | J100: 邵心妮 | K100: 王超 | L100: 安装支架毛刺 100%；PCB 无丝印版本号；实际安装螺丝规格与TDS不符；产品克重与TDS不符 | M100: 客户验货 | N100: 外观 | O100: 1.毛刺供应商来料不良 2.PCB未设计丝印版本号 3.研发未客户要求配置螺丝规格 4.客户增加电源盒后未与客户沟通同步更新TDS资料 | P100: 其它 | Q100: 毛刺与螺丝返工处理 | R100: 1.毛刺供应商改善 2.PCB无丝印版本号：PCB研发设计图纸未添加版本号丝印设计； 3.安装螺丝规格与TDS不符：研发设计未按客户要求适配安装螺丝； 4.实际产品克重超TDS 上限：按客户要求增加电源盒后，未及时同步变更提供给客户的TDS资料 | S100: 是 | T100: 设计变更-预防 | U100: 宜胜照明3 | V100: 研发一 | W100: 46142 | X100: 46142 | Y100: =IF(A100="","",_xlfn.IFS(AND(W100=0,X100=0),"未回复",AND(X100<>0,W100=0),"报错",AND(W100>=NOW(),W100<>0,X100=0),"正常进行中",AND(X100<>0,W100>=X100),"按时关闭",AND(W100<>0,W100<=X100),"延期关闭",AND(X100=0,W100<NOW()),"延期未关闭")) -> 按时关闭 | AA100: =IF(W100="","",YEAR(W100)) -> 2026 | AB100: =IF(W100="","",TEXT(W100,"m")) -> 4 | AC100: =IF(W100="","","W"&WEEKNUM(W100,2)) -> W18
...

Sheet 工业委外客诉台账
A1: 发生时间 | B1: 年 | C1: 月 | D1: 周 | E1: 订单号 | F1: 产品型号 | G1: 客户 | H1: 事业部 | I1: 委外供应商 | J1: 业务 | K1: 产品 | L1: CQE | M1: 问题描述 | N1: 问题来源 | O1: 问题类别 | P1: 数量 | Q1: 不良率 | R1: 原因分析 | S1: 原因类别 | T1: 临时措施 | U1: 长期措施 | V1: 是否根本解 | W1: 措施类型 | X1: 责任部门 | Y1: 二级部门3
A2: 46034 | B2: =IF(A2="","",YEAR(A2)) -> 2026 | C2: =IF(A2="","",TEXT(A2,"m")) -> 1 | D2: =IF(A2="","","W"&WEEKNUM(A2,2)) -> W3 | E2: F24A002-6 F23A012-6 F23A009-6 | F2: R球泡 | G2: 俄罗斯004 | H2: 宜胜照明1 | I2: 安富 | K2: 谢彭沛 | L2: 刘晓慧 | M2: 订单号：F24A002-6 F23A012-6 F23A009-6 灯泡第一次点亮时就不工作，客户方分析是由于焊锡不良造成的，不良比例较大，客户要求全额索赔（73436.44元）。 | N2: 售后客诉 | O2: 功能 | P2: 30800 | Q2: 5%-12% | R2: 1、R球泡LN端子起翘导致产品供电异常故出现无法点亮现象 2、端子起翘原因为：端子焊盘锡量偏少，锡膏印刷钢网厚度偏薄 | S2: 来料不良 | T2: 委外安富等供应商，目前已倒闭，客诉金额工业承担 | V2: 否 | X2: 宜胜照明1 | Y2: 产品六分司
A3: 46036 | B3: =IF(A3="","",YEAR(A3)) -> 2026 | C3: =IF(A3="","",TEXT(A3,"m")) -> 1 | D3: =IF(A3="","","W"&WEEKNUM(A3,2)) -> W3 | E3: A125S224-1 | F3: MR16 5W 4000K | G3: 中国1796-木林森 | H3: 宜胜照明1 | I3: 佳昊 | L3: 王超 | M3: A125S224-1订单MR16 5W 4000K，3000pcs，客验发现2pcs灯杯不亮 | N3: 客户验货 | O3: 功能 | P3: 3003 | Q3: 0.01 | R3: 1pcs连锡短路电阻损坏 1pcs内部电源板贴红标签，无IC芯片 | S3: 来料不良 | T3: 安排光源11线返工点亮测试，返工不良共计25pcs，不良明细如下： 15pcs贴片电容裂，2pcs电解电容用错（2.7vf400v用错为3.3vf）,2pcs芯片连锡导致芯片坏，6pcs灯珠裂 | V3: 否 | X3: 宜胜照明1 | Y3: 产品六分司
A4: 46106 | B4: =IF(A4="","",YEAR(A4)) -> 2026 | C4: =IF(A4="","",TEXT(A4,"m")) -> 3 | D4: =IF(A4="","","W"&WEEKNUM(A4,2)) -> W13 | E4: L24Y024 | F4: LC2121W-5W | G4: 墨西哥520 | H4: 宜胜照明1 | I4: 安富 | K4: 何海卿 | M4: 订单:L24Y024-1 型号:LC2121W-5W 订单数量：37910pcs 客户反馈不良数量：200pcs 客户寄回不良数量：5pcs 问题描述：输入接触不良，灯不亮 | N4: 售后客诉 | O4: 功能 | P4: 37910 | Q4: 0.0052 | R4: 打点机设备运行过程气压不稳定或钢针磨损，凹点深度不够，输入线接触不良，导致接触不良灯不亮。 | S4: 过程工艺 | T4: 确认不良数量，赔货处理 | U4: 供应商已倒闭 | V4: 否 | X4: 计划采购部 | Y4: 供方管理组
A5: 46155 | B5: =IF(A5="","",YEAR(A5)) -> 2026 | C5: =IF(A5="","",TEXT(A5,"m")) -> 5 | D5: =IF(A5="","","W"&WEEKNUM(A5,2)) -> W20 | E5: W25M175-2 | F5: G45-8W-3000K-E27 | G5: 克罗地亚019 | H5: 宜胜照明1 | I5: 南通瑞特 | L5: 李宁 | M5: 订单:W25M175-2 型号:G45-8W-3000K-E27 客户货号：305-727 订单数量：3000pcs 问题描述：客诉反馈有混灯现象，G45-8W-3000K-E27产品混入G45-4.9W-4000K-E14产品（客户检验305-727款时，发现305-727款彩盒里面装的是305-822的产品） | N5: 售后客诉 | O5: 包装 | P5: 3000 | R5: 经查该款产品于2025年12月23日完工并完成出货检验，检验留底图片无异常，该款混灯应为个别尾数维修后未经过检验直接包装导致混灯 | S5: 人员作业 | T5: 更换正确产品 | U5: 纠正措施：1.维修员修复完成后需填写好维修记录表，如：维修问题点、数量、班组等； 2.班组长拿回维修品后，必须检验确认产品功性能及外观合格后才能流转下到工序； 3.生产小组对所补尾数数量及所有包材类需再次确认信息合同订单BOM一致性 预防措施：1.新员工培训合格后上岗，包含但不限于产品参数如色温、功率、灯头种类（E27/E14等），并定期组织质量基础知识及以质量意识相关培训，避免低级错误发生； 2.尾数单独登记报检，FQC人员核对尾数数量，并执行全检或在正常抽样水平上在加严一级进行检验。 | V5: 否 | W5: 流程优化 | X5: 其它事业部 | Y5: 供方管理组

Sheet 原始缺陷代码
A1: 类别 | B1: 代码 | C1: 缺陷等级 | D1: 缺陷描述 | G1: 类别 | H1: 代码 | I1: 缺陷等级 | J1: 缺陷描述 | M1: 类别 | N1: 代码 | O1: 缺陷等级 | P1: 缺陷描述 | S1: 类别 | T1: 代码 | U1: 缺陷等级 | V1: 缺陷描述 | Y1: 类别 | Z1: 代码 | AA1: 缺陷等级 | AB1: 缺陷描述 | AE1: 类别 | AF1: 代码 | AG1: 缺陷等级 | AH1: 缺陷描述 | AK1: 类别 | AL1: 代码 | AM1: 缺陷等级 | AN1: 缺陷描述
A2: 包装 | B2: 101 | C2: M/C | D2: 缺少附件 | G2: 外观 | H2: 201 | I2: m/M | J2: 划伤 | M2: 内部 | N2: 301 | O2: M | P2: 漏打螺丝 | S2: 功能 | T2: 401 | U2: M | V2: 功率超标 | Y2: 安规 | Z2: 501 | AA2: C | AB2: 内配线芯裸露/破损 | AE2: SMT、DIP | AF2: 601 | AG2: M | AH2: 图纸丝印错误/缺失 | AK2: 其它 | AN2: 其它
B3: 102 | C3: M | D3: 条码问题 | H3: 202 | I3: m/M | J3: 脏污 | N3: 302 | O3: M | P3: 漏装部件 | T3: 402 | U3: M | V3: 异响 | Z3: 502 | AA3: C | AB3: 电源线拉力异常 | AF3: 602 | AG3: M | AH3: 实物丝印错误/缺失
B4: 103 | C4: m/M | D4: 包材破损 | H4: 203 | I4: m | J4: 注塑问题（缩水、料花、流纹、杂点、模印、缺胶、气纹等） | N4: 303 | O4: M | P4: 塑胶异物 | T4: 403 | U4: M | V4: 不通电 | Z4: 503 | AA4: C | AB4: 关键元器件用错/参数规格问题 | AF4: 603 | AH4: 焊盘问题
B5: 104 | C5: m/M | D5: 包材脏污、褶皱、水渍 | H5: 204 | I5: m | J5: 变形 | N5: 304 | O5: C | P5: 金属异物 | T5: 404 | U5: M | V5: 灯不亮 | Z5: 504 | AA5: C | AB5: 电气安全问题（耐压、泄露、接地，爬电距离、电气间隙） | AF5: 604 | AH5: 测试不过
B6: 105 | C6: m | D6: 包装方式有误 | H6: 205 | I6: m | J6: 飞边 | N6: 305 | O6: m/M | P6: 可视部件有污物/黑点 | T6: 405 | U6: M | V6: 灯异常闪烁 | Z6: 505 | AA6: C | AB6: 锋利点
B7: 106 | C7: m/M | D7: 开箱异味 | H7: 206 | I7: m | J7: 色差 | N7: 306 | O7: M | P7: 螺钉未锁到位 | T7: 406 | U7: M | V7: 光参数不符 | Z7: 506 | AA7: C | AB7: 缺少安规标志、标语
B8: 107 | C8: M/C | D8: 漏贴贴纸 | H8: 207 | I8: M | J8: 部件损坏 | N8: 307 | O8: M | P8: 内部件装配不良 | T8: 407 | U8: M | V8: 接触不良（电源线/线路连接） | Z8: 507 | AA8: C | AB8: EMC测试不过
B9: 108 | C9: M | D9: 包材内容与资料不符 | H9: 208 | I9: m/M | J9: 五金件变形、凸包 | N9: 308 | O9: M | P9: 零部件用错 | T9: 408 | U9: M | V9: 开关、按键、旋钮失灵（功能性） | Z9: 508 | AA9: C | AB9: IP等级不过 | AF9: 600 | AH9: 其它SMT&DIP
B10: 109 | C10: M | D10: 粘贴/覆膜不良 | H10: 209 | I10: M | J10: 五金件脱焊 | N10: 309 | O10: M | P10: 布线不良、夹线 | T10: 409 | U10: M | V10: 开关、按键、旋钮卡涩/卡死 | Z10: 509 | AA10: C | AB10: IK等级不过
B11: 110 | C11: m | D11: 包材印刷不良 | H11: 210 | I11: m/M | J11: 五金件氧化/生锈/砂眼 | N11: 310 | O11: M | P11: 配合干涉 | T11: 410 | U11: M
B12: 111 | C12: M | D12: 包材/配件用错 | H12: 211 | I12: m/M | J12: 五金件涂层脱落、喷漆/电镀等不良 | N12: 301 | O12: M | P12: 反光罩不正/过大过小 | T12: 411 | U12: M
B13: 100 | D13: 其它包装 | H13: 212 | I13: m/M | J13: 塑胶件喷漆/电镀不良 | T13: 412 | U13: M | V13: 程序错误/乱码 | Z13: 500 | AB13: 其它安规
H14: 213 | I14: m/M | J14: 配合间隙 | N14: 300 | P14: 其它内部 | T14: 413 | U14: M | V14: 显示异常
H15: 214 | I15: m/M | J15: 配合台阶 | T15: 414 | U15: M | V15: 感应开关失效
H16: 215 | I16: m/M | J16: 镭雕、烫金、丝印不良 | T16: 415 | U16: M
H17: 216 | I17: m | J17: 夹膜 | T17: 416 | U17: M
H18: 217 | I18: m | J18: 溢胶 | T18: 417 | U18: M
H19: 218 | I19: C | J19: 头发 | T19: 418 | U19: M
H20: 219 | I20: C | J20: 血渍 | T20: 419 | U20: M
H21: 220 | T21: 420 | U21: M
H22: 221 | T22: 421 | U22: M
H23: 200 | J23: 其它外观 | T23: 400 | U23: M | V23: 其它功能

Sheet 数据源
B1: 问题分类 | D1: 发现环节 | E1: 试产 | H1: 包装 | I1: 外观 | J1: 内部 | K1: 功能 | L1: 安规 | M1: SMT、DIP | N1: 其它 | S1: 原因分类 | X1: 责任部门 | Z1: 宜胜照明1 | AA1: 宜胜照明2 | AB1: 宜胜照明3 | AC1: 计划采购部 | AD1: 技术质量部 | AE1: 其它事业部 | AG1: 来料 | AJ1: 是 | AK1: 否 | AL1: 不涉及 | AN1: 问题来源 | AQ1: 设计变更-预防 | AT1: 粘贴为值 | AU1: 组装困难 | BC1: 转置 | BD1: 组装困难 | BE1: 外观配合 | BF1: PCB丝印问题 | BG1: 焊盘问题 | BH1: BOM错误/漏挂/多挂 | BI1: 实物与资料不符 | BJ1: 拼板问题 | BK1: 资料错误 | BL1: 优化建议 | BM1: 贴片干涉 | BN1: 其它 | BO1: 贴片制程 | BP1: 注塑缺陷 | BQ1: 测试问题 | BR1: 影响插件 | BS1: 来料不良 | BT1: 老化不良 | BU1: 温升过高 | BV1: 需求变更 | BW1: 装配不良 | CD1: 转置 | CE1: 设计变更-预防 | CF1: 标准升级 | CG1: 防呆防错 | CH1: 自动化 | CI1: 其它 | CJ1: 人员培训 | CK1: 流程优化 | CL1: 工艺优化 | CM1: 模具维修 | CN1: 克服生产 | CO1: 供应商改善 | CP1: 设备维修 | CQ1: 存储/防护升级 | CR1: 纠错 | CS1: 设计变更-优化 | CT1: 未回复 | CU1: 不涉及
B2: 包装 | D2: 设计评审 | E2: SMT | H2: =IF(原始缺陷代码!D2=""," ",原始缺陷代码!D2) -> 缺少附件 | I2: =IF(原始缺陷代码!J2=""," ",原始缺陷代码!J2) -> 划伤 | J2: =IF(原始缺陷代码!P2=""," ",原始缺陷代码!P2) -> 漏打螺丝 | K2: =IF(原始缺陷代码!V2=""," ",原始缺陷代码!V2) -> 功率超标 | L2: =IF(原始缺陷代码!AB2=""," ",原始缺陷代码!AB2) -> 内配线芯裸露/破损 | M2: =IF(原始缺陷代码!AH2=""," ",原始缺陷代码!AH2) -> 图纸丝印错误/缺失 | N2: =IF(原始缺陷代码!AN2=""," ",原始缺陷代码!AN2) -> 其它 | S2: 人员作业 | X2: 宜胜照明1 | Z2: 研发六 | AA2: 研发三 | AB2: 研发一 | AC2: 计划物流组 | AD2: 技术支持组 | AE2: 优耐特国贸 | AG2: 五金件 | AJ2: 设计变更-预防 | AK2: 人员培训 | AL2: 不涉及 | AN2: 售后客诉 | AQ2: 标准升级 | AU2: 外观配合
B3: 外观 | D3: 手板验证 | E3: DIP | H3: =IF(原始缺陷代码!D3=""," ",原始缺陷代码!D3) -> 条码问题 | I3: =IF(原始缺陷代码!J3=""," ",原始缺陷代码!J3) -> 脏污 | J3: =IF(原始缺陷代码!P3=""," ",原始缺陷代码!P3) -> 漏装部件 | K3: =IF(原始缺陷代码!V3=""," ",原始缺陷代码!V3) -> 异响 | L3: =IF(原始缺陷代码!AB3=""," ",原始缺陷代码!AB3) -> 电源线拉力异常 | M3: =IF(原始缺陷代码!AH3=""," ",原始缺陷代码!AH3) -> 实物丝印错误/缺失 | N3: =IF(原始缺陷代码!AN3=""," ",原始缺陷代码!AN3) | S3: 过程工艺 | X3: 宜胜照明2 | Z3: 研发十 | AA3: 研发五 | AB3: 研发二 | AC3: 供方管理组 | AD3: 质量管理组 | AE3: 富沃特国贸 | AG3: 注塑件 | AJ3: 标准升级 | AK3: 流程优化 | AN3: 客户验货 | AQ3: 防呆防错 | AU3: PCB丝印问题
B4: 内部 | D4: 终样测试 | E4: 成品组装 | H4: =IF(原始缺陷代码!D4=""," ",原始缺陷代码!D4) -> 包材破损 | I4: =IF(原始缺陷代码!J4=""," ",原始缺陷代码!J4) -> 注塑问题（缩水、料花、流纹、杂点、模印、缺胶、气纹等） | J4: =IF(原始缺陷代码!P4=""," ",原始缺陷代码!P4) -> 塑胶异物 | K4: =IF(原始缺陷代码!V4=""," ",原始缺陷代码!V4) -> 不通电 | L4: =IF(原始缺陷代码!AB4=""," ",原始缺陷代码!AB4) -> 关键元器件用错/参数规格问题 | M4: =IF(原始缺陷代码!AH4=""," ",原始缺陷代码!AH4) -> 焊盘问题 | N4: =IF(原始缺陷代码!AN4=""," ",原始缺陷代码!AN4) | S4: 资料错误 | X4: 宜胜照明3 | Z4: 生产一 | AA4: 研发九 | AB4: 生产三 | AE4: 快仓科技司 | AG4: 电子料 | AJ4: 防呆防错 | AK4: 工艺优化 | AN4: 样品确认 | AQ4: 自动化 | AU4: 焊盘问题
B5: 功能 | D5: 可靠性验证 | E5: 测试 | H5: =IF(原始缺陷代码!D5=""," ",原始缺陷代码!D5) -> 包材脏污、褶皱、水渍 | I5: =IF(原始缺陷代码!J5=""," ",原始缺陷代码!J5) -> 变形 | J5: =IF(原始缺陷代码!P5=""," ",原始缺陷代码!P5) -> 金属异物 | K5: =IF(原始缺陷代码!V5=""," ",原始缺陷代码!V5) -> 灯不亮 | L5: =IF(原始缺陷代码!AB5=""," ",原始缺陷代码!AB5) -> 电气安全问题（耐压、泄露、接地，爬电距离、电气间隙） | M5: =IF(原始缺陷代码!AH5=""," ",原始缺陷代码!AH5) -> 测试不过 | N5: =IF(原始缺陷代码!AN5=""," ",原始缺陷代码!AN5) | S5: 来料不良 | X5: 计划采购部 | AA5: 生产二 | AG5: 机电料 | AJ5: 自动化 | AK5: 模具维修 | AN5: FQC抽检 | AQ5: 其它 | AU5: BOM错误/漏挂/多挂
B6: 安规 | D6: 试产 | E6: QC检验 | H6: =IF(原始缺陷代码!D6=""," ",原始缺陷代码!D6) -> 包装方式有误 | I6: =IF(原始缺陷代码!J6=""," ",原始缺陷代码!J6) -> 飞边 | J6: =IF(原始缺陷代码!P6=""," ",原始缺陷代码!P6) -> 可视部件有污物/黑点 | K6: =IF(原始缺陷代码!V6=""," ",原始缺陷代码!V6) -> 灯异常闪烁 | L6: =IF(原始缺陷代码!AB6=""," ",原始缺陷代码!AB6) -> 锋利点 | M6: =IF(原始缺陷代码!AH6=""," ",原始缺陷代码!AH6) | N6: =IF(原始缺陷代码!AN6=""," ",原始缺陷代码!AN6) | S6: 结构设计 | X6: 技术质量部 | AG6: 包材料 | AJ6: 其它 | AK6: 克服生产 | AN6: IPQC巡检 | AQ6: 人员培训 | AU6: 实物与资料不符
B7: 其它 | D7: 量产 | H7: =IF(原始缺陷代码!D7=""," ",原始缺陷代码!D7) -> 开箱异味 | I7: =IF(原始缺陷代码!J7=""," ",原始缺陷代码!J7) -> 色差 | J7: =IF(原始缺陷代码!P7=""," ",原始缺陷代码!P7) -> 螺钉未锁到位 | K7: =IF(原始缺陷代码!V7=""," ",原始缺陷代码!V7) -> 光参数不符 | L7: =IF(原始缺陷代码!AB7=""," ",原始缺陷代码!AB7) -> 缺少安规标志、标语 | M7: =IF(原始缺陷代码!AH7=""," ",原始缺陷代码!AH7) | N7: =IF(原始缺陷代码!AN7=""," ",原始缺陷代码!AN7) | S7: 电子设计 | X7: 其它事业部 | AG7: 安规料 | AK7: 供应商改善 | AN7: 设计评审 | AQ7: 流程优化 | AU7: 拼板问题
H8: =IF(原始缺陷代码!D8=""," ",原始缺陷代码!D8) -> 漏贴贴纸 | I8: =IF(原始缺陷代码!J8=""," ",原始缺陷代码!J8) -> 部件损坏 | J8: =IF(原始缺陷代码!P8=""," ",原始缺陷代码!P8) -> 内部件装配不良 | K8: =IF(原始缺陷代码!V8=""," ",原始缺陷代码!V8) -> 接触不良（电源线/线路连接） | L8: =IF(原始缺陷代码!AB8=""," ",原始缺陷代码!AB8) -> EMC测试不过 | M8: =IF(原始缺陷代码!AH8=""," ",原始缺陷代码!AH8) | N8: =IF(原始缺陷代码!AN8=""," ",原始缺陷代码!AN8) | S8: 包装设计 | AG8: 硅胶/橡胶 | AK8: 设备维修 | AN8: 手板验证 | AQ8: 工艺优化 | AU8: 资料错误
H9: =IF(原始缺陷代码!D9=""," ",原始缺陷代码!D9) -> 包材内容与资料不符 | I9: =IF(原始缺陷代码!J9=""," ",原始缺陷代码!J9) -> 五金件变形、凸包 | J9: =IF(原始缺陷代码!P9=""," ",原始缺陷代码!P9) -> 零部件用错 | K9: =IF(原始缺陷代码!V9=""," ",原始缺陷代码!V9) -> 开关、按键、旋钮失灵（功能性） | L9: =IF(原始缺陷代码!AB9=""," ",原始缺陷代码!AB9) -> IP等级不过 | M9: =IF(原始缺陷代码!AH9=""," ",原始缺陷代码!AH9) -> 其它SMT&DIP | N9: =IF(原始缺陷代码!AN9=""," ",原始缺陷代码!AN9) | S9: 软件设计 | AG9: 辅料 | AK9: 存储/防护升级 | AN9: 终样测试 | AQ9: 模具维修 | AU9: 优化建议
H10: =IF(原始缺陷代码!D10=""," ",原始缺陷代码!D10) -> 粘贴/覆膜不良 | I10: =IF(原始缺陷代码!J10=""," ",原始缺陷代码!J10) -> 五金件脱焊 | J10: =IF(原始缺陷代码!P10=""," ",原始缺陷代码!P10) -> 布线不良、夹线 | K10: =IF(原始缺陷代码!V10=""," ",原始缺陷代码!V10) -> 开关、按键、旋钮卡涩/卡死 | L10: =IF(原始缺陷代码!AB10=""," ",原始缺陷代码!AB10) -> IK等级不过 | M10: =IF(原始缺陷代码!AH10=""," ",原始缺陷代码!AH10) | N10: =IF(原始缺陷代码!AN10=""," ",原始缺陷代码!AN10) | S10: 设备问题 | AG10: 其它 | AK10: 纠错 | AN10: 可靠性验证 | AQ10: 克服生产 | AU10: 贴片干涉
H11: =IF(原始缺陷代码!D11=""," ",原始缺陷代码!D11) -> 包材印刷不良 | I11: =IF(原始缺陷代码!J11=""," ",原始缺陷代码!J11) -> 五金件氧化/生锈/砂眼 | J11: =IF(原始缺陷代码!P11=""," ",原始缺陷代码!P11) -> 配合干涉 | K11: =IF(原始缺陷代码!V11=""," ",原始缺陷代码!V11) | L11: =IF(原始缺陷代码!AB11=""," ",原始缺陷代码!AB11) | M11: =IF(原始缺陷代码!AH11=""," ",原始缺陷代码!AH11) | N11: =IF(原始缺陷代码!AN11=""," ",原始缺陷代码!AN11) | S11: 其它 | AK11: 设计变更-优化 | AN11: 试产 | AQ11: 供应商改善 | AU11: 其它
H12: =IF(原始缺陷代码!D12=""," ",原始缺陷代码!D12) -> 包材/配件用错 | I12: =IF(原始缺陷代码!J12=""," ",原始缺陷代码!J12) -> 五金件涂层脱落、喷漆/电镀等不良 | J12: =IF(原始缺陷代码!P12=""," ",原始缺陷代码!P12) -> 反光罩不正/过大过小 | K12: =IF(原始缺陷代码!V12=""," ",原始缺陷代码!V12) | L12: =IF(原始缺陷代码!AB12=""," ",原始缺陷代码!AB12) | M12: =IF(原始缺陷代码!AH12=""," ",原始缺陷代码!AH12) | N12: =IF(原始缺陷代码!AN12=""," ",原始缺陷代码!AN12) | AK12: 未回复 | AQ12: 设备维修 | AU12: 贴片制程
H13: =IF(原始缺陷代码!D13=""," ",原始缺陷代码!D13) -> 其它包装 | I13: =IF(原始缺陷代码!J13=""," ",原始缺陷代码!J13) -> 塑胶件喷漆/电镀不良 | J13: =IF(原始缺陷代码!P13=""," ",原始缺陷代码!P13) | K13: =IF(原始缺陷代码!V13=""," ",原始缺陷代码!V13) -> 程序错误/乱码 | L13: =IF(原始缺陷代码!AB13=""," ",原始缺陷代码!AB13) -> 其它安规 | M13: =IF(原始缺陷代码!AH13=""," ",原始缺陷代码!AH13) | N13: =IF(原始缺陷代码!AN13=""," ",原始缺陷代码!AN13) | AK13: 其它 | AQ13: 存储/防护升级 | AU13: 注塑缺陷
H14: =IF(原始缺陷代码!D14=""," ",原始缺陷代码!D14) | I14: =IF(原始缺陷代码!J14=""," ",原始缺陷代码!J14) -> 配合间隙 | J14: =IF(原始缺陷代码!P14=""," ",原始缺陷代码!P14) -> 其它内部 | K14: =IF(原始缺陷代码!V14=""," ",原始缺陷代码!V14) -> 显示异常 | L14: =IF(原始缺陷代码!AB14=""," ",原始缺陷代码!AB14) | M14: =IF(原始缺陷代码!AH14=""," ",原始缺陷代码!AH14) | N14: =IF(原始缺陷代码!AN14=""," ",原始缺陷代码!AN14) | AQ14: 纠错 | AU14: 测试问题
H15: =IF(原始缺陷代码!D15=""," ",原始缺陷代码!D15) | I15: =IF(原始缺陷代码!J15=""," ",原始缺陷代码!J15) -> 配合台阶 | J15: =IF(原始缺陷代码!P15=""," ",原始缺陷代码!P15) | K15: =IF(原始缺陷代码!V15=""," ",原始缺陷代码!V15) -> 感应开关失效 | L15: =IF(原始缺陷代码!AB15=""," ",原始缺陷代码!AB15) | M15: =IF(原始缺陷代码!AH15=""," ",原始缺陷代码!AH15) | N15: =IF(原始缺陷代码!AN15=""," ",原始缺陷代码!AN15) | AQ15: 设计变更-优化 | AU15: 影响插件
H16: =IF(原始缺陷代码!D16=""," ",原始缺陷代码!D16) | I16: =IF(原始缺陷代码!J16=""," ",原始缺陷代码!J16) -> 镭雕、烫金、丝印不良 | J16: =IF(原始缺陷代码!P16=""," ",原始缺陷代码!P16) | K16: =IF(原始缺陷代码!V16=""," ",原始缺陷代码!V16) | L16: =IF(原始缺陷代码!AB16=""," ",原始缺陷代码!AB16) | M16: =IF(原始缺陷代码!AH16=""," ",原始缺陷代码!AH16) | N16: =IF(原始缺陷代码!AN16=""," ",原始缺陷代码!AN16) | AQ16: 其它 | AU16: 来料不良
H17: =IF(原始缺陷代码!D17=""," ",原始缺陷代码!D17) | I17: =IF(原始缺陷代码!J17=""," ",原始缺陷代码!J17) -> 夹膜 | J17: =IF(原始缺陷代码!P17=""," ",原始缺陷代码!P17) | K17: =IF(原始缺陷代码!V17=""," ",原始缺陷代码!V17) | L17: =IF(原始缺陷代码!AB17=""," ",原始缺陷代码!AB17) | M17: =IF(原始缺陷代码!AH17=""," ",原始缺陷代码!AH17) | N17: =IF(原始缺陷代码!AN17=""," ",原始缺陷代码!AN17) | AQ17: 不涉及 | AU17: 老化不良
H18: =IF(原始缺陷代码!D18=""," ",原始缺陷代码!D18) | I18: =IF(原始缺陷代码!J18=""," ",原始缺陷代码!J18) -> 溢胶 | J18: =IF(原始缺陷代码!P18=""," ",原始缺陷代码!P18) | K18: =IF(原始缺陷代码!V18=""," ",原始缺陷代码!V18) | L18: =IF(原始缺陷代码!AB18=""," ",原始缺陷代码!AB18) | M18: =IF(原始缺陷代码!AH18=""," ",原始缺陷代码!AH18) | N18: =IF(原始缺陷代码!AN18=""," ",原始缺陷代码!AN18) | AU18: 温升过高
H19: =IF(原始缺陷代码!D19=""," ",原始缺陷代码!D19) | I19: =IF(原始缺陷代码!J19=""," ",原始缺陷代码!J19) -> 头发 | J19: =IF(原始缺陷代码!P19=""," ",原始缺陷代码!P19) | K19: =IF(原始缺陷代码!V19=""," ",原始缺陷代码!V19) | L19: =IF(原始缺陷代码!AB19=""," ",原始缺陷代码!AB19) | M19: =IF(原始缺陷代码!AH19=""," ",原始缺陷代码!AH19) | N19: =IF(原始缺陷代码!AN19=""," ",原始缺陷代码!AN19) | AU19: 需求变更
H20: =IF(原始缺陷代码!D20=""," ",原始缺陷代码!D20) | I20: =IF(原始缺陷代码!J20=""," ",原始缺陷代码!J20) -> 血渍 | J20: =IF(原始缺陷代码!P20=""," ",原始缺陷代码!P20) | K20: =IF(原始缺陷代码!V20=""," ",原始缺陷代码!V20) | L20: =IF(原始缺陷代码!AB20=""," ",原始缺陷代码!AB20) | M20: =IF(原始缺陷代码!AH20=""," ",原始缺陷代码!AH20) | N20: =IF(原始缺陷代码!AN20=""," ",原始缺陷代码!AN20) | AU20: 装配不良
H21: =IF(原始缺陷代码!D21=""," ",原始缺陷代码!D21) | I21: =IF(原始缺陷代码!J21=""," ",原始缺陷代码!J21) | J21: =IF(原始缺陷代码!P21=""," ",原始缺陷代码!P21) | K21: =IF(原始缺陷代码!V21=""," ",原始缺陷代码!V21) | L21: =IF(原始缺陷代码!AB21=""," ",原始缺陷代码!AB21) | M21: =IF(原始缺陷代码!AH21=""," ",原始缺陷代码!AH21) | N21: =IF(原始缺陷代码!AN21=""," ",原始缺陷代码!AN21)
H22: =IF(原始缺陷代码!D22=""," ",原始缺陷代码!D22) | I22: =IF(原始缺陷代码!J22=""," ",原始缺陷代码!J22) | J22: =IF(原始缺陷代码!P22=""," ",原始缺陷代码!P22) | K22: =IF(原始缺陷代码!V22=""," ",原始缺陷代码!V22) | L22: =IF(原始缺陷代码!AB22=""," ",原始缺陷代码!AB22) | M22: =IF(原始缺陷代码!AH22=""," ",原始缺陷代码!AH22) | N22: =IF(原始缺陷代码!AN22=""," ",原始缺陷代码!AN22)
H23: =IF(原始缺陷代码!D23=""," ",原始缺陷代码!D23) | I23: =IF(原始缺陷代码!J23=""," ",原始缺陷代码!J23) -> 其它外观 | J23: =IF(原始缺陷代码!P23=""," ",原始缺陷代码!P23) | K23: =IF(原始缺陷代码!V23=""," ",原始缺陷代码!V23) -> 其它功能 | L23: =IF(原始缺陷代码!AB23=""," ",原始缺陷代码!AB23) | M23: =IF(原始缺陷代码!AH23=""," ",原始缺陷代码!AH23) | N23: =IF(原始缺陷代码!AN23=""," ",原始缺陷代码!AN23)
H24: =IF(原始缺陷代码!D24=""," ",原始缺陷代码!D24) | I24: =IF(原始缺陷代码!J24=""," ",原始缺陷代码!J24) | J24: =IF(原始缺陷代码!P24=""," ",原始缺陷代码!P24) | K24: =IF(原始缺陷代码!V24=""," ",原始缺陷代码!V24) | L24: =IF(原始缺陷代码!AB24=""," ",原始缺陷代码!AB24) | M24: =IF(原始缺陷代码!AH24=""," ",原始缺陷代码!AH24) | N24: =IF(原始缺陷代码!AN24=""," ",原始缺陷代码!AN24)
